{
  "filename": "saunier-duval-themaplus-condens-notice-installateur-2012-09-291158.pdf",
  "text": "\n\nTHEMAPLUS CONDENS\nF 25\nF 30\nF 35\ncondens\nManuel d’installation\n\n\n\n- 1 -\nINTRODUCTION\n1 Guide d’instructions .....................................................................................................................3\n1.1 Documentation produit .......................................................................................3\n1.2 Documents associés  ...........................................................................................3\n1.3 Explication des symboles ....................................................................................3\n2 Description de l’appareil ...............................................................................................................3\n2.1 Dispositifs de sécurité  ........................................................................................3\n2.2 Plaque signalétique ............................................................................................4\n2.3 Classe de gaz  .....................................................................................................4\n2.4 Réglementation et dispositions législatives ..........................................................4\n2.5 Schéma hydraulique  ..........................................................................................5\n3 Consignes de sécurité et réglementations ......................................................................................6\n3.1 Consignes de sécurité .........................................................................................6\n3.2 Réglementations   ...............................................................................................6\n4 Recyclage ....................................................................................................................................7\n4.1 Appareil .............................................................................................................7\n4.2 Emballage ..........................................................................................................7\nINSTALLATION\n5 Emplacement de l’appareil ............................................................................................................8\n5.1 Emplacement ......................................................................................................8\n5.2 Accessibilité .......................................................................................................8\n6 Installation de l’appareil  ..............................................................................................................8\n6.1 Liste du matériel livré ..........................................................................................8\n6.2 Recommandations avant installation ....................................................................9\n6.3 Dimensions ......................................................................................................10\n6.4 Montage   .........................................................................................................10\n7 Connexion hydraulique ...............................................................................................................11\n7.1 Raccordement gaz et eau ...................................................................................11\n7.2 Raccordement du récupérateur de condensats ....................................................12\n8 Évacuation des gaz de combustion ..............................................................................................12\n8.1 Réglementation ................................................................................................12\n8.2 Description de la configuration d’évacuation des gaz de combustion ....................14\n9 Connexion électrique ..................................................................................................................18\n9.1 Accès au tableau principal .................................................................................18\n9.2 Carte principale ................................................................................................18\n9.3 Accessoires externes .........................................................................................18\n9.4 Schéma électrique ............................................................................................19\n10 Mise en service  .........................................................................................................................20\n10.1 Première mise en fonctionnement ......................................................................20\n10.2 Remplissage de l’installation de chauffage .........................................................20\n10.3 Remplissage du circuit d’eau chaude sanitaire ....................................................20\n10.4 Remise en pression du système .........................................................................20\n10.5 Débits de gaz ....................................................................................................21\n10.6 Test du système de chauffage ............................................................................21\n10.7 Test du système d'eau chaude sanitaire ..............................................................21\n10.8 Finalisation ......................................................................................................21\n11 Réglages spécifiques  .................................................................................................................21\n11.1 Réglage du circuit de chauffage..........................................................................21\n11.2 Réglages techniques de l’appareil et liste des paramètres ...................................22\n11.3 Mesure du CO2 .................................................................................................25\n11.4 Nouvelle vérification et remise en fonctionnement ..............................................25\n12 Informations utilisateur ..............................................................................................................25\nTABLE DES MATIÈRES\nFR\n\n- 2 -\nMAINTENANCE\n13 Dépannage ................................................................................................................................26\n13.1 Diagnostic de pannes ........................................................................................26\n13.2 Historique des codes défauts .............................................................................26\n13.3 Codes défauts ...................................................................................................27\n14 Changement de gaz ....................................................................................................................28\n14.1 Réglages ..........................................................................................................28\n14.2 Redémarrage et nouvelle vérification avant mise en fonctionnement ....................29\n15 Vidange  ....................................................................................................................................29\n15.1 Circuit de chauffage  ..........................................................................................29\n15.2 Circuit d’eau chaude sanitaire   ..........................................................................29\n16 Maintenance ..............................................................................................................................29\n16.1 Maintenance annuelle .......................................................................................29\n16.2 Démontage de la façade avant ...........................................................................30\n16.3 Démontage du silencieux ..................................................................................30\n16.4 Vase d'expansion ..............................................................................................30\n16.5 Bloc hydraulique ...............................................................................................31\n16.6 Bloc de combustion ...........................................................................................33\n16.7 Remplacement du câble d'alimentation ..............................................................34\n17 Pièces de rechange ....................................................................................................................34\nDONNÉES TECHNIQUES\n18 Données techniques ...................................................................................................................35\nTABLE DES MATIÈRES\nFR\n\n0020130774_02 - 09/12 - Saunier Duval\n- 3 -\nINTRODUCTION\nFR\nINTRODUCTION\n1 Guide d’instructions\n1.1 Documentation produit\nLe manuel fait partie intégrante de l’appareil et doit être remis \nà l’utilisateur lorsque l’appareil est installé, conformément aux \nréglementations en vigueur.\n•\tLisez ce manuel attentivement afin de comprendre l’intégralité \ndes informations et de garantir une installation, une utilisation \net un entretien en toute sécurité. Nous déclinons toute \nresponsabilité en cas de dommages occasionnés par le non-\nrespect des consignes figurant dans le présent manuel.\n1.2 Documents associés \n -1 notice d'emploi\n -1 magnet\n -1 carte \"Installateur confiance\"\n -1 carte de \"Demande de garantie\"\n -2 étiquettes de changement de gaz\ni\nLa demande de garantie est à remettre au technicien \nde la Station Technique Agréée lors de la mise en \nservice de l’appareil.\n1.3 Explication des symboles\na\nDANGER : Risque de blessure corporelle.\ne\nDANGER : Risque de choc électrique.\nb\nATTENTION : Risque de dégradation de l’appareil ou \nde son environnement.\ni\nIMPORTANT : Information utile.\n2 Description de l’appareil\n2.1 Dispositifs de sécurité \n2.1.1 Sécurité de surchauffe\nL'appareil est conçu pour identifier les possibles cas de \nsurchauffe et pour s'arrêter avant qu'une surchauffe se produise.\n2.1.2 Soupape de sécurité\nUne soupape de sécurité chauffage et une soupape de sécurité \nsanitaire sont installées sur cet appareil.\n -La soupape de sécurité chauffage s'ouvre dès que la pression \ndans le circuit chauffage dépasse 3 bar.\n -La soupape de sécurité sanitaire s'ouvre dès que la pression \ndans le circuit sanitaire dépasse 10 bar.\n2.1.3 Protection de l'appareil contre le gel\nLe système de protection contre le gel commande la mise \nen fonctionnement de la pompe de l'appareil dès lors que la \ntempérature dans le circuit de chauffage descend en dessous \nde 12°C. La pompe s’arrête dès que la température de l’eau \ncontenue dans le circuit de chauffage atteint 15°C. Si la \ntempérature dans le circuit de chauffage descend en dessous de \n7°C, le brûleur s’allume et fonctionne tant que cette température \nest inférieure à 35°C.\nLe dispositif de protection contre le gel est actif lorsque l'appareil \nest allumé.\nLa protection de l’installation contre le gel ne peut être garantie \nuniquement par l'appareil. Un thermostat d’ambiance est \nnécessaire pour contrôler la température de l’installation.\nb\nATTENTION : Votre circuit d'eau sanitaire (froide ou \nchaude) n'est pas protégé par la chaudière.\n2.1.4 Evacuation des condensats\nPendant les périodes de gel, il est possible que de la glace se \nforme dans le tuyau d'évacuation des condensats s'il est situé à \nl'extérieur de l'habitation. Dans ce cas, un dispositif de sécurité \narrête l'appareil.\n\n0020130774_02 - 09/12 - Saunier Duval\n- 4 -\nINTRODUCTION\nFR\n2.2 Plaque signalétique\nLa plaque signalétique indique le pays où l’appareil doit être \ninstallé.\nEmplacement de la plaque signalétique :\n1\nLégende\n1    Plaque signalétique\nLa plaque signalétique comporte les éléments suivants :\n -Le nom du fabricant\n -Le pays de destination\n -Le nom commercial de l'appareil et son numéro de série\n -Les types d'installation de ventouse autorisés\n -Le code produit\n -La catégorie de gaz de l'appareil\n -La nature, le groupe et la pression du gaz réglé en usine \n -Le débit spécifique (D) \n -La pression maximale de service du circuit chauffage (PMS) \n -La pression maximale de service du circuit sanitaire (PMW) \n -La classe NOx de l'appareil\n -La nature et la tension d'alimentation\n -La puissance maximale absorbée\n -L'indice de protection électrique\n -Le débit calorifique minimal et maximal (Q)\n -La puissance utile minimale et maximale (P)\n -Le numéro et le logo CE\na\nL’appareil doit impérativement être raccordé au(x) \ntype(s) de gaz indiqué(s) sur la plaque signalétique.\n2.3 Classe de gaz \nCette chaudière est dédiée pour fonctionner uniquement aux G20 \nou G31, mais elle peut être adaptée pour être raccordée aux G20, \nG25 et G31.\n•\tConsultez la plaque signalétique pour connaître le type de gaz \npour lequel l'appareil a été réglé en usine.\nGaz réglé en usineChangements de gaz possibles\nG20G25, G31\nG31G20, G25\n•\tPour adapter l'appareil à un autre type de gaz, reportez-vous \nau chapitre \"Changement de gaz\".\n2.4 Réglementation et dispositions législatives\nMarquage CE\nLe marquage CE indique que les appareils décrits dans le présent \nmanuel sont conformes aux directives suivantes :\n -Directive Européenne n°2009-142 relative aux appareils à gaz\n -Directive Européenne n°2004-108 du Parlement Européen et \ndu Conseil relative à la compatibilité électromagnétique\n -Directive Européenne n°2006-95 du Parlement Européen et du \nConseil relative à la basse tension\n -Directive Européenne n°92-42 relative au rendement des \nchaudières\n\n0020130774_02 - 09/12 - Saunier Duval\n- 5 -\nINTRODUCTION\nFR\n2.5 Schéma hydraulique \n18\n17\n16\n15\n14\n13\n12\n11\n10\n9\n8\n7\n6\n5\n4\n3\n2\n1\n20\n19\n21\n22\n23\n24\n25\n26\n27\n28\n29\n30\n31\n32\nLégende\n1    Robinet d'arrêt de l'arrivée eau froide\n2    Robinet d'arrêt du retour chauffage\n3    Filtre eau froide\n4    Disconnecteur\n5    Robinet de remplissage\n6    Robinet de vidange du circuit chauffage\n7    Capteur de débit\n8    Capteur de pression\n9    Pompe\n10    Capteur de température du retour chauffage\n11    Echangeur sanitaire\n12    By-pass\n13    Récupérateur de condensats\n14    Électrode d’allumage et de contrôle de flamme\n15    Brûleur\n16    Echangeur chauffage\n17    Vase d'expansion chauffage\n18    Fusible thermique\n19    Evacuation des gaz brûlés\n20    Capteur de température du ballon de micro-accumulation\n21    Silencieux\n22    Ballon de micro-accumulation\n23    Résistance de maintien en température\n24    Ventilateur\n25    Soupape de sécurité sanitaire\n26    Mécanisme gaz\n27    Allumeur\n28    Capteur de température du départ chauffage\n29    Vanne 3 voies\n30    Soupape de sécurité chauffage\n31    Robinet d'arrêt du gaz\n32    Robinet d'arrêt du départ chauffage\nA    Retour chauffage\nB    Arrivée eau froide \nC   Départ chauffage\nD    Départ eau chaude \nE   Arrivée gaz\nF   Evacuation des condensats\n\n0020130774_02 - 09/12 - Saunier Duval\n- 6 -\nINTRODUCTION\nFR\n3 Consignes de sécurité et réglementations\n3.1 Consignes de sécurité\nSi la pression de gaz à l’entrée de l’appareil est en dehors \nde la plage spécifiée, l’appareil ne doit pas être mis en \nfonctionnement.\ne\nUne installation incorrecte peut provoquer un choc \nélectrique voire détériorer l’appareil.\n•\tNe désactivez jamais les dispositifs de sécurité et n’essayez \njamais d’en modifier les réglages.\n•\tPrenez impérativement en considération les techniques et \nprécautions de manutention suivantes :\n -Saisissez l'appareil par sa base.\n -Si nécessaire, portez des vêtements de protection, comme des \ngants de protection et des chaussures de sécurité.\n•\tAssurez-vous que les techniques utilisées pour soulever \nl’appareil garantissent votre sécurité :\n -Maintenez votre dos droit.\n -Évitez de vous tourner au niveau de la taille.\n -Évitez de trop pencher la partie supérieure de votre corps.\n -Utilisez toujours la paume de la main pour saisir l’appareil.\n -Utilisez les poignées conçues pour la manutention.\n -Placez la charge le plus près possible de votre corps.\n -Faites-vous aider dès que cela s’avère nécessaire.\n•\tL’utilisateur ne doit en aucun cas toucher ni régler les \ncomposants scellés.\n•\tLors des branchements, positionnez correctement les joints \nafin d’éviter tout risque de fuite de gaz ou d’eau.\n•\tL'appareil contient des pièces métalliques (composants). Elles \ndoivent être manipulées et nettoyées avec précaution. Soyez \nparticulièrement attentifs aux bords coupants.\n•\tRespectez les consignes de sécurité de base avant de procéder à \nl’entretien ou au remplacement des pièces détachées :\n -Arrêtez l’appareil.\n -Coupez l’alimentation électrique de l’appareil.\n -Fermez la vanne d’arrêt de gaz de l’appareil.\n -Coupez le circuit hydraulique de l’appareil à l’aide des vannes \nd’isolement, le cas échéant.\n -Laissez refroidir l'appareil avant d'effectuer les travaux \nd'entretien.\n -Vidangez l’appareil si vous devez remplacer des composants \ndu circuit hydraulique.\n -Protégez tous les composants électriques de l’eau lorsque \nvous intervenez sur l’appareil.\n -Utilisez uniquement des pièces détachées d’origine.\n -Utilisez uniquement des joints toriques et des joints neufs.\n -Vérifiez l’étanchéité des conduites de gaz et d’eau lorsque \nvous aurez réalisé votre intervention.\n -Procédez à un test de fonctionnement et vérifiez la sécurité du \nsystème une fois votre intervention terminée.\n3.2 Réglementations  \nLors de l’installation et de la mise en fonctionnement de \nl’appareil, les arrêtés, directives, règles techniques, normes et \ndispositions ci-dessous doivent être respectés dans leur version \nactuellement en vigueur :\n3.2.1 Bâtiments d’habitation:\n -Arrêté du 2 Août 1977 modifié, relatif aux règles techniques et \nde sécurité applicables aux installations de gaz combustibles \net d’hydrocarbures liquéfiés situées à l’intérieur des bâtiments \nd’habitation et de leurs dépendances.\n -NF DTU 61.1 (norme P 45-204) : Installations de gaz dans les \nlocaux d’habitation.\n -NF DTU 65.14 (norme P 52-307) Exécution de planchers \nchauffants à eau chaude. \nDOMAINE D’APPLICATION \nLa classe 2 définie dans ce guide technique correspond à \ndes installations de type “basse température” comportant \npar exemple des panneaux rayonnants constitués de tubes \ndisposés dans le plancher du local, parcourus par de l’eau dont \nla température est normalement inférieure ou égale à 50°C et \npouvant subir des pointes accidentelles à 65°C. Un dispositif \nparticulier limite impérativement la température de l’eau à 65°C \nau plus. \nSECURITE \nUn dispositif de sécurité indépendant de la régulation, avec \nréarmement manuel et fonctionnant même en l’absence de \ncourant ou de fluide moteur, coupe impérativement la fourniture \nde chaleur dans le circuit des panneaux lorsque la température \ndu fluide atteint 65°C.\n -NF DTU 24.1 (norme P 51-201) \"Travaux de fumisterie \n- Systèmes d’évacuation des produits de combustion \ndesservant un ou des appareils\".\n -Norme NF C 15-100 relative à l’installation des appareils \nraccordés au réseau électrique.\n -Norme NF C 73-600 relative à l’obligation de raccordement des \nappareils électriques à une prise de terre.\n -Règlement Sanitaire Départemental. \n\n0020130774_02 - 09/12 - Saunier Duval\n- 7 -\nINTRODUCTION\nFR\n3.2.2 Etablissements recevant du public (ERP) \nPar «établissements recevant du public», l’article R 123-\n2 du Code de la construction et de l’habitation désigne les \n«bâtiments, locaux et enceintes dans lesquels des personnes \nsont admises soit librement, soit moyennant une rétribution ou \nune participation quelconque, ou dans lesquels sont tenues des \nréunions ouvertes à tout venant ou sur invitation, payantes ou \nnon».\nLes textes réglementaires applicables à ces établissements sont :\n -d’une part, les articles R 123-1 à R 123-55 du Code de la \nconstruction et de l’habitation (ancien décret du 31 octobre \n1973);\n -d’autre part, le règlement de sécurité contre les risques \nd’incendie et de panique dans les établissements rece-\nvant du public qui peut être, selon la nature de l’activité de \nl’établissement, soit le règlement issu de l’arrêté du 23 mars \n1965 modifié, soit celui approuvé par l’arrêté du 25 juin 1980 \nmodifié.\n4 Recyclage\ni\nLe recyclage de l’emballage doit être effectué par le \nprofessionnel qualifié qui a installé l’appareil.\n4.1 Appareil\nL’appareil est principalement constitué de matériaux recyclables.\nCe symbole signifie que cet appareil ne doit pas être \njeté avec les ordures ménagères, qu’il fait l’objet \nd’une collecte sélective en vue de sa valorisation, de \nsa réutilisation ou de son recyclage.\n•\tConfiez l’appareil à un point de collecte approprié pour le \ntraitement, la valorisation, le recyclage des déchets. \ni\nEn respectant cette directive, vous faites un geste pour \nl’environnement, vous contribuez à la préservation \ndes ressources naturelles et à la protection de la santé \nhumaine.\n4.2 Emballage\nNous vous conseillons de recycler l’emballage de l’appareil de \nmanière responsable.\n•\tTriez les déchets de manière à séparer ceux qui peuvent être \nrecyclés (cartons, plastiques...) et ceux qui ne peuvent pas être \nrecyclés (cerclage...).\n•\tEliminez ces déchets conformément à la réglementation en \nvigueur.\n\n0020130774_02 - 09/12 - Saunier Duval\n- 8 -\nINSTALLATION\nFR\nINSTALLATION\ni\nToutes les dimensions des illustrations sont exprimées \nen millimètres (mm).\n5 Emplacement de l’appareil\n5.1 Emplacement\nConsignes\n•\tAvant de choisir l’emplacement de l’appareil, lisez \nattentivement les mises en garde relatives à la sécurité ainsi \nque les consignes du manuel d’utilisation et du manuel \nd’installation.\n•\tVérifiez que la structure du mur sur lequel doit être installé \nl’appareil permet de supporter le poids de l’appareil. \n•\tVérifiez que l’espace dans lequel doit être posé l’appareil \npermet une installation correcte et que l'accessibilité \nest respectée. Vous devez vous assurer que les raccords \nd'alimentation en eau, gaz et à l’évacuation des gaz de \ncombustion sont accessibles pour être vérifiés (voir le chapitre \n\"Accessibilité\").\n•\tExpliquez ces exigences à l’utilisateur.\n•\tN’installez pas l’appareil au-dessus d’un autre appareil \nqui pourrait l’endommager (par exemple, au-dessus d’une \ncuisinière susceptible de dégager de la vapeur et des graisses) \nou dans une pièce fortement chargée en poussière ou dont \nl’atmosphère est corrosive.\n•\tL’emplacement de montage doit être à l’abri du gel toute \nl’année. Si cette condition ne peut être respectée, informez \nl’utilisateur et conseillez-lui de prendre les mesures qui \ns’imposent.\n5.2 Accessibilité\n•\tPour permettre un entretien périodique, respectez les \ndistances indiquées sur le schéma ci-après.\n600\nmin.\n0\nmin.\n0\nmin.\n300\nmin.\n300\nmin.\nØA\nØA + 5 min.\n6 Installation de l’appareil \n6.1 Liste du matériel livré\nL'appareil est livré en un seul colis avec un sachet de documents \net un sachet d'accessoires.\nLa plaque de raccordement commandée séparément est livrée \nen un seul colis avec un gabarit de perçage et une barrette de \nfixation.\ni\nLes colis de ventouse seront commandés en fonction \nde la configuration de l'installation.\n•\tVérifiez le contenu des colis.\n\n0020130774_02 - 09/12 - Saunier Duval\n- 9 -\nINSTALLATION\nFR\n2.5\n2.4\n2.3\n2.2\n2.12\n56\n4\n3.4\n3.3\n3.2\n3.1\n3.6\n3\n1\n3.5\nLégende\n1Chaudière(x1)\n2Sachet d'accessoires(x1)\n2.1    Flexible d'évacuation des condensats(x1)\n2.2    Sachet de joints(x1)\n     - Joint plat ½\"(x2)\n     - Joint plat ¾\" (x5)\n     - Joint pour arrivée eau foride ¾\" (x4)\n2.3    Rallonge de robinet de remplissage(x1)\n2.4    Sachet d'évacuation(x1)\n2.5    Sachet de raccordement(x1)\n     - Douille retour chauffage(x1)\n     - Douille arrivée eau froide(x1)\n     - Douille départ chauffage(x1)\n     - Douille eau chaude sanitaire (x1)\n     - Douille gaz(x1)\n3Sachet de documents(x1)\n3.1    Etiquette de changement de gaz(x2)\n3.2    Magnet(x1)\n3.3    Carte installateur confiance(x1)\n3.4    Demande de garantie(x1)\n3.5    Notice d'emploi(x1)\n3.6    Manuel d'installation(x1)\n4Gabarit de perçage (*)(x1)\n5Plaque de raccordement (*)(x1)\n6Barrette de fixation (*)(x1)\n(*)Commandés séparément\n6.2 Recommandations avant installation\n6.2.1 Conception du circuit sanitaire\nLe circuit de distribution sera réalisé de manière à éviter au \nmaximum les pertes de charge (limiter le nombre de coudes, \nutiliser des robinetteries à forte section de passage afin de \npermettre un débit suffisant).\nL'appareil peut fonctionner avec une pression d’alimentation \nminimale. Un meilleur confort d’utilisation sera obtenu à partir de \n0.8 bar de pression d’alimentation.\n6.2.2 Conception du circuit chauffage\nL'appareil peut être intégrée à tous les types d’installation :  \nbi-tube, mono-tube série ou dérivé, plancher chauffant, etc...\nLes surfaces de chauffe peuvent être constituées de radiateurs, \nde convecteurs, d’aérothermes ou de planchers chauffant. Dans \nle cas d’un plancher chauffant, l’installation doit être équipée \nd’un dispositif de limitation de température à 54°C sur le départ \n(voir chapitre \"Raccordements électriques\"). Ce dispositif non \nfourni, doit pouvoir absorber par son inertie les trains de chaleur \nconsécutifs.\nAttention ! Si les matériaux utilisés sont de nature différente, \nil peut se produire des phénomènes de corrosion. Dans ce cas, \nil est recommandé d’ajouter à l’eau du circuit chauffage un \ninhibiteur (dans les proportions indiquées par son fabricant) qui \névitera la production de gaz et la formation d’oxydes.\nLes sections des canalisations seront déterminées en utilisant la \ncourbe débit/ pression (Reportez-vous au chapitre \"Réglage du \ncircuit chauffage\"). Le réseau de distribution sera calculé selon \nle débit correspondant à la puissance réellement nécessaire \nsans tenir compte de la puissance maximale que peut fournir \nl'appareil. Il est toutefois recommandé de prévoir un débit \nsuffisant pour que l’écart de température entre départ et retour \nsoit inférieur ou égal à 20°C. Le débit minimal est indiqué dans le \nchapitre \"Données techniques\" en fin de manuel.\nLe tracé des tuyauteries sera conçu afin de prendre toutes les \ndispositions nécessaires pour éviter les poches d’air et faciliter le \ndégazage permanent de l’installation. Des purgeurs devront être \nprévus à chaque point haut des canalisations ainsi que sur tous \nles radiateurs.\nLe volume d’eau total admissible pour le circuit de chauffage \ndépend, entre autres, de la charge statique à froid.  \nLe vase d’expansion incorporé à l'appareil est livré réglé en \nusine (Reportez-vous au chapitre \"Données techniques\" en fin de \nmanuel). Il est possible de modifier, à la mise en service, cette \npression de gonflage en cas de charge statique plus élevée.\nIl est recommandé de prévoir un robinet de vidange au point le \nplus bas de l’installation.\nDans le cas d’utilisation de robinets thermostatiques, il est \nimpératif de ne pas en équiper la totalité des radiateurs en \nveillant à poser ces robinets dans les locaux à fort apport et \njamais dans le local où est installé le thermostat d’ambiance.\n•\tS’il s’agit d’une ancienne installation, il est indispensable de \nrincer le circuit radiateurs avant d’installer le nouvel appareil.\n\n0020130774_02 - 09/12 - Saunier Duval\n- 10 -\nINSTALLATION\nFR\n•\tSi l'appareil n’est pas mis en place immédiatement, protégez \nles différents raccords afin que plâtre et peinture ne puissent \ncompromettre l’étanchéité du raccordement ultérieur.\n6.3 Dimensions\n418\n344\n130\n740\n6.4 Montage  \n•\tAssurez-vous que les matériaux utilisés pour la réalisation de \nl’installation sont compatibles avec ceux de l’appareil.\n•\tDéterminez l’emplacement de montage. Reportez-vous au \nchapitre \"Choix de l’emplacement\".\nLa fixation de la barrette devra être adaptée aux caractéristiques \ndu mur porteur et devra tenir compte du poids de la chaudière \n(voir chapitre \"Données techniques\" en fin de manuel).\n748\n65.5\n811\n=320=\n=276=\nØ105\n0\n55\n57.5\n57.5\n55\n•\tPercez les trous des vis de fixation conformément au gabarit \nde perçage livré avec la plaque de raccordement de l’appareil.\n3\n2\n1\n4\nLégende\n1    Chaudière\n2    Barrette de fixation\n3    Gabarit\n4    Plaque de raccordement\n\n0020130774_02 - 09/12 - Saunier Duval\n- 11 -\nINSTALLATION\nFR\n•\tPositionnez l'appareil sur la barrette de fixation.\n•\tMettez en place les joints sur les différents raccords.\n7 Connexion hydraulique\n7.1 Raccordement gaz et eau\n•\tAvant d’effectuer toute opération, procédez à un nettoyage \nsoigné des canalisations à l’aide d’un produit approprié \nafin d’éliminer les impuretés telles que limailles, soudures, \nhuiles et graisses diverses pouvant être présentes. Ces \ncorps étrangers seraient susceptibles d’être entraînés dans \nl'appareil, ce qui en perturberait le fonctionnement.\n•\tN’utilisez pas de produit solvant à cause du risque \nd’endommagement du circuit.\n•\tNe brasez pas les tubulures montées en place : cette opération \nrisque d'endommager les joints et l’étanchéité des robinets.\n•\tN'utilisez que les joints d'origine fournis avec l'appareil.\n•\tVérifiez qu’il n’y a pas de fuite. Réparez si nécessaire.\nmur\n2\n3\n45\n1\n6\n149,5\nLégende\n1    Douille retour chauffage : 2 écrous ¾\" + tubulure coudée \n2    Douille arrivée eau froide : 1 écrou ¾\" + tubulure coudée  \n+ 1 écrou ½\n3    Douille départ chauffage : 2 écrous ¾\" + tubulure coudée\n4    Douille eau chaude sanitaire : 1 écrou ¾\" + tubulure coudée  \n+ 1 écrou ½\"\n5    Douille gaz : 2 écrous ½\" + tubulure coudée\n6    Plaque de raccordement + flexible\n3\n1\n2\n4\n2\nLégende\nA    Test d'étanchéité du circuit chauffage + remplissage du circuit \nchauffage\nB    Test d'étanchéité du circuit sanitaire\n1    Départ chauffage\n2    Flexible\n3    Arrivée eau froide\n4    Départ eau chaude sanitaire\n -Configuration A :\nLe flexible (2) permet de faire les tests d’étanchéité sur le circuit \nchauffage et d'effectuer le remplissage du circuit chauffage.\n -Configuration B :\nLe flexible (2) permet de faire les tests d’étanchéité sur le circuit \nsanitaire.\n1\n2\n3\n4\n6\n5\n7\n8\n9\nLégende\n1    Flexible d'évacuation des soupapes de sécurité chauffage et \nsanitaire\n2    Flexible d'évacuation du disconnecteur\n3    Rallonge du robinet de remplissage\n4    Robinet de remplissage\n5    Evacuation des soupapes de sécurité chauffage et sanitaire\n6    Robinet de vidange\n7    Evacuation du disconnecteur\n8    Clip de fixation du flexible\n9    Evacuation vers les égouts (siphon non fourni)\n•\tRaccordez les soupapes de sécurité et le disconnecteur à un \ncircuit d’évacuation vers les égouts en utilisant les flexibles \nfournis. Le dispositif d’évacuation doit permettre de voir \nl’écoulement de l’eau.\n•\tEmboîtez la rallonge bleue (3) sur le robinet de remplissage (4).\n\n0020130774_02 - 09/12 - Saunier Duval\n- 12 -\nINSTALLATION\nFR\n7.2 Raccordement du récupérateur de condensats\na\nAttention : les condensats sont très acides (leur pH \nest compris entre 3.5 et 5), utilisez des gants de \nprotection.\nb\nLe rejet direct des condensats dans le milieu naturel \nest interdit.\ni\nLe volume de condensats évacué peut atteindre \nenviron 15 litres par jour en maison individuelle.  \nCe volume est négligeable comparé au volume d'eaux \nusées rejeté par une maison car les condensats sont \ndilués dans ces eaux.\n1\n2\n3\nLégende\n1    Siphon d’évacuation (non fourni)\n2    Flexible d’évacuation des condensats\n3    Récupérateur de condensats\n•\tRaccordez le flexible d’évacuation des condensats (2) à un \ncircuit d’évacuation vers les égouts.\n•\tAssurez-vous que les condensats ne stagnent pas dans le \ncircuit d'évacuation.\n•\tUtilisez du PVC ou d'autres matériaux adaptés pour évacuer \nles condensats non neutralisés. L'acier noir, l'acier galvanisé \net le cuivre ne sont pas recommandés compte tenu des risques \nde corrosion.\n•\tSi les matériaux du dispositif d'évacuation ne sont pas \nadaptés, installez un kit de neutralisation des condensats \nafin d'obtenir en sortie un pH pratiquement neutre. Dans \nce cas, prévoyez la possibilité de réaliser un prélèvement \nd'échantillon à la sortie du dispositif afin de vérifier le pH.\nOK\nOK\n8 Évacuation des gaz de combustion\n8.1 Réglementation\nb\nSeuls les accessoires d'évacuation des gaz de \ncombustion spécialement conçus pour cet appareil \ndoivent être utilisés.\nDifférentes configurations de sortie ventouse sont réalisables.\n•\tN’hésitez pas à consulter votre revendeur pour obtenir des \ninformations supplémentaires sur les autres possibilités et les \naccessoires associés.\n•\tRespectez une pente minimum de 5% entre le coude et \nl’extrémité du terminal ventouse pour permettre le retour des \ncondensats vers l’appareil.\nLa longueur maximale de la ventouse est définie en fonction de \nson type (par exemple C13).\n•\tQuel que soit le type de ventouse sélectionné, respectez les \ndistances minimales indiquées dans le tableau ci-après pour \nle positionnement des terminaux de ventouse.\n•\tInstallez le conduit d'évacuation des gaz de combustion à \nl'aide de la notice d'installation fournie avec la ventouse.\n•\tExpliquez ces exigences à l’utilisateur de l’appareil.\n\n0020130774_02 - 09/12 - Saunier Duval\n- 13 -\nINSTALLATION\nFR\na\nAttention ! Si la configuration de sortie des fumées est \nsituée à moins de 1.80 m du sol, vous devez installer \nun kit de protection terminal.\nb\nAttention ! L’étanchéité entre la sortie du ventilateur \net la ventouse doit être assurée.\nI\nN\n2000\nF\nG\nE\nE\nI\nH\nM\nL\nD\nA\nC\nB\nP\nO\nRepèrePositionnement des terminaux de ventousemm\nASous une fenêtre600\nBSous une bouche d’aération600\nCSous une gouttière300\nDSous un balcon300\nED’une fenêtre adjacente400\nFD’une bouche d’aération adjacente600\nGDe tubes d’évacuation verticaux ou horizontaux600\nHD’un angle de l’édifice300\nID’un angle rentrant de l’édifice1000\nRepèrePositionnement des terminaux de ventousemm\nLDu sol ou d’un autre étage1800\nMEntre 2 terminaux verticaux1500\nNEntre 2 terminaux horizontaux600\nOD’une bouche d’aération adjacente600\nPD’une fenêtre de toit adjacente400\n\n0020130774_02 - 09/12 - Saunier Duval\n- 14 -\nINSTALLATION\nFR\n8.2 Description de la configuration d’évacuation \ndes gaz de combustion\n8.2.1 Système ventouse horizontale Ø 60/100 mm ou \nØ 80/125 mm (installation de type C13)\na\nAttention ! Si la configuration de sortie des fumées est \nsituée à moins de 1.80 m du sol, vous devez installer \nun kit de protection terminal.\nb\nAttention ! Les orifices d’un terminal pour conduits \nséparés doivent déboucher dans un carré de 50 cm \nde côté.\nØ 60/100 mm\nL\n63\n1\nLégende\n1    Joint\nØ 80/125 mm\n/\u0003\n1 \nLégende\n1    Joint\nTypeLongueur max.\nØ 60/10010 m\nØ 80/12525 m\nChaque fois qu‘un coude à 90° supplémentaire est nécessaire (ou \n2 à 45°), la longueur (L) doit être réduite de 1 m.\n8.2.2 Système ventouse verticale Ø 60/100 mm ou Ø \n80/125 mm (installation de type C33)\na\nAttention ! Si la configuration de sortie des fumées est \nsituée à moins de 1.80 m du sol, vous devez installer \nun kit de protection terminal.\nb\nAttention ! Les orifices d’un terminal pour conduits \nséparés doivent déboucher dans un carré de 50 cm \nde côté.\nL\nTypeLongueur max.\nØ 60/10010 m\nØ 80/12525 m\nChaque fois qu’un coude à 90° supplémentaire est nécessaire (ou \n2 à 45°), la longueur (L) doit être réduite de 1 m.\n\n0020130774_02 - 09/12 - Saunier Duval\n- 15 -\nINSTALLATION\nFR\n8.2.3 Système ventouse pour conduit collectif \nØ 60/100 mm (installation de type C43)\nb\nAttention ! Les liaisons au conduit seront réalisées à \nl'aide de l'accessoire spécialement développé par le \nfabricant de l'appareil.\nb\nUne chaudière raccordée à une installation de type C4 \ndoit être connectée uniquement sur des cheminées à \ntirage naturel.\nb\nL'écoulement des condensats provenant des \nsystèmes de conduit collectif n'est pas autorisé dans \nla chaudière.\nB\nA\n1\n2\n3\n4\n5\nL\nLégende\n1    Dispositif d’équilibrage des pressions\n2    Conduit d’amenée d’air \n3    Conduit collecteur\n4    Chaudière\n5    Trappe de visite\nA    Dernier étage\nB    Ré de chaussée\nL      Longueur max.\nTypeLongueur max.\nØ 60/10010 m\nChaque fois qu‘un coude 90° supplémentaire est nécessaire (ou 2 \nà 45°), la longueur (L) doit être réduite de 1 m.\n8.2.4 Système ventouse pour conduit collectif sous \npression Ø 80/125 mm  (installation de type \nC43P)\na\nAttention ! Lors de la pose ou de la dépose de \nl'appareil, il y a risque de pollution dans la pièce par \nles produits de combustion.  \nAssurez-vous de l'étanchéité du conduit.\nb\nAttention ! Les liaisons au conduit seront réalisées à \nl'aide de l'accessoire spécialement développé par le \nfabricant de l'appareil.\nL\n153\n1\nLégende\n1    Clapet 0020081283\nSi d’autres appareils raccordés au conduit collectif sont en \nfonctionnement, le clapet (1) dans le circuit de combustion évite \nla circulation inverse des fumées quand l'appareil est arrêté.\nChaque fois qu’un coude à 90° supplémentaire est nécessaire (ou \n2 à 45°), la longueur (L) doit être réduite de 1 m.\n•\tReportez-vous au chapitre \" Réglages spécifiques ▸ Réglages \nà l'installation\" et renseignez le code d.85 en fonction de la \nvaleur indiquée dans les tableaux suivant.\nDescriptionUnitéF 25\nGazG20\nMode\nQnkW5,616,823,5\nPu (80/60)kW5,316,4-\nPu (50/30)kW617,8-\nPukW--23,5\nCO2%8,99,29,2\nDébit massique des fuméesg/s2,67,610,6\nTempérature des fumées (80°C/60°C)°C6364-\nTempérature des fumées (50°C/30°C)°C4950-\nTempérature des fumées °C--71\nPression sortie de chaudièrePa2980136\nParamètre d.85kW7\n\n0020130774_02 - 09/12 - Saunier Duval\n- 16 -\nINSTALLATION\nFR\nDescriptionUnitéF 30\nGazG20\nMode\nQnkW6,623,228,4\nPu (80/60)kW6,322,7-\nPu (50/30)kW7,124,8-\nPukW--28,4\nCO2%8,99,29,2\nDébit massique des fuméesg/s3,110,412,8\nTempérature des fumées (80°C/60°C)°C6269-\nTempérature des fumées (50°C/30°C)°C4855-\nTempérature des fumées °C--72\nPression sortie de chaudièrePa2791150\nParamètre d.85kW8\nDescriptionUnitéF 35\nGazG20\nMode\nQnkW8,2128,3532,46\nPu (80/60)kW7,727,1931,81\nPu (50/30)kW8,7730,3334,73\nPukW---\nCO2%99,239,43\nDébit massique des fuméesg/s3,812,814,3\nTempérature des fumées (80°C/60°C)°C6469-\nTempérature des fumées (50°C/30°C)°C4547-\nTempérature des fumées °C--65\nPression sortie de chaudièrePa27129175\nParamètre d.85kW10\n8.2.5 Système flexible ventouse pour raccordement \ncheminée (installation de type C93)\nCette configuration permet de réutiliser un ancien conduit de \nfumée ou de ventilation pour l’implantation d’un conduit de \nchaudière étanche. La longueur du conduit vertical (L2) est un \nflexible d’évacuation des fumées Ø 80 mm.\nb\nPour éviter que toutes les impuretés de la cheminée \nsoient récupérées par l’aspiration de la chaudière :\nNe raccordez pas l’appareil directement en sortie \nverticale. \nNe raccordez pas l’appareil sur une cheminée ayant \névacuée des produits fuels. \nL2\nL1\nS\nS\nD\nA\nB\nLégende\nL1    Longueur du conduit concentrique horizontal\nL2     Longueur du conduit vertical\nD     Diamètre intérieur de la cheminée\nS     Largeur intérieure de la cheminée\nA    Coude du terminal ventouse horizontal\nB    Coude du conduit flexible\nL1: Longueur du conduit concentrique horizontal. Cette valeur \nprend en compte la perte de charge générée par le coude A.\nL2: Longueur du conduit vertical. Cette valeur prend en compte \nla perte de charge générée par le Coude B et le terminal de la \ncheminée.\nLa prise d’air se fait par le conduit de cheminée (intervalle entre \nles deux conduits). En conséquence, la valeur (L2) évolue en \nfonction de la section de cheminée et des caractéristiques de la \nchaudière selon le tableau ci dessous.\n\n0020130774_02 - 09/12 - Saunier Duval\n- 17 -\nINSTALLATION\nFR\nØ du conduit pour la \npartie L1\n60/100\nDimension cheminée\n(mm)\nD = \nØ130\nS = \n120\nD = \nØ150\nS = \n130\nD = \nØ180\nS = \n140\nF25\nL1 (m)111\nL2 max. (m)121226\nL1 + L2 (m)131327\nF30\nL1 (m)111\nL2 max. (m)121730\nL1 + L2 (m)131831\nF35\nL1 (m)111\nL2 max. (m)93130\nL1 + L2 (m)103231\nChaque fois qu’un coude à 90° supplémentaire est nécessaire (ou \n2 à 45°), la longueur (L1+L2) doit être réduite de 1 m.\nb\nLa longueur du conduit concentrique horizontal (L1) \nne doit jamais être supérieure à 3 m.\ni\nSi (L1) est supérieure à 1m la longueur majorée doit \nêtre retranchée de (L2).\n8.2.6 Système flexible condensation pour \nraccordement cheminée sous pression \n(installation de type B23P)\nb\nDans cette configuration, les conditions \nréglementaires concernant les aérations doivent être \nrespectées.\nCette configuration permet de réutiliser un ancien conduit de \nfumée ou de ventilation pour l’implantation d’un conduit de \nchaudière étanche. La longueur du conduit horizontal (L1) est de \ntype concentrique Ø 60/100. La longueur du conduit vertical (L2) \nest un flexible d’évacuation des fumées Ø 80 mm.\nL’air frais est pris dans la pièce où est installé l'appareil par \nl'intermédiaire du coude du terminal ventouse horizontal (A).\nL2\nL1\nA\nB\nLégende\nL1    Longueur du conduit concentrique horizontal\nL2    Longueur du conduit vertical\nA    Coude du terminal ventouse horizontal\nB    Coude du conduit flexible\nTypeLongueur L1 min. \nLongueur L2 min. \nLongueur  \nL1 + L2 max. \nØ 60/1000.5 m-\n18\nØ 80-1 m\nChaque fois qu’un coude à 90° supplémentaire est nécessaire (ou \n2 à 45°), la longueur (L1+L2) doit être réduite de 1 m.\n\n0020130774_02 - 09/12 - Saunier Duval\n- 18 -\nINSTALLATION\nFR\n9 Connexion électrique\ne\nUne installation incorrecte peut provoquer un choc \nélectrique voire détériorer l’appareil.  \nLe branchement électrique de l’appareil ne doit être \neffectué que par un professionnel qualifié.\nL’appareil doit être branché directement à une prise de courant \naccessible, fixe et commutable.\nLe câblage extérieur doit être relié à la terre. La polarité doit être \ncorrecte et conforme aux normes en vigueur.\nLe fabricant décline toute responsabilité en cas de dommages \ncausés à des tiers par une mise à la terre incorrecte de l’appareil. \nCela inclut le non-respect des normes en vigueur.\nDes protections supplémentaires peuvent être requises à \nl'installation afin d'assurer une catégorie de surtension II.\nL'installation doit être munie d'une protection en courant.\n•\tRaccordez le câble d’alimentation de l'appareil au réseau 230 \nV monophasé + terre.\n•\tRespectez le raccordement phase et neutre sur l'appareil.\n•\tN’utilisez pas du câble supérieur à 10 mm de diamètre pour \nles raccordements électriques.\nSelon les normes en vigueur, ce raccordement doit être réalisé \npar l’intermédiaire d’un interrupteur bipolaire avec une \nséparation d’au moins 3 mm entre chaque contact.\n9.1 Accès au tableau principal\n1\n2\n3\n4\n \nLégende\n1    Accès pour raccordement 24 V\n2    Borniers de raccordement 24 V\n3    Borniers de raccordement 230 V\n4    Accès pour raccordement 230 V\n9.2 Carte principale\n1\n2\n3\nLégende\n1    Connecteur\n2    Fils électriques\n3    Gaine\nLorsque vous raccordez des câbles électriques sur un connecteur \nde la carte électronique :\n•\tConservez une distance de 30 mm maximum entre le \nconnecteur (1) et la gaine dénudée (3). \n•\tDans le cas contraire, attachez les fils électriques (2) ensemble \nà l’aide d’un collier plastique.\n•\tFixez les câbles dans le serre-câbles du boîtier électrique.\n9.3 Accessoires externes\n230\nV\nX17\nX18\nRT 24VT° extBUS\nBUS\n24 V\n3\n4\n7\n2\n1\nLégende\n1    Connecteur thermostat d'ambiance 24V\n2    Connecteur thermostat d'ambiance Ebus ou récepteur radio Ebus\n3    Connecteur sonde de température extérieure\n4    Connecteur sécurité de surchauffe pour plancher chauffant\n\n0020130774_02 - 09/12 - Saunier Duval\n- 19 -\nINSTALLATION\nFR\n9.4 Schéma électrique\n1\n10\n2\n11\n3\n12\n4\n13\n5\n14\n6\n15\n7\n16\n8\n17\n9\n18\n10\n5\n9\n4\n8\n3\n7\n2\n6\n1\n1 2\n3 4\n10 9 8 7 6 5 4 3 2 1\n1920  18 17 16 1514 13 12 11\nM\nD\nM\nTT\nT°C\nNTC\nEbus\n24 V\nX2\nX30\nX90\nX32\nX40\nX51\nX31\nX25\nX21\nX13\n230 VAC\nLN\nX12\nX101\nFUS\nX14\nX20\nX18\nX17\nX17\n1 2 3\n1\n4\n2\n5\n3\n6\n10 9 8 7 6 5 4 3 2 1\n1920  18 17 16 1514 13 12 11\n1 234   2 1\nX2\n1 23452 11111...892 1\n1\n10\n2\n11\n3\n12\n4\n13\n5\n14\n6\n15\n7\n16\n8\n17\n9\n18\nX20\n1 2\n3 4\n1\n1 2\n1\nX21\n1918171615\n1\n2\n3\n4\n5\n8\n9\n6\n7\n1011121314\nLégende\n1    Connecteur sécurité de surchauffe pour plancher chauffant\n2    Connecteur accessoires de régulation\n3    Connecteur pour capteur de température à raccorder avec un kit \nsolaire optionnel\n4    Carte option 24V\n5    Interface utilisateur\n6    Fusible\n7    Connecteur pour option 230 V\n8    Pompe \n9    Ballon de micro-accumulation\n10    Electrode d’allumage et de contrôle de flamme\n11    Capteur de température du départ chauffage\n12    Capteur de température du retour chauffage\n13    Mécanisme gaz\n14    Ventilateur\n15    Fusible thermique\n16    Capteur de température du ballon de micro-accumulation\n17    Capteur de débit sanitaire\n18    Vanne 3 voies\n19    Détecteur de pression du circuit chauffage\n\n0020130774_02 - 09/12 - Saunier Duval\n- 20 -\nINSTALLATION\nFR\n10 Mise en service \n10.1 Première mise en fonctionnement\n•\tAppuyez sur le bouton marche/arrêt pour mettre en service \nl’appareil.\n•\tAssurez-vous que les fonctions sanitaire et chauffage de votre \nappareil sont désactivées.\n10.2   Remplissage de l’installation de chauffage\n•\tAssurez-vous que le robinet d'arrivée d'eau froide de \nl'installation est ouvert.\n•\tOuvrez les robinets d’arrêt situés sur les raccordements : ils \ndoivent être positionnés dans le sens de l’écoulement.\n4\n3\n2\n1\nLégende\n1    Robinet de remplissage\n2    Pompe \n3    Vis de l'arbre de la pompe\n4    Bouchon du purgeur de la pompe \n•\tOuvrez le bouchon du purgeur situé sur la pompe ainsi que les \npurgeurs automatiques de l’installation.\n•\tOuvrez le robinet de remplissage situé sous l'appareil jusqu’à \nlire 0.8 bar sur l’indicateur de pression.\ni\nUne routine de dégazage se lance automatiquement \npendant 5 minutes dès que l'appareil atteint 0.5 \nbar de pression. Pendant ce temps, les fonctions \nchauffage et eau chaude sanitaire ne peuvent pas être \nactivées.\n•\tPurgez chaque radiateur jusqu’à écoulement normal de l’eau \npuis refermez les purgeurs de l'installation.\n•\tLaissez le bouchon du purgeur de la pompe ouvert.\ni\nLes deux opérations suivantes permettent de \ndébloquer le moteur de la pompe suite à un \nstockage prolongé et de purger l’air du circuit de \nrefroidissement de la pompe.\n•\tRetirez la vis de l'arbre de la pompe et introduisez un tournevis \nplat. Un filet d’eau sans pression doit normalement sortir de la \npompe.\n•\tEntraînez l’arbre de la pompe sur quelques tours, puis \nremettez en place la vis.\n10.3 Remplissage du circuit d’eau chaude sanitaire\n•\tOuvrez les différents robinets d’eau chaude pour remplir le \ncircuit sanitaire.\n10.4 Remise en pression du système\n1\n1\n\u0015\nLégende\n1    Bouchon\n2    Récupérateur de condensats\n•\tAmorcez le bouchon (1) du récupérateur de condensats en le \nremplissant avec de l'eau.\n•\tActivez les fonctions sanitaire et chauffage de votre appareil.\n•\tFaites fonctionner l’appareil au moins 15 minutes en chauffage \navec une température de consigne chauffage supérieure \nou égale à 50°C (non applicable pour une installation avec \nplancher chauffant).\n•\tPurgez à nouveau chaque radiateur jusqu’à écoulement \nnormal de l’eau puis refermez les purgeurs.\n•\tSi vous rencontrez des difficultés de dégazage, lancez les \nprogrammes de dégazage du circuit chauffage (reportez-vous \nau chapitre \"Réglages techniques de l’appareil et liste des \nparamètres\").\n•\tAssurez-vous que l’indicateur de pression affiche une valeur \nde 0.8 bar; sinon, remplissez à nouveau l'appareil.\n\n0020130774_02 - 09/12 - Saunier Duval\n- 21 -\nINSTALLATION\nFR\n10.5 Débits de gaz\nLes débits de gaz dépendent du taux de CO2 et de la vitesse du \nventilateur.\n•\tVérifiez le taux de CO2 dans les produits de combustion et \ncomparez-le avec les valeurs indiquées au chapitre \"Mesure \ndu CO2\".\n24\nV\n21\nLégende\n1    XXXX = vitesse min. du ventilateur\n2    YYYY = vitesse max. du ventilateur\n•\tPour connaître les vitesses min. (1) et max. (2) du ventilateur, \nconsultez l'étiquette collée sur le silencieux de l'appareil.\n10.5.1 Vérification de la vitesse max. du ventilateur\n•\tRéglez l'appareil sur le mode de test \"P.03 : forçage brûleur à \nP. max.\". Reportez-vous au chapitre \"Modes de test\".\n•\tDès que le mode de forçage du brûleur est activé, appuyez sur \nla touche  pendant plus de 7 secondes pour basculer \ndans le mode paramétrage. L’écran affiche \"0\".\n•\tPour vérifier la vitesse max. du ventilateur, reportez-vous au \nchapitre \"Réglages à l'installation\" et utilisez le code \"d.34\".\n•\tSi la valeur affichée à l'écran correspond à ± 200 tr/min à la \nvaleur \"YYYY\" indiquée sur l'étiquette, les débits de gaz sont \ncorrects.\n•\tSi ce n'est pas le cas, contactez le service après-vente.\n•\tAppuyer sur la touche RESET  pour quitter le menu de test \nou appuyer sur la touche  pendant plus de 3 secondes \npour basculer dans le mode test.\n10.5.2 Vérification de la vitesse min. du ventilateur\n•\tActivez le mode de test \"P.01\" et réglez la valeur à \"0\" pour \nforcer l'appareil à Pmin. Reportez-vous au chapitre \"Modes de \ntest\".\n•\tDès que le mode de forçage du brûleur est activé, appuyez sur \nla touche   pendant plus de 7 secondes pour basculer \ndans le mode paramétrage. L’écran affiche \"0\".\n•\tPour vérifier la vitesse min. du ventilateur, reportez-vous au \nchapitre \"Réglages à l'installation\" et utilisez le code \"d.34\".\n•\tSi la valeur affichée à l'écran correspond à ± 200 tr/min à la \nvaleur \"XXXX\" indiquée sur l'étiquette, les débits de gaz sont \ncorrects.\n•\tSi ce n'est pas le cas, contactez le service après-vente.\n•\tAppuyer sur la touche RESET  pour quitter le menu de test \nou appuyer sur la touche  pendant plus de 3 secondes \npour basculer dans le mode test.\n10.6 Test du système de chauffage\n•\tAssurez-vous que les organes de régulation externes \n(thermostat d'ambiance, sonde extérieure, ...) envoient une \ndemande de chauffage à l'appareil.\n•\tAssurez-vous que toutes les vannes thermostatiques des \nradiateurs sont ouvertes.\n•\tActivez la fonction chauffage sur le tableau de bord de \nl'appareil.\n•\tÉquilibrez les émetteurs de chaleur si nécessaire.\n10.7 Test du système d'eau chaude sanitaire\n•\tOuvrez un robinet d'eau chaude.\n•\tVérifiez que la température obtenue est conforme au réglage \neffectué sur l'appareil.\n10.8 Finalisation\n•\tAssurez-vous que le magnet est placé sur la façade de \nl'appareil.\n11 Réglages spécifiques \n11.1 Réglage du circuit de chauffage\nIl est nécessaire d’adapter ce débit en fonction du calcul de \nl’installation. A la livraison, la vis (1) du by-pass intégré est \nouverte de ½ tour.\n1\nLégende\n1    Vis du by-pass\n•\tEn fonction des besoins, effectuez la rotation de cette \nvis (par exemple, vissez pour fermer) pour adapter la \nhauteur manométrique disponible à la perte de charge de \nl’installation.\n\n0020130774_02 - 09/12 - Saunier Duval\n- 22 -\nINSTALLATION\nFR\nCourbe débit/pression : THEMAPLUS CONDENS F 25\n60\n50\n40\n30\n20\n10\n0\n50010001500\nB\n12\nLégende\nA    Pression disponible entre départ et retour chauffage (kPa)\nB    Débit dans le circuit chauffage (l/h)\n1    Vitesse min.\n2    Vitesse max.\nCourbe débit/pression : THEMAPLUS CONDENS F 30 \n60\n50\n40\n30\n20\n10\n0\n50010001500\nB\n12\nLégende\nA    Pression disponible entre départ et retour chauffage (kPa)\nB    Débit dans le circuit chauffage (l/h)\n1    Vitesse min.\n2    Vitesse max.\nCourbe débit/pression : THEMAPLUS CONDENS F 35 \n60\n50\n40\n30\n20\n10\n0\n50010001500\nB\n12\nLégende\nA    Pression disponible entre départ et retour chauffage (kPa)\nB    Débit dans le circuit chauffage (l/h)\n1    Vitesse min.\n2    Vitesse max.\n11.2 Réglages techniques de l’appareil et liste des \nparamètres\nL’accès aux données techniques de l'appareil permet d’effectuer \ncertains réglages et d’analyser d’éventuels dysfonctionnements.\nNota : la diminution de la puissance en chauffage n’a aucune \nincidence sur la puissance en eau chaude sanitaire.\n11.2.1 Réglages à l'installation\n•\tAppuyez pendant plus de 7 secondes sur la touche  pour \naccéder au menu de paramétrage. L’écran affiche \"0\".\n•\tAppuyez 4 fois sur la touche . \nL’écran affiche \"96\", c’est le mot de passe installateur.\n•\tAppuyez sur  pour valider. L’ecran affiche le paramètre \n\"d.00\" et sa valeur \"XX\".\n•\tAppuyez sur la touche  ou  du mode  pour accéder au \nparamètre à modifier. \n•\tAppuyez sur la touche  ou  du mode  pour modifier la \nvaleur du paramètre.\n•\tRépéter les deux phases précédentes pour chaque paramètre \nqui nécessite d’être modifié.\n•\tAppuyez pendant plus de 3 secondes sur la touche  pour \nsortir du menu de paramétrage.\n\n0020130774_02 - 09/12 - Saunier Duval\n- 23 -\nINSTALLATION\nFR\nCodeParamètreUnitéDescription\nRéglage \nusine\nParamètre \nmodifiable\nd.00Puissance maximale chauffagekW\nChoisissez une valeur :\nF 25 ▸ 5 à 18 kW\nF 30 ▸ 6 à 25 kW\nF 35 ▸ 8 à 30 kW\n \n15 \n15\n20\noui\nd.01Temps de post balayage en chauffagemin.Choisissez une valeur comprise entre 2 et 60.5oui\nd.02\nTemps de blocage du brûleur en mode \nchauffage (anti-court cycles)\nmin.\nAfin d’éviter une mise en marche et à l’arrêt fréquentes\ndu brûleur, un blocage électronique de la remise en marche est activé \npour une durée déterminée après chaque arrêt du brûleur. Le temps \nde blocage du brûleur peut être adapté aux conditions d’utilisation \nde l’installation de chauffage et dépend de la température de \nconsigne du chauffage :\n- à 80°C, la durée est fixe (2 minutes)\n- à 10°C, la durée est réglable : choisissez une valeur comprise entre \n2 et 60 minutes.\n20oui\nd.04Température de l'eau du ballon°CAffichage de la température de l'eau du ballon.-non\nd.18Fonctionnement de la pompe-\nMode de fonctionnement :\n0 = Discontinu avec brûleur\n1 = Continu avec T.A. \n2 = Permanent\n1oui\nd.19Vitesse de la pompe-\nMode de fonctionnement :\n0 = Automatique : vitesse max. lorsque le brûleur est allumé\n1 = Vitesse min. \n2 =  Automatique : vitesse automatique lorsque le brûleur est allumé \n3 = Vitesse max.\n2oui\nd.20\nTempérature de consigne de l'eau \nchaude sanitaire max.\n°C\nLa température de consigne de l'eau chaude sanitaire max. conseillée \nest de 60°C. Choisissez une valeur entre 50°C et 60°C.\n60oui\nLes 2 menus suivants s'affichent si une carte option (non fournie) est installée sur l'appareil.\nd.27Fonction relais 1-\nAffectation d’une fonction au relais 1 de la carte option :\n1 = Pompe de recirculation sanitaire\n2 = Pompe chauffage additionnelle\n3 = Pompe de charge ballon\n4 = Clapet fumées / ventilateur cheminée\n5 = Vanne gaz externe\n6 = message d’erreur externe\n1oui\nd.28Fonction relais 2-\nAffectation d’une fonction au relais 2 de la carte option :\n1 = Pompe de recirculation sanitaire\n2 = Pompe chauffage additionnelle\n3 = Pompe de charge ballon\n4 = Clapet fumées / ventilateur hotte\n5 = Vanne gaz externe\n6 = message d’erreur externe\n2oui\nLe menu suivant s'affiche si un kit de remplissage automatique du circuit chauffage (non fourni) est installé sur l'appareil.\nd.31Mode de remplissage-\nMode de fonctionnement : \n0 = Manuel\n1 = Semi-automatique\n2 = Automatique\n0oui\nd.34Vitesse du ventilateur\ntr/\nmin.\nAffichage de la vitesse du ventilateur entre 0 et 99.\nMultipliez la valeur affichée par 100.\n-non\nd.35Position de la vanne 3 voies-\n0 = Position chauffage\n100 = Position eau chaude sanitaire \n-non\nd.36Débit d'eau chaude sanitaire\nl/\nmin.\nAffichage du débit d'eau chaude sanitaire. -non\nLe menu suivant s'affiche si un système solaire (non fourni) est raccordé sur l'appareil.\nd.39Température de l'eau du circuit solaire°C\nAffiche la température de l'eau du circuit solaire mesurée par la \nsonde située en amont du mitigeur.\n-non\nd.40Température départ chauffage°CAffichage de la température départ chauffage.-non\nd.41Température retour chauffage°CAffichage de la température retour chauffage.-non\nd.43Courbe chauffageK\nReportez-vous à la notice de la sonde extérieure raccordée\nsur l'appareil.\n1.2oui\nd.45Pied de courbe chauffage°C20oui\n\n0020130774_02 - 09/12 - Saunier Duval\n- 24 -\nINSTALLATION\nFR\nCodeParamètreUnitéDescription\nRéglage \nusine\nParamètre \nmodifiable\nLe menu suivant s'affiche si une sonde extérieure (non fourni) est installée sur l'appareil.\nd.47Température extérieure °CAffiche la température mesurée par la sonde extérieure.-non\nd.62Offset nuit°C\nChoix de l’abaissement de consigne entre le jour (période CONFORT \ndu T.A.) et la nuit (période ECO du T.A.).\nChoisissez une valeur entre 0 et 31°C.\n0oui\nd.67\nTemps restant avant la fin de l'anti-\ncourt cycle en mode chauffage.\nmin.Affiche le temps restant avant la fin de l'anti-court cycle.-non\nd.71\nTempérature de consigne max. du \ndépart chauffage\n°CSélectionnez une valeur entre 50°C et 80°C.75oui\nd.85Puissance minimale de l'appareilkW\nChoisissez une valeur :\nF 25 ▸ 5 à 18 kW\nF 30 ▸ 6 à 25 kW\nF 35 ▸ 8 à 30 kW\n \n5\n6\n 8\noui\nd.88Filtrage du débit sanitaire-\nCette fonction permet d'éviter le déclenchement intempestif d'une \ndemande sanitaire lord d'un puisage d'eau froide\n0 = Non ▸ Q sanitaire > 1,5 l/min\n1 = Actif ▸ Q sanitaire > 1,5 l/min pendant 2 secondes\n0oui\nd.90\nDétection d'un thermostat d'ambiance \neBUS\n-\n0 = Non détecté\n1 = Détecté\n-non\nd.94\nRemise à zéro de la liste des codes \ndéfauts\n-\nCette fonction permet de remettre à zéro la liste des codes défauts \napparus sur l'appareil.\n0 = Non\n1 = Remise à zéro des défauts\n0oui\n11.2.2 Etat de l'appareil\n•\tAppuyez sur la touche  du mode  pendant plus de 3 \nsecondes pour connaître l'état de fonctionnement en cours de \nl'appareil. \nL’écran affiche l'état de l'appareil \"S.XX\".\n•\tAppuyez sur la touche  pendant plus de 3 secondes pour \nsortir de ce menu.\nEtatMode Chauffage\nS.00Pas de demande chauffage\nS.01Pré-balayage ventilateur\nS.02Pré-balayage pompe\nS.03Allumage\nS.04Brûleur allumé\nS.05Post balayage pompe / ventilateur\nS.06Post balayage ventilateur\nS.07Post balayage pompe\nS.08Temporisation anti court-cycles après chauffage\nEtatMode Eau Chaude Sanitaire\nS.10Demande sanitaire\nS.11Pré-balayage ventilateur\nS.13Allumage\nS.14Brûleur allumé\nS.15Post balayage pompe / ventilateur\nS.16Post balayage ventilateur\nS.17Post balayage pompe\nEtatRéchauffage sanitaire\nS.20Pré-balayage pompe\nS.21Pré-balayage ventilateur\nS.23Allumage\nS.24Brûleur allumé\nS.25Post balayage pompe / ventilateur\nS.26Post balayage ventilateur\nS.27Post balayage pompe\nS.28\nLa chaudière bloque le réchauffage du ballon après un cycle de \nréchauffage.\nEtatMessages particuliers\nS.30\nEtat par défaut, pas de demande chauffage, ni sanitaire. Si un \nT.A. EBUS est raccordé sur la chaudière, vérifiez que le shunt \nest présent sur les bornes 3 et 4 de la carte principale de la \nchaudière.\nS.31Mode de fonctionnement \"Eau chaude seule\"\nS.32\nCycle de contrôle : la vitesse du ventilateur en phase de \nfonctionnement est hors tolérance.\nS.34Mode de fonctionnement \"Protection contre le gel\"\nS.39 Contact plancher chauffant ouvert.\nS.41Pression d'eau trop élevée\nS.53\nCycle d'attente : différence de température entre le départ et le \nretour chauffage trop élevée. Si ∆T > 30, forçage à Pmin.\nS.54\nCycle d'attente : manque d'eau dans l'installation / montée en \ntempérature entre le départ et le retour chauffage trop élevée. \nS.96Test du capteur de température du retour chauffage.\nS.98\nTest des capteurs de température départ et retour chauffage ou \nl'appareil est en défaut. \nS.99Remplissage automatique en cours\n11.2.3 Modes de test\nEn activant ces différents modes de test, vous pouvez déclencher \ndes fonctions spéciales sur l'appareil.\n•\tAppuyez sur le bouton marche/arrêt pour éteindre l'appareil.\n•\tTout en maintenant la touche  enfoncée pendant plus de \n5 secondes, appuyez sur le bouton marche/arrêt.  \nL’écran affiche le premier mode de test \"P01\" et \"Off\".\n•\tAppuyez sur la touche  ou  du mode  pour choisir le \nmode de test que vous souhaitez lancer.\n\n0020130774_02 - 09/12 - Saunier Duval\n- 25 -\nINSTALLATION\nFR\n•\tMode de test \"P.01\" :  \n- Appuyez sur  pour afficher le réglage du forçage       \n  bruleur. L’écran affiche \"P.01\" et \"0\". \n- Appuyez sur la touche  ou  du mode  pour modifier     \n  la valeur du réglage de \"0\" (0%) à \"100\" (100%). \n- Appuyez sur  1 seconde pour sortir du sous menu ou    \nplus de 7 secondes pour acceder au menu paramétrage .\n•\tMode de test \"P.02\" à \"P.07\":  \n- Appuyez sur  pour lancer le mode de test. L’écran      \n  affiche \"P.0X\" et \"On\". \n- Le mode de test sera automatiquement arrêté au bout de     \n  15 minutes\n•\tLorsque vous avez terminé, appuyer sur RESET  ou faites un \nON/OFF sur l’appareil pour quitter le mode de test.\nCodeParamètreDescription\nP.01\nForçage du \nbrûleur à \npuissance \najustable en \nchauffage\nL’appareil fonctionne à une puissance \najustable de \"0\" (0% = Pmin.) à \n\"100\" (100% = Pmax.) en utilisant les \ntouches  ou  du mode  après un \nallumage réussi.\nP.02\nForçage du \nbrûleur à \npuissance \nallumage \nchauffage\nL’appareil fonctionne à la puissance \nallumage après un allumage réussi.\nP.03\nForçage du \nbrûleur à Pmax. \nchauffage\nL’appareil fonctionne à la puissance max. \nchauffage après un allumage réussi.\nP.05\nRemplissage de \nl'appareil \nLa vanne 3 voies est en position centrale,  \nla pompe et le brûleur s'arrêtent pour \nremplir l'appareil.\nP.06\nDégazage de \nl'installation\nLa fonction est activée pour une durée de 5 \nminutes sur le circuit chauffage.  \nAssurez-vous que le purgeur est ouvert.\nP.07\nDégazage de \nl'appareil\nLa fonction est activée pour une durée de 5 \nminutes sur le circuit court.  \nAssurez-vous que le purgeur est ouvert.\n11.3 Mesure du CO2\n24\n1\n2\n3\nLégende \n1    Vis de réglage de la puissance max. \n2    Prise de mesure\n3    Bouchon \n•\tEnlevez tout d’abord la façade étanche.\n•\tEnlevez le bouchon (3) puis raccordez un analyseur de CO2 par \nla prise de mesure (2).\n•\tActivez le mode de test \"P.01\" et réglez la valeur à 100 pour \nforcer l'appareil à Pmax. Reportez-vous au chapitre \"Modes de \ntest\".\n•\tAttendez environ 5 minutes pour lire une valeur de CO2 \nstabilisée.\n•\tSi la valeur n'est pas correcte, ajustez progressivement le \nréglage en tournant la vis (1) pour obtenir la valeur de CO2 \nindiquée dans le tableau ci-après.\nb\nTout scellage détruit doit être reconstitué.\nRéglageG25G31G20\nCO2 façade ouverte8.8 +/- 0.2 10.1 +/- 0.29 +/- 0.2 \nCO2 façade fermée9 +/- 0.310.3 +/- 0.39.2 +/- 0.3\n11.4 Nouvelle vérification et remise en \nfonctionnement\n•\tUne fois que l’appareil est installé, vérifiez son fonctionnement.\n•\tMettez l’appareil en fonctionnement pour vous assurer que \nles réglages sont opérationnels et vérifiez que l’appareil \nfonctionne en toute sécurité.\n•\tEffacez l'historique des codes défauts apparus sur l'appareil. \nPour ce faire, reportez-vous au chapitre \"Réglages à \nl'installation\" et utilisez le code \"d.94\".\n•\tVérifiez l'étanchéité de l'appareil (gaz et eau) et éliminez les \nfuites éventuelles.\n•\tVérifiez que les fumées sont évacuées correctement.\n•\tContrôlez l'ensemble des dispositif de commande et de \nsécurité, leurs réglages et leurs états de fonctionnement.\n12 Informations utilisateur\nAu terme de l’installation, l’installateur doit :\n -expliquer à l’utilisateur le fonctionnement de l’appareil, \ndes dispositifs de sécurité et, si nécessaire, faire une \ndémonstration et répondre aux questions\n -donner à l’utilisateur tous les documents relatifs à l'appareil \n -remplir les documents, le cas échéant\n -informer l’utilisateur sur les précautions à prendre pour ne pas \nendommager le système, l’appareil et le local.\n -rappeler à l’utilisateur de faire effectuer un entretien annuel.\n -expliquer à l'utilisateur comment vidanger l'appareil et lui \nmontrer les éléments à manipuler.\n\n0020130774_02 - 09/12 - Saunier Duval\n- 26 -\nMAINTENANCE\nFR\nMAINTENANCE\n13 Dépannage\n13.1 Diagnostic de pannes\n•\tAvant de procéder à un diagnostic spécifique, procédez aux \nvérifications suivantes :\n -Vérifiez qu’il n’y a pas de coupure du réseau électrique et que \nl’appareil est correctement branché.\n -Vérifiez l'alimentation en gaz de l'appareil.\n -Assurez-vous que les robinets d'arrêt soient ouverts.\n -Assurez-vous que l’indicateur de pression affiche une valeur \nde 0.8 bar; sinon, remplissez l'appareil.\n -Vérifiez le bon fonctionnement des organes de régulation \nexternes (thermostat d'ambiance, sonde extérieure, ...).\n -Si le symbole  et le message \"rE SEt\" s'affichent à l'écran, \nappuyez sur le bouton reset  pour redémarrer l'appareil.\n13.2 Historique des codes défauts\nCe menu permet d'afficher les 5 derniers codes défauts apparus \nsur l'appareil.\n•\tPour afficher l'historique des codes défauts, appuyez \nsimultanément sur les touches  et  du mode  pendant \nplus de 7 secondes. \nL'écran affiche le premier défaut \"01   XX\".\n•\tPour afficher les autres défauts apparus sur l'appareil, \nappuyez sur la touche  ou  du mode .\n•\tAppuyez sur la touche  pendant plus de 3 secondes pour \nsortir de ce menu.\nHistorique\nCode \ndéfaut\nDescription\n01XXReportez-vous au chapitre \"Codes défauts\".\n02XXReportez-vous au chapitre \"Codes défauts\".\n03XXReportez-vous au chapitre \"Codes défauts\".\n04XXReportez-vous au chapitre \"Codes défauts\".\n05XXReportez-vous au chapitre \"Codes défauts\".\n06XXReportez-vous au chapitre \"Codes défauts\".\n07XXReportez-vous au chapitre \"Codes défauts\".\n08XXReportez-vous au chapitre \"Codes défauts\".\n09XXReportez-vous au chapitre \"Codes défauts\".\n10XXReportez-vous au chapitre \"Codes défauts\".\n•\tPour effacer l'historique des codes défauts apparus sur \nl'appareil, reportez-vous au chapitre \"Réglages à l'installation\" \net utilisez le code \"d.94\".\n\n0020130774_02 - 09/12 - Saunier Duval\n- 27 -\nMAINTENANCE\nFR\n13.3 Codes défauts\ni\nLes pannes décrites dans ce chapitre doivent être \ntraitées par un professionnel qualifié et, si nécessaire, \npar le service après-vente.\nDescription\nCode \ndéfaut\nCauseSolution\nManque d'eau dans l'installation \n(<0.3 bar)\nF22\nRobinet d’arrivée d'eau fermé\nPompe déconnectée \nFuite dans l'installation\n• Remplissez l'installation.\n• Purgez l'installation.\n• Vérifiez les connexions de la pompe.\n• Vérifiez les connexions des capteurs départ et retour \nchauffage.\n• Vérifiez qu'il n'y a pas de fuite.\nAbsence d'eau dans l'installation : \npas d'élévation de température \nmais le brûleur est allumé\nF83\nDéfaut d’allumageF28\nPas d’arrivée de gaz / Débit gaz insuffisant \nMauvais réglage du mécanisme gaz \nElectrode d’allumage et de contrôle de flamme \ndéfectueuses  \nAllumeur défectueux \n• Vérifiez le circuit d’arrivée gaz (robinet gaz ouvert).\n• Vérifiez le réglage du mécanisme gaz.\n• Vérifiez les connexions de l’allumeur.\n• Vérifiez l’état de l'électrode (corrosion).\nPerte de flamme en fonctionnementF29\nFluctuation du signal de la flammeF 68\nDéfaut d’extraction ou de \nl’aspiration de l’air\nF32Vitesse du ventilateur incorrecte \n• Vérifiez l’arrivée d’air et l’évacuation des fumées.\n• Vérifiez les connections électriques du ventilateur.\nDéfaut de surchauffe\nF20Sécurité de surchauffe activée (97°C)\n• Vérifiez le fonctionnement de la pompe. \n• Vérifiez que les robinets d'arrêt départ et retour \nchauffage sont ouverts.\n-Mauvais dégazage\nDéfaut du capteur de température \ndépart chauffage\nF00Capteur déconnecté\n• Vérifiez les connexions du capteur.\n• Vérifiez les câbles du capteur.\n• Vérifiez le capteur.\nF10Court-circuit du capteur\nDéfaut du capteur de température \ndu ballon\nF13Court-circuit du capteur de température du ballon\nF79Défaut capteur de température du ballon\nDéfaut du capteur de pression \ncircuit chauffage\nF73Capteur de pression en court-circuit ou déconnecté\n• Vérifiez les connexions du capteur.\n• Vérifiez le capteur.\nF74Capteur de pression en défaut\nDéfaut capteur de température \nretour chauffage\nF01\nCapteur de température retour chauffage \ndéconnecté\n• Vérifiez les connexions du capteur. \n• Vérifiez les câbles du capteur. \n• Vérifiez le capteur.\nF11\nCourt-circuit du capteur de température retour \nchauffage\nDéfaut de tension EBUSF49\nDéfaut sur la ligne EBUS \nCourt circuit sur le connecteur EBUS\n• Vérifiez la charge sur la ligne EBUS.\nDéfaut de la carte principale\nF61Défaut de commande de la vanne gaz\n• Vérifiez l’ensemble des connexions de la carte \nprincipale.\n• Vérifiez la carte électronique.\n• Vérifiez le code produit.\n• Faites un reset de l’appareil.\nF62Défaut de fermeture de la vanne gaz\nF63Défaut de mémoire de la carte principale\nF64\nFluctuation rapide du capteur départ ou retour \nchauffage\nF65Température de la carte principale trop élevée\nF67Défaut du signal de flamme sur la carte principale\nDéfaut du moteur du mécanisme \ngaz\n-Court-circuit du moteur mécanisme gaz\n• Vérifiez les connexions du mécanisme gaz. \n• Vérifiez le fonctionnement du mécanisme gaz.\n• Vérifiez le fonctionnement de la pompe à \ncondensats (en option)\nF26Câbles déconnectés ou défectueux\nF77\nMécanisme gaz défectueux\nPompe à condensats défectueuse (en option)\nDéfaut de détection de flamme\nF27Détection de flamme anormale\n• Vérifiez l’électrode de détection de flamme. \n• Vérifiez la carte principale.\n• Vérifiez l'allumeur.\n-Mécanisme gaz défectueux\nDéfaut de l'interface utilisateur-Carte interface défectueuse• Remplacez la carte interface.\nDéfaut du capteur de température \ndépart chauffage\nF71\nCapteur de température départ chauffage déclipsé \nou défectueux (pas de variation de température)\n• Vérifiez les connexions du capteur.\n• Assurez-vous que le capteur est clipsé sur la \ntubulure.\nInterface utilisateur incompatible \navec la carte principale\nF70Mauvais code produit\n• Vérifiez que le code produit affiché à l'écran \ncorrespond au code produit de la plaque signalétique \n(en cas de défaut, le code produit ne s'affiche pas, \nreportez-vous au menu.d.93 réservé aux SAV). \n• Vérifiez la référence de la carte.\nDéfaut de circulation d’eauF24\nMauvais fonctionnement de la pompe (montée en \ntempérature trop rapide)\n• Vérifiez que les robinets d'arrêt départ et retour \nchauffage sont ouverts.\n\n0020130774_02 - 09/12 - Saunier Duval\n- 28 -\nMAINTENANCE\nFR\nDescription\nCode \ndéfaut\nCauseSolution\nEcart de température maximum \natteint entre départ et retour \nchauffage\nF23Problème de circulation d’eau\n• Vérifiez la connexion des capteurs départ et retour \nchauffage. \n• Vérifiez la vitesse de la pompe.\nEcart de température permanent \nentre les capteurs départ et retour \nchauffage\nF72\nIncohérence entre les températures départ et \nretour chauffage (écart permanent)\n• Vérifiez les connexions des capteurs de \ntempérature.\n• Remplacez les capteurs défectueux.\nF84\nCapteurs de température départ et retour \nchauffage inversés ou déconnectés\nCapteurs de température défectueux\nDéfaut du fusible thermiqueF76\nFusible thermique déconnecté\nFusible thermique défectueux\n• Vérifiez les connexions du fusible.\n• Remplacez le corps de chauffe.\nDéfaut des capteurs départ et retour \nchauffage\nF85\nCapteurs de température départ et retour \nchauffage connectés sur la même tubulure\n• Vérifiez les connexions des capteurs de \ntempérature.\nDéfaut contact plancher chauffantF86\nContact plancher chauffant ouvert\nCapteur déconnecté ou défectueux\n• Vérifiez les connexions du capteur.\n• Vérifiez que le capteur est connecté sur la carte \nprincipale et que le shunt est retiré.\n14 Changement de gaz\nb\nTout scellage détruit doit être reconstitué.\nPour un fonctionnement avec un gaz autre que celui prévu en \nusine, il faut effectuer certains réglages au niveau du mécanisme \ngaz.\n14.1 Réglages\n24\n1\n2\n3\nLégende \n1    Vis de réglage de la puissance max. \n2    Prise de mesure\n3    Bouchon \n•\tEnlevez tout d’abord la façade étanche.\n•\tEnlevez le bouchon (3) puis raccordez un analyseur de CO2 par \nla prise de mesure (2).\n14.1.1 Réglage du mécanisme gaz\n•\tAppuyez sur le bouton marche/arrêt pour mettre hors service \nl’appareil.\n•\tTournez la vis en respectant le sens et le nombre de tours \nindiqués dans le tableau ci-après.\nRéglage \nchangement \nde gaz\nModèleG20 ▸ G25G20 ▸ G31G31 ▸ G20\nF251.5 tour2 tours\nF30\n1.5 tour\n3 tours\nF351.5 tour2.5 tours\nF25\n2 tours\nF303 tours\nF352.5 tours\n14.1.2 Réglage de la puissance maximale \n•\tRéglez l'appareil sur le mode de test \"P.03 : forçage brûleur à \nP. max.\". Reportez-vous au chapitre \"Modes de test\".\n•\tAttendez environ 5 minutes pour lire une valeur de CO2 \nstabilisée.\n•\tComparez la valeur mesurée avec les valeurs indiquée dans le \ntableau ci-après.\nRéglage changement \nde gaz\nG20 ▸ G25G20 ▸ G31G31 ▸ G20\nCO2 façade ouverte8.8 ± 0.2 %10.1 ± 0.2 %9 ± 0.2 %\nCO2 façade fermée9 ± 0.3 %10.3 ± 0.3 %9.2 ± 0.3 %\n•\tVérifiez le taux de CO dans les produits de combustion et \ncomparez-le avec les valeurs indiquées au chapitre \"Données \ntechniques\" (il doit être inférieur à 500 ppm).\n\n0020130774_02 - 09/12 - Saunier Duval\n- 29 -\nMAINTENANCE\nFR\n14.1.3 Remise en service\n•\tRemettez en place le bouchon du coude de ventouse.\n•\tRemontez la façade étanche de l’appareil.\nNota : après remontage de la façade étanche, la valeur de CO2 \nchange et doit correspondre à celle indiquée dans le tableau ci-\ndessus.\n1\n\u0015\nLégende\n1    Emplacement étiquette changement de gaz\n2    Plaque signalétique\n•\tCollez l’étiquette de changement de gaz fournie avec l’appareil \nsur l’emplacement (1) du couvercle du boîtier électrique.\n•\tEn fonction des étiquettes de changement de gaz, cochez sur \nl'étiquette le type de gaz raccordé.\n14.2 Redémarrage et nouvelle vérification avant \nmise en fonctionnement\n•\tAvant de mettre l’appareil en fonctionnement, suivez les \nconsignes du chapitre Réglage spécifique.\n15 Vidange \n15.1 Circuit de chauffage \n1\nLégende\n1    Robinet de vidange chauffage\n•\tOuvrez le robinet de vidange (1) situé en dessous de la \nchaudière.\n•\tFaites une prise d’air en ouvrant, par exemple, un purgeur de \nl’installation.\n•\tPour vidanger uniquement l’eau du circuit chauffage présente \ndans l’appareil, fermez tout d’abord les robinets d’arrêt départ \net retour chauffage.\n15.2 Circuit d’eau chaude sanitaire  \n•\tFermez le robinet d'arrivée d’eau de l’installation.\n•\tFaites une prise d’air en ouvrant un robinet d’eau chaude.\n16 Maintenance\n•\tReportez-vous au chapitre \"Consignes de sécurité\" pour \nconsulter la liste des opérations à effectuer avant de procéder \nà la maintenance de l'appareil.\n•\tUne fois les opérations de maintenance terminées, reportez-\nvous au chapitre \"Mise en service\" pour redémarrer l'appareil.\n16.1 Maintenance annuelle\n16.1.1 Vérification des composants\n•\tVérifiez que le capteur de débit fonctionne correctement.\n•\tVérifiez que le mécanisme gaz module correctement.\n•\tVérifiez que les capteurs de température fonctionnent \ncorrectement.\n•\tVérifiez la qualité de l'ionisation.\n•\tVérifiez que le fusible thermique assure la protection de \nl'appareil contre les surchauffes.\n•\tVérifiez que le détecteur de pression fonctionne correctement.\n•\tVérifiez la pression du vase d'expansion.\n16.1.2 Autres vérifications\n•\tVérifiez le taux de CO2 dans les produits de combustion et \ncomparez-le avec les valeurs indiquées au chapitre \"Mesure \ndu CO2\".\n•\tVérifiez qu'il n'y a pas de fuites au niveau des joints, des \nsoupapes de sécurité et du disconnecteur.\n•\tVérifiez qu'il n'y a pas de fuites de gaz.\n•\tVérifiez l'état du joint du conduit d'évacuation des produits de \ncombustion.\n•\tVérifiez le raccordement à la terre de l'appareil.\n\n0020130774_02 - 09/12 - Saunier Duval\n- 30 -\nMAINTENANCE\nFR\n16.1.3 Nettoyage des composants\n•\tNettoyez les composants suivants :\n -Le filtre eau froide\n -Le filtre chauffage\n -Le récupérateur de condensats \n -Le corps de chauffe\n -Le brûleur\n -Le ventilateur\n16.1.4 Protection anti-corrosion et anti-boues\nPour éviter tout phénomènes de corrosion, il est recommandé \nd’ajouter un inhibiteur de corrosion dans l’eau du circuit \nchauffage. Cet inhibiteur aura pour résultat d’arrêter les réactions \nélectriques entre les différents métaux de l’installation. \nIl évitera aussi par voie de conséquence la formation de gaz qui \npourraient se produire lors des réactions chimiques.\nLe traitement d’eau est particulièrement important sur les \nplanchers chauffants car la basse température est favorable à \nla prolifération bactérienne. Il peut en résulter des boues qui \npeuvent boucher tout ou partie des circuits.\nLe dosage de ces produits nécessite de connaître le volume d’eau \ndans l’installation. Il est recommandé de noter ce volume pour de \nfuturs besoins.\nLes inhibiteurs doivent être compatibles avec les matériaux \nutilisés dans l’installation.\n16.2 Démontage de la façade avant\n24\nV\n230\nV\n2\n1\nC\nA\nA\nB\nLégende\n1    Façade avant\n2    Vis de fixation de la façade avant\n•\tRetirez la façade avant de l'appareil en respectant l’ordre des \nopérations (A) à (C).\n16.3 Démontage du silencieux\n24\nV\n230\nV\n2\n1\nB\nC\nA\nLégende\n1    Vis de fixation du silencieux\n2    Silencieux\n•\tRetirez la vis de fixation du silencieux (1).\n•\tEnlevez le silencieux (2).\n•\tNettoyez l’intérieur du silencieux avec un chiffon sec si \nnécessaire en prenant soin de ne pas abîmer la mousse \nintérieure.\n•\tProcédez dans l’ordre inverse des opérations pour remonter le \nsilencieux.\n16.4 Vase d'expansion\n24\nV\n230\nV\n1\nLégende\n1    Vase d'expansion\n•\tContrôlez la pression d’alimentation du vase d’expansion (voir \nchapitre \"Données techniques\") par la prise de pression située \nau-dessous du vase d'expansion et adaptez-la si nécessaire.\n•\tAprès le montage d’un vase d’expansion neuf, remplissez et \npurgez l’appareil, ou l’installation si nécessaire.\n\n0020130774_02 - 09/12 - Saunier Duval\n- 31 -\nMAINTENANCE\nFR\n16.5 Bloc hydraulique\n2\n1\n3\n4\n5\n6\n7\n8\n9\n10\n11\n12\n13\n14\n15\n16\n17\n18\n19\n20\n21\n22\n23\n24\n25\n26\nLégende\n1    Rallonge du robinet de remplissage\n2    Clip de fixation du filtre chauffage\n3    Filtre chauffage\n4    Clip de fixation de la tubulure sanitaire\n5    Robinet de remplissage\n6    Clip de fixation du robinet de remplissage\n7    Filtre eau froide\n8    Clip de fixation du filtre eau froide\n9    Connecteur du capteur de débit\n10    Capteur de débit\n11    Clip de fixation du capteur de débit\n12    Pompe\n13    Vis de fixation de la pompe\n14    Bouchon du purgeur\n15    Détecteur de pression circuit chauffage\n16    Connecteur du détecteur de pression circuit chauffage\n17    Echangeur sanitaire\n18    Clip de fixation de la soupape de sécurité sanitaire \n19    Soupape de sécurité sanitaire\n20    Connecteur de la vanne 3 voies\n21    Vanne 3 voies\n22    Disconnecteur\n23    Clip de fixation de la tubulure sanitaire\n24    Tubulure sanitaire\n25    Récupérateur de condensats\n26    Bouchon du récupérateur de condensats\n\n0020130774_02 - 09/12 - Saunier Duval\n- 32 -\nMAINTENANCE\nFR\n16.5.1 Filtre eau froide\n•\tFermez l’alimentation générale en eau froide.\n•\tDégagez le clip de fixation du filtre au froide (8).\n•\tEnlevez le filtre eau froide (7) et nettoyez-le.\n16.5.2 Filtre chauffage\nLe filtre chauffage améliore le dégazage du circuit chauffage.\n•\tFermez les robinets d’arrêt départ et retour chauffage, puis \nvidangez la chaudière.\n•\tDégagez le clip de fixation du filtre (2) placé sous la pompe. \n•\tEnlevez le filtre chauffage (3).\n•\tNettoyez puis remettez-le en place en positionnant \ncorrectement l’ergot. \n16.5.3 Récupérateur de condensats\na\nAttention : les condensats sont très acides, utilisez \ndes gants de protection.\n•\tPositionnez un récipient sous le récupérateur de condensats \n(25).\n•\tEnlevez le bouchon du récupérateur (26).\n•\tNettoyez les flexibles et enlevez les débris éventuellement \nprésents.\n•\tRemontez l’ensemble en prenant soin de bien positionner le \njoint d’étanchéité.\nb\nVérifiez que les condensats s'évacuent correctement \npar le flexible. Si ce n'est pas le cas, amorcez le \nsiphon en déversant ¼ de litre d'eau par l'orifice \nd'évacuation des produits de combustion.\n\n0020130774_02 - 09/12 - Saunier Duval\n- 33 -\nMAINTENANCE\nFR\n16.6 Bloc de combustion\n9\n10\n11\n12\n13\n14\n15\n16\n1\n2\n3\n4\n5\n6\n7\n8\nLégende\n1    Connecteur du mécanisme gaz\n2    Vis de fixation de l’électrode d’allumage et de contrôle de flamme\n3    Electrode d’allumage et de contrôle de flamme\n4    Joint de l'électrode d’allumage et de contrôle de flamme\n5    Ecrou de fixation de l’ensemble brûleur\n6    Vis de fixation de l’ensemble brûleur\n7    Connecteur du fusible thermique\n8    Extration fumée\n9    Serpentin \n10    Corps de chauffe \n11    Joint du brûleur\n12    Brûleur\n13    Mécanisme gaz\n14    Ventilateur\n15    Connecteur du ventilateur\n16    Tubulure gaz\n\n0020130774_02 - 09/12 - Saunier Duval\n- 34 -\nMAINTENANCE\nFR\n16.6.1 Démontage de l’ensemble brûleur\n•\tDémontez le silencieux (reportez-vous au chapitre \"Démontage \ndu silencieux\").\n•\tDéconnectez le connecteur de l’électrode d’allumage et de \ncontrôle de flamme (3) à partir de l’allumeur.\n•\tEnlevez la tubulure gaz (16). \n•\tRetirez les connecteurs du mécanisme gaz (1) et du ventilateur \n(15).\n•\tDesserrez les 4 écrous (5).\n•\tRetirez l’ensemble brûleur du corps de chauffe (10).\nLes vis (6) soudées sur le corps de chauffe ne doivent pas être \nendommagées. Dans le cas contraire, remplacez le corps de \nchauffe.\nL’isolation de la porte du brûleur sur l’ensemble brûleur ne doit \npas être endommagée. Dans le cas contraire, remplacez-la.\n16.6.2 Nettoyage du corps de chauffe \n•\tNettoyez le serpentin (9) du corps de chauffe (10) avec de \nl’eau.\n16.6.3 Contrôle du brûleur\nLe brûleur (12) ne nécessite aucun entretien et n’a pas besoin \nd’être nettoyé. \n•\tVérifiez que sa surface n’est pas endommagée. Remplacez le \nbrûleur si nécessaire.\n•\tAprès le contrôle ou le remplacement du brûleur, montez \nl’ensemble brûleur comme décrit au chapitre suivant.\n16.6.4 Montage de l’ensemble brûleur\nb\nAttention : A chaque démontage du brûleur, il est \nobligatoire de remplacer le joint (11) et au minimum \ntous les 5 ans..\n•\tPlacez l’ensemble brûleur sur le corps de chauffe (10).\n•\tSerrez progressivement les 4 écrous (5) dans un ordre croisé.\n•\tRemontez le silencieux.\n•\tRaccordez la tubulure gaz (16) avec un joint neuf sur \nl’ensemble brûleur.\n•\tBranchez le connecteur de l’électrode d’allumage et de \ncontrôle de flamme (3) sur l’allumeur.\n•\tBranchez le connecteur du mécanisme gaz (1) et du ventilateur \n(15).\n•\tOuvrez l’arrivée de gaz de l’appareil. \n•\tVérifiez l’étanchéité sur le raccord de gaz.\n16.7 Remplacement du câble d'alimentation\ne\nLe câble d'alimentation de l'appareil doit être \nremplacé par le fabricant, son service après-vente ou \ndes personnes de qualification similaire afin d'éviter \nun danger.\n•\tSi le câble d'alimentation est endommagé, remplacez-le en \nsuivant les recommandations du chapitre \"électrique\".\n17 Pièces de rechange\nAfin de garantir la sécurité du fonctionnement de l’appareil ainsi \nque sa longévité, utilisez des pièces d’origine agréées par le \nfabricant.\ni\nCet appareil porte le marquage CE de conformité. \nUtilisez uniquement des pièces détachées d’origine, \nneuves et agréées par le fabricant.\n•\tAssurez-vous que les pièces détachées sont correctement \ninstallées et positionnées dans le bon sens. Après toute \ninstallation de pièce et tout entretien, contrôlez l’appareil et \nvérifiez qu’il fonctionne correctement.\n\n0020130774_02 - 09/12 - Saunier Duval\n- 35 -\nDONNÉES TECHNIQUES\nFR\nDONNÉES TECHNIQUES\n18 Données techniques\nChaudière type C13, C33, C43, C43P, C93, B23P\nDescriptionUnitéF 25 F 30F35\nCatégorie gazll\n2Esi3P\nll\n2Esi3P\nll\n2Esi3P\nChauffage\nPuissance utile min. à 80°C/60°C (P min.)\nkW4.95.98.5\nPuissance utile max. à 80°C/60°C (P max.)\nkW18.124.530\nPuissance utile min. à 50°C/30°C (P min.)kW5.46.69.3\nPuissance utile max. à 50°C/30°C (P max.)kW19.626.732.8\nRendement sur P.C.I. à 80°C/60°C%97.797.798.3\nRendement sur P.C.I. à 50°C/30°C\n%106.2106.8 107.1\nRendement à charge partielle (30%) sur P.C.I. à 40°C/30°C%108.4109.2109.2\nNiveau de rendement selon la Directive Européenne 92/42-Condensation\nDébit calorifique minimal (Q min.)kW5.16.18.7\nDébit calorifique maximal (Q max.)kW18.52530.6\nDébit minimum de chauffagel/h400400400\nTempérature départ chauffage min.°C101010\nTempérature départ chauffage max. °C808080\nVase d’expansion, capacité utilel888\nPression de prégonflage du vase d’expansionbar0.750.750.75\nCapacité maxi. de l’installation à 75°Cl160160160\nSoupape de sécurité, pression maximale de service (PMS)bar333\nSanitaire\nPuissance utile min. (P min.)\nkW5.16.18.7\nPuissance utile max. (P max.)\nkW25.530.635.7\nDébit calorifique min. (Q min.)kW5.16.18.7\nDébit calorifique max. (Q max.)kW25.530.635.7\nTempérature eau chaude min.°C383838\nTempérature eau chaude max.°C606060\nDébit spécifique (D) selon EN 13203l/min12.214.617\nDébit spécifique selon EN 625l/min---\nConfort sanitaire selon EN 13203-*********\nDébit seuil de fonctionnementl/min1.91.91.9\nCapacité micro-accumulationl333\nLimiteur de débit eau froidel/min81010\nSoupape de sécurité, pression maximale de service (PMW)bar101010\nPression d’alimentation min.bar0.30.30.3\nPression d’alimentation conseillée (*)bar222\nPression d’alimentation max. (**)bar101010\n(*) Réglage conseillé pour le remplissage de l’installation compte tenu de la perte de charge du disconnecteur.\n(**) Pour une pression d'alimentation supérieure à 3 bar, il est conseillé d'installer un réducteur de pression.\n\n0020130774_02 - 09/12 - Saunier Duval\n- 36 -\nDONNÉES TECHNIQUES\nFR\nDescriptionUnitéF 25 F 30F35\nCombustion\nDébit d’air neuf (1013 mbar - 0°C)\nm\n3\n/h\n22.129.836.5\nDébit d’évacuation des gaz brûlés à Pmin.g/s2.32.84\nDébit d’évacuation des gaz brûlés à Pmax.g/s8.311.313.8\nDébit d’évacuation des gaz brûlés en mode eau chaude sanitaireg/s11.513.816\nTempérature fumées à P min. 80°C/60°C°C66.859.672\nTempérature fumées à P min. 50°C/30°C°C47.139.347.4\nTempérature fumées à P max. 80°C/60°C°C65.763.472\nTempérature fumées à P max. 50°C/30°C°C48.84455.8\nTempérature des fumées en surchauffe°C10595104\nTempérature des fumées en mode eau chaude sanitaire°C70.76875\nValeurs des produits de la combustion (mesurée au débit calorifique nominal et avec le gaz de référence G20, en chauffage) :\nCO\nppm 98.3103.680\nmg/kWh105110.685.3\nCO2 %9.29.29.2\nNOx pondéré\nppm 22.621.918.4\nmg/kWh39.938.632.6\nElectrique\nTension d’alimentationV/Hz\n230V \n50Hz\n230V \n50Hz\n230V \n50Hz\nPuissance maximale absorbéeW181181181\nIntensitéA0.790.790.79\nFusibleT 2A/250VT 2A/250VT 2A/250V\nProtection électriqueIPX4DIPX4DIPX4D\nClasse électriqueIII\nDescriptionUnitéF 25F 30F35\nDimensions :\nHauteurmm740740740\nLargeurmm418418418\nProfondeurmm344344344\nPoids netkg38.43939.6\nNuméro CE\n1312 \nBU 5334\n1312\nBU 5335\n1312\nBV 5336 \nDescriptionUnitéF 25F 30F35\nGaz naturel G 20 (*)\nDébit gaz à puissance maximale sanitaire\nm\n3\n/h\n2.703.243.77\nDébit gaz à puissance maximale chauffage\nm\n3\n/h\n1.962.653.24\nDébit gaz à puissance minimale\nm\n3\n/h\n0.540.650.92\nPression d’alimentation en gazmbar202020\nGaz naturel G 25 (*)\nDébit gaz à puissance maximale sanitaire\nm\n3\n/h\n3.143.774.39\nDébit gaz à puissance maximale chauffage\nm\n3\n/h\n2.283.083.76\nDébit gaz à puissance minimale\nm\n3\n/h\n0.630.751.07\nPression d’alimentation en gazmbar252525\nGaz liquide G 31 (*)\nDébit gaz à puissance maximale sanitairekg/h1.982.382.77\nDébit gaz à puissance maximale chauffagekg/h1.441.942.37\nDébit gaz à puissance minimalekg/h0.400.470.67\nPression d’alimentation en gaz mbar373737\n(*) réf. 15°C - 1013 mbar gaz sec\n\n\n\n0020130774_02 - 09/12\nSous réserve de modifications techniques\nVAILLANT GROUP FRANCE SA\n«Le Technipole» - 8, avenue Pablo Picasso\n94132 Fontenay-sous-Bois cedex – France\nTéléphone : 01 49 74 11 11\nTélécopie : 01 48 76 89 32\nSA au capital de 7.328.460 Euros\n301 917 233 RCS CRETEIL\nwww.saunierduval.fr",
  "pages": 40,
  "metadata": {
    "marque": "saunier duval",
    "modele": "themaplus condens",
    "type": "chaudiere"
  },
  "sections": {
    "themaplus_condens": "F 25\nF 30\nF 35\ncondens",
    "manuel_dinstallation": "- 1 -",
    "guide_dinstructions_3": "1.1 Documentation produit .......................................................................................3\n1.2 Documents associés  ...........................................................................................3\n1.3 Explication des symboles ....................................................................................3",
    "description_de_lappareil_3": "2.1 Dispositifs de sécurité  ........................................................................................3\n2.2 Plaque signalétique ............................................................................................4\n2.3 Classe de gaz  .....................................................................................................4\n2.4 Réglementation et dispositions législatives ..........................................................4\n2.5 Schéma hydraulique  ..........................................................................................5",
    "consignes_de_scurit_et_rglemen": "3.1 Consignes de sécurité\nSi la pression de gaz à l’entrée de l’appareil est en dehors\nde la plage spécifiée, l’appareil ne doit pas être mis en\nfonctionnement.\ne",
    "recyclage_7": "4.1 Appareil .............................................................................................................7\n4.2 Emballage ..........................................................................................................7",
    "emplacement_de_lappareil_8": "5.1 Emplacement ......................................................................................................8\n5.2 Accessibilité .......................................................................................................8",
    "installation_de_lappareil_8": "6.1 Liste du matériel livré ..........................................................................................8",
    "2_recommandations_avant_instal": "6.2.1 Conception du circuit sanitaire\nLe circuit de distribution sera réalisé de manière à éviter au\nmaximum les pertes de charge (limiter le nombre de coudes,\nutiliser des robinetteries à forte section de passage afin de\npermettre un débit suffisant).\nL'appareil peut fonctionner avec une pression d’alimentation\nminimale. Un meilleur confort d’utilisation sera obtenu à partir de\n0.8 bar de pression d’alimentation.\n6.2.2 Conception du circuit chauffage",
    "connexion_hydraulique_11": "7.1 Raccordement gaz et eau ...................................................................................11\n7.2 Raccordement du récupérateur de condensats ....................................................12\n8 Évacuation des gaz de combustion ..............................................................................................12\n8.1 Réglementation ................................................................................................12\n8.2 Description de la configuration d’évacuation des gaz de combustion ....................14",
    "connexion_lectrique_18": "9.1 Accès au tableau principal .................................................................................18\n9.2 Carte principale ................................................................................................18\n9.3 Accessoires externes .........................................................................................18\n9.4 Schéma électrique ............................................................................................19",
    "mise_en_service_20": "10.1 Première mise en fonctionnement ......................................................................20",
    "2_remplissage_de_linstallation": "•\tAssurez-vous que le robinet d'arrivée d'eau froide de",
    "rglages_spcifiques_21": "11.1 Réglage du circuit de chauffage..........................................................................21\n11.2 Réglages techniques de l’appareil et liste des paramètres ...................................22\n11.3 Mesure du CO2 .................................................................................................25\n11.4 Nouvelle vérification et remise en fonctionnement ..............................................25",
    "table_des_matires": "FR\n0020130774_02 - 09/12 - Saunier Duval\n- 3 -",
    "dpannage_26": "13.1 Diagnostic de pannes ........................................................................................26\n13.2 Historique des codes défauts .............................................................................26\n13.3 Codes défauts ...................................................................................................27",
    "changement_de_gaz_28": "14.1 Réglages ..........................................................................................................28\n14.2 Redémarrage et nouvelle vérification avant mise en fonctionnement ....................29",
    "vidange_29": "15.1 Circuit de chauffage  ..........................................................................................29\n15.2 Circuit d’eau chaude sanitaire   ..........................................................................29",
    "1_maintenance_annuelle_29": "16.2 Démontage de la façade avant ...........................................................................30\n16.3 Démontage du silencieux ..................................................................................30\n16.4 Vase d'expansion ..............................................................................................30\n16.5 Bloc hydraulique ...............................................................................................31\n16.6 Bloc de combustion ...........................................................................................33\n16.7 Remplacement du câble d'alimentation ..............................................................34",
    "pices_de_rechange_34": "DONNÉES TECHNIQUES",
    "introduction": "FR\n3.2.2 Etablissements recevant du public (ERP)\nPar «établissements recevant du public», l’article R 123-\n2 du Code de la construction et de l’habitation désigne les\n«bâtiments, locaux et enceintes dans lesquels des personnes\nsont admises soit librement, soit moyennant une rétribution ou\nune participation quelconque, ou dans lesquels sont tenues des\nréunions ouvertes à tout venant ou sur invitation, payantes ou\nnon».\nLes textes réglementaires applicables à ces établissements sont :\n-d’une part, les articles R 123-1 à R 123-55 du Code de la\nconstruction et de l’habitation (ancien décret du 31 octobre\n1973);\n-d’autre part, le règlement de sécurité contre les risques\nd’incendie et de panique dans les établissements rece-\nvant du public qui peut être, selon la nature de l’activité de\nl’établissement, soit le règlement issu de l’arrêté du 23 mars\n1965 modifié, soit celui approuvé par l’arrêté du 25 juin 1980\nmodifié.",
    "guide_dinstructions": "1.1 Documentation produit\nLe manuel fait partie intégrante de l’appareil et doit être remis\nà l’utilisateur lorsque l’appareil est installé, conformément aux\nréglementations en vigueur.\n•\tLisez ce manuel attentivement afin de comprendre l’intégralité",
    "des_informations_et_de_garanti": "et un entretien en toute sécurité. Nous déclinons toute\nresponsabilité en cas de dommages occasionnés par le non-\nrespect des consignes figurant dans le présent manuel.\n1.2 Documents associés\n-1 notice d'emploi\n-1 magnet\n-1 carte \"Installateur confiance\"\n-1 carte de \"Demande de garantie\"\n-2 étiquettes de changement de gaz\ni\nLa demande de garantie est à remettre au technicien\nde la Station Technique Agréée lors de la mise en\nservice de l’appareil.\n1.3 Explication des symboles\na\nDANGER : Risque de blessure corporelle.\ne\nDANGER : Risque de choc électrique.\nb\nATTENTION : Risque de dégradation de l’appareil ou\nde son environnement.\ni\nIMPORTANT : Information utile.",
    "description_de_lappareil": "2.1 Dispositifs de sécurité\n2.1.1 Sécurité de surchauffe\nL'appareil est conçu pour identifier les possibles cas de\nsurchauffe et pour s'arrêter avant qu'une surchauffe se produise.\n2.1.2 Soupape de sécurité\nUne soupape de sécurité chauffage et une soupape de sécurité\nsanitaire sont installées sur cet appareil.\n-La soupape de sécurité chauffage s'ouvre dès que la pression\ndans le circuit chauffage dépasse 3 bar.\n-La soupape de sécurité sanitaire s'ouvre dès que la pression\ndans le circuit sanitaire dépasse 10 bar.\n2.1.3 Protection de l'appareil contre le gel\nLe système de protection contre le gel commande la mise\nen fonctionnement de la pompe de l'appareil dès lors que la\ntempérature dans le circuit de chauffage descend en dessous\nde 12°C. La pompe s’arrête dès que la température de l’eau\ncontenue dans le circuit de chauffage atteint 15°C. Si la\ntempérature dans le circuit de chauffage descend en dessous de\n7°C, le brûleur s’allume et fonctionne tant que cette température\nest inférieure à 35°C.\nLe dispositif de protection contre le gel est actif lorsque l'appareil\nest allumé.",
    "la_protection_de_linstallation": "uniquement par l'appareil. Un thermostat d’ambiance est",
    "ncessaire_pour_contrler_la_tem": "b\nATTENTION : Votre circuit d'eau sanitaire (froide ou\nchaude) n'est pas protégé par la chaudière.\n2.1.4 Evacuation des condensats\nPendant les périodes de gel, il est possible que de la glace se\nforme dans le tuyau d'évacuation des condensats s'il est situé à\nl'extérieur de l'habitation. Dans ce cas, un dispositif de sécurité\narrête l'appareil.\n0020130774_02 - 09/12 - Saunier Duval\n- 4 -",
    "plaque_signaltique": "•\tCollez l’étiquette de changement de gaz fournie avec l’appareil\nsur l’emplacement (1) du couvercle du boîtier électrique.\n•\tEn fonction des étiquettes de changement de gaz, cochez sur\nl'étiquette le type de gaz raccordé.\n14.2 Redémarrage et nouvelle vérification avant\nmise en fonctionnement\n•\tAvant de mettre l’appareil en fonctionnement, suivez les\nconsignes du chapitre Réglage spécifique.",
    "les_types_dinstallation_de_ven": "-Le code produit\n-La catégorie de gaz de l'appareil\n-La nature, le groupe et la pression du gaz réglé en usine\n-Le débit spécifique (D)\n-La pression maximale de service du circuit chauffage (PMS)\n-La pression maximale de service du circuit sanitaire (PMW)\n-La classe NOx de l'appareil\n-La nature et la tension d'alimentation\n-La puissance maximale absorbée\n-L'indice de protection électrique\n-Le débit calorifique minimal et maximal (Q)\n-La puissance utile minimale et maximale (P)\n-Le numéro et le logo CE\na\nL’appareil doit impérativement être raccordé au(x)\ntype(s) de gaz indiqué(s) sur la plaque signalétique.\n2.3 Classe de gaz\nCette chaudière est dédiée pour fonctionner uniquement aux G20\nou G31, mais elle peut être adaptée pour être raccordée aux G20,\nG25 et G31.\n•\tConsultez la plaque signalétique pour connaître le type de gaz\npour lequel l'appareil a été réglé en usine.\nGaz réglé en usineChangements de gaz possibles\nG20G25, G31\nG31G20, G25\n•\tPour adapter l'appareil à un autre type de gaz, reportez-vous\nau chapitre \"Changement de gaz\".\n2.4 Réglementation et dispositions législatives\nMarquage CE\nLe marquage CE indique que les appareils décrits dans le présent\nmanuel sont conformes aux directives suivantes :\n-Directive Européenne n°2009-142 relative aux appareils à gaz\n-Directive Européenne n°2004-108 du Parlement Européen et\ndu Conseil relative à la compatibilité électromagnétique\n-Directive Européenne n°2006-95 du Parlement Européen et du\nConseil relative à la basse tension\n-Directive Européenne n°92-42 relative au rendement des\nchaudières\n0020130774_02 - 09/12 - Saunier Duval\n- 5 -",
    "rcuprateur_de_condensats": "•\tAmorcez le bouchon (1) du récupérateur de condensats en le\nremplissant avec de l'eau.\n•\tActivez les fonctions sanitaire et chauffage de votre appareil.\n•\tFaites fonctionner l’appareil au moins 15 minutes en chauffage\navec une température de consigne chauffage supérieure",
    "robinet_darrt_du_dpart_chauffa": "A    Retour chauffage\nB    Arrivée eau froide\nC   Départ chauffage\nD    Départ eau chaude\nE   Arrivée gaz\nF   Evacuation des condensats\n0020130774_02 - 09/12 - Saunier Duval\n- 6 -",
    "une_installation_incorrecte_pe": "électrique voire détériorer l’appareil.\nLe branchement électrique de l’appareil ne doit être\neffectué que par un professionnel qualifié.\nL’appareil doit être branché directement à une prise de courant\naccessible, fixe et commutable.\nLe câblage extérieur doit être relié à la terre. La polarité doit être\ncorrecte et conforme aux normes en vigueur.\nLe fabricant décline toute responsabilité en cas de dommages\ncausés à des tiers par une mise à la terre incorrecte de l’appareil.\nCela inclut le non-respect des normes en vigueur.\nDes protections supplémentaires peuvent être requises à",
    "lors_de_linstallation_et_de_la": "l’appareil, les arrêtés, directives, règles techniques, normes et\ndispositions ci-dessous doivent être respectés dans leur version\nactuellement en vigueur :\n3.2.1 Bâtiments d’habitation:\n-Arrêté du 2 Août 1977 modifié, relatif aux règles techniques et",
    "de_scurit_applicables_aux_inst": "et d’hydrocarbures liquéfiés situées à l’intérieur des bâtiments\nd’habitation et de leurs dépendances.",
    "nf_dtu_611_norme_p_45204_insta": "locaux d’habitation.\n-NF DTU 65.14 (norme P 52-307) Exécution de planchers\nchauffants à eau chaude.\nDOMAINE D’APPLICATION\nLa classe 2 définie dans ce guide technique correspond à",
    "des_installations_de_type_bass": "par exemple des panneaux rayonnants constitués de tubes\ndisposés dans le plancher du local, parcourus par de l’eau dont\nla température est normalement inférieure ou égale à 50°C et\npouvant subir des pointes accidentelles à 65°C. Un dispositif\nparticulier limite impérativement la température de l’eau à 65°C\nau plus.\nSECURITE\nUn dispositif de sécurité indépendant de la régulation, avec\nréarmement manuel et fonctionnant même en l’absence de\ncourant ou de fluide moteur, coupe impérativement la fourniture\nde chaleur dans le circuit des panneaux lorsque la température\ndu fluide atteint 65°C.\n-NF DTU 24.1 (norme P 51-201) \"Travaux de fumisterie\n- Systèmes d’évacuation des produits de combustion\ndesservant un ou des appareils\".",
    "norme_nf_c_15100_relative_lins": "raccordés au réseau électrique.\n-Norme NF C 73-600 relative à l’obligation de raccordement des\nappareils électriques à une prise de terre.\n-Règlement Sanitaire Départemental.\n0020130774_02 - 09/12 - Saunier Duval\n- 7 -",
    "recyclage": "i\nLe recyclage de l’emballage doit être effectué par le\nprofessionnel qualifié qui a installé l’appareil.\n4.1 Appareil\nL’appareil est principalement constitué de matériaux recyclables.\nCe symbole signifie que cet appareil ne doit pas être\njeté avec les ordures ménagères, qu’il fait l’objet\nd’une collecte sélective en vue de sa valorisation, de\nsa réutilisation ou de son recyclage.\n•\tConfiez l’appareil à un point de collecte approprié pour le\ntraitement, la valorisation, le recyclage des déchets.\ni\nEn respectant cette directive, vous faites un geste pour\nl’environnement, vous contribuez à la préservation\ndes ressources naturelles et à la protection de la santé\nhumaine.\n4.2 Emballage\nNous vous conseillons de recycler l’emballage de l’appareil de\nmanière responsable.\n•\tTriez les déchets de manière à séparer ceux qui peuvent être\nrecyclés (cartons, plastiques...) et ceux qui ne peuvent pas être\nrecyclés (cerclage...).\n•\tEliminez ces déchets conformément à la réglementation en\nvigueur.\n0020130774_02 - 09/12 - Saunier Duval\n- 8 -",
    "installation": "FR\n•\tMode de test \"P.01\" :\n- Appuyez sur  pour afficher le réglage du forçage\nbruleur. L’écran affiche \"P.01\" et \"0\".\n- Appuyez sur la touche  ou  du mode  pour modifier\nla valeur du réglage de \"0\" (0%) à \"100\" (100%).\n- Appuyez sur  1 seconde pour sortir du sous menu ou\nplus de 7 secondes pour acceder au menu paramétrage .\n•\tMode de test \"P.02\" à \"P.07\":\n- Appuyez sur  pour lancer le mode de test. L’écran\naffiche \"P.0X\" et \"On\".\n- Le mode de test sera automatiquement arrêté au bout de\n15 minutes\n•\tLorsque vous avez terminé, appuyer sur RESET  ou faites un\nON/OFF sur l’appareil pour quitter le mode de test.\nCodeParamètreDescription\nP.01\nForçage du\nbrûleur à\npuissance\najustable en\nchauffage\nL’appareil fonctionne à une puissance\najustable de \"0\" (0% = Pmin.) à\n\"100\" (100% = Pmax.) en utilisant les\ntouches  ou  du mode  après un\nallumage réussi.\nP.02\nForçage du\nbrûleur à\npuissance\nallumage\nchauffage\nL’appareil fonctionne à la puissance\nallumage après un allumage réussi.\nP.03\nForçage du\nbrûleur à Pmax.\nchauffage\nL’appareil fonctionne à la puissance max.\nchauffage après un allumage réussi.\nP.05\nRemplissage de\nl'appareil\nLa vanne 3 voies est en position centrale,\nla pompe et le brûleur s'arrêtent pour\nremplir l'appareil.\nP.06\nDégazage de",
    "emplacement_de_lappareil": "5.1 Emplacement\nConsignes\n•\tAvant de choisir l’emplacement de l’appareil, lisez\nattentivement les mises en garde relatives à la sécurité ainsi\nque les consignes du manuel d’utilisation et du manuel",
    "dinstallation": "•\tVérifiez que la structure du mur sur lequel doit être installé\nl’appareil permet de supporter le poids de l’appareil.\n•\tVérifiez que l’espace dans lequel doit être posé l’appareil",
    "permet_une_installation_correc": "est respectée. Vous devez vous assurer que les raccords\nd'alimentation en eau, gaz et à l’évacuation des gaz de\ncombustion sont accessibles pour être vérifiés (voir le chapitre\n\"Accessibilité\").\n•\tExpliquez ces exigences à l’utilisateur.\n•\tN’installez pas l’appareil au-dessus d’un autre appareil\nqui pourrait l’endommager (par exemple, au-dessus d’une\ncuisinière susceptible de dégager de la vapeur et des graisses)\nou dans une pièce fortement chargée en poussière ou dont\nl’atmosphère est corrosive.\n•\tL’emplacement de montage doit être à l’abri du gel toute\nl’année. Si cette condition ne peut être respectée, informez\nl’utilisateur et conseillez-lui de prendre les mesures qui\ns’imposent.\n5.2 Accessibilité\n•\tPour permettre un entretien périodique, respectez les\ndistances indiquées sur le schéma ci-après.\n600\nmin.\n0\nmin.\n0\nmin.\n300\nmin.\n300\nmin.\nØA\nØA + 5 min.",
    "installation_de_lappareil": "6.1 Liste du matériel livré\nL'appareil est livré en un seul colis avec un sachet de documents\net un sachet d'accessoires.\nLa plaque de raccordement commandée séparément est livrée\nen un seul colis avec un gabarit de perçage et une barrette de\nfixation.\ni\nLes colis de ventouse seront commandés en fonction",
    "de_la_configuration_de_linstal": "•\tVérifiez le contenu des colis.\n0020130774_02 - 09/12 - Saunier Duval\n- 9 -",
    "6_manuel_dinstallationx1": "4Gabarit de perçage (*)(x1)\n5Plaque de raccordement (*)(x1)\n6Barrette de fixation (*)(x1)\n(*)Commandés séparément",
    "lappareil_peut_tre_intgre_tous": "bi-tube, mono-tube série ou dérivé, plancher chauffant, etc...\nLes surfaces de chauffe peuvent être constituées de radiateurs,\nde convecteurs, d’aérothermes ou de planchers chauffant. Dans",
    "le_cas_dun_plancher_chauffant_": "d’un dispositif de limitation de température à 54°C sur le départ\n(voir chapitre \"Raccordements électriques\"). Ce dispositif non\nfourni, doit pouvoir absorber par son inertie les trains de chaleur\nconsécutifs.\nAttention ! Si les matériaux utilisés sont de nature différente,\nil peut se produire des phénomènes de corrosion. Dans ce cas,\nil est recommandé d’ajouter à l’eau du circuit chauffage un\ninhibiteur (dans les proportions indiquées par son fabricant) qui\névitera la production de gaz et la formation d’oxydes.\nLes sections des canalisations seront déterminées en utilisant la\ncourbe débit/ pression (Reportez-vous au chapitre \"Réglage du\ncircuit chauffage\"). Le réseau de distribution sera calculé selon\nle débit correspondant à la puissance réellement nécessaire\nsans tenir compte de la puissance maximale que peut fournir\nl'appareil. Il est toutefois recommandé de prévoir un débit\nsuffisant pour que l’écart de température entre départ et retour\nsoit inférieur ou égal à 20°C. Le débit minimal est indiqué dans le\nchapitre \"Données techniques\" en fin de manuel.\nLe tracé des tuyauteries sera conçu afin de prendre toutes les\ndispositions nécessaires pour éviter les poches d’air et faciliter le",
    "dgazage_permanent_de_linstalla": "prévus à chaque point haut des canalisations ainsi que sur tous\nles radiateurs.\nLe volume d’eau total admissible pour le circuit de chauffage\ndépend, entre autres, de la charge statique à froid.\nLe vase d’expansion incorporé à l'appareil est livré réglé en\nusine (Reportez-vous au chapitre \"Données techniques\" en fin de\nmanuel). Il est possible de modifier, à la mise en service, cette\npression de gonflage en cas de charge statique plus élevée.\nIl est recommandé de prévoir un robinet de vidange au point le",
    "plus_bas_de_linstallation": "Dans le cas d’utilisation de robinets thermostatiques, il est\nimpératif de ne pas en équiper la totalité des radiateurs en\nveillant à poser ces robinets dans les locaux à fort apport et\njamais dans le local où est installé le thermostat d’ambiance.",
    "_sil_sagit_dune_ancienne_insta": "rincer le circuit radiateurs avant d’installer le nouvel appareil.\n0020130774_02 - 09/12 - Saunier Duval\n- 10 -",
    "linstallation_sont_compatibles": "•\tDéterminez l’emplacement de montage. Reportez-vous au\nchapitre \"Choix de l’emplacement\".\nLa fixation de la barrette devra être adaptée aux caractéristiques\ndu mur porteur et devra tenir compte du poids de la chaudière\n(voir chapitre \"Données techniques\" en fin de manuel).\n748\n65.5\n811\n=320=\n=276=\nØ105\n0\n55\n57.5\n57.5\n55\n•\tPercez les trous des vis de fixation conformément au gabarit\nde perçage livré avec la plaque de raccordement de l’appareil.\n3\n2\n1\n4\nLégende",
    "plaque_de_raccordement": "0020130774_02 - 09/12 - Saunier Duval\n- 11 -",
    "connexion_hydraulique": "7.1 Raccordement gaz et eau\n•\tAvant d’effectuer toute opération, procédez à un nettoyage\nsoigné des canalisations à l’aide d’un produit approprié\nafin d’éliminer les impuretés telles que limailles, soudures,\nhuiles et graisses diverses pouvant être présentes. Ces\ncorps étrangers seraient susceptibles d’être entraînés dans\nl'appareil, ce qui en perturberait le fonctionnement.\n•\tN’utilisez pas de produit solvant à cause du risque\nd’endommagement du circuit.\n•\tNe brasez pas les tubulures montées en place : cette opération\nrisque d'endommager les joints et l’étanchéité des robinets.\n•\tN'utilisez que les joints d'origine fournis avec l'appareil.\n•\tVérifiez qu’il n’y a pas de fuite. Réparez si nécessaire.\nmur\n2\n3\n45\n1\n6\n149,5\nLégende",
    "douille_arrive_eau_froide_1_cr": "+ 1 écrou ½",
    "douille_eau_chaude_sanitaire_1": "+ 1 écrou ½\"",
    "plaque_de_raccordement_flexibl": "3\n1\n2\n4\n2\nLégende\nA    Test d'étanchéité du circuit chauffage + remplissage du circuit\nchauffage\nB    Test d'étanchéité du circuit sanitaire",
    "dpart_eau_chaude_sanitaire": "-Configuration A :\nLe flexible (2) permet de faire les tests d’étanchéité sur le circuit\nchauffage et d'effectuer le remplissage du circuit chauffage.\n-Configuration B :\nLe flexible (2) permet de faire les tests d’étanchéité sur le circuit\nsanitaire.\n1\n2\n3\n4\n6\n5\n7\n8\n9\nLégende",
    "flexible_dvacuation_des_soupap": "sanitaire",
    "evacuation_vers_les_gouts_siph": "•\tRaccordez les soupapes de sécurité et le disconnecteur à un\ncircuit d’évacuation vers les égouts en utilisant les flexibles\nfournis. Le dispositif d’évacuation doit permettre de voir\nl’écoulement de l’eau.\n•\tEmboîtez la rallonge bleue (3) sur le robinet de remplissage (4).\n0020130774_02 - 09/12 - Saunier Duval\n- 12 -",
    "laide_de_la_notice_dinstallati": "•\tExpliquez ces exigences à l’utilisateur de l’appareil.\n0020130774_02 - 09/12 - Saunier Duval\n- 13 -",
    "_80125_mm_installation_de_type": "a\nAttention ! Si la configuration de sortie des fumées est\nsituée à moins de 1.80 m du sol, vous devez installer\nun kit de protection terminal.\nb\nAttention ! Les orifices d’un terminal pour conduits\nséparés doivent déboucher dans un carré de 50 cm\nde côté.\nØ 60/100 mm\nL\n63\n1\nLégende",
    "joint": "TypeLongueur max.\nØ 60/10010 m\nØ 80/12525 m\nChaque fois qu‘un coude à 90° supplémentaire est nécessaire (ou\n2 à 45°), la longueur (L) doit être réduite de 1 m.\n8.2.2 Système ventouse verticale Ø 60/100 mm ou Ø",
    "125_mm_installation_de_type_c3": "a\nAttention ! Si la configuration de sortie des fumées est\nsituée à moins de 1.80 m du sol, vous devez installer\nun kit de protection terminal.\nb\nAttention ! Les orifices d’un terminal pour conduits\nséparés doivent déboucher dans un carré de 50 cm\nde côté.\nL\nTypeLongueur max.\nØ 60/10010 m\nØ 80/12525 m\nChaque fois qu’un coude à 90° supplémentaire est nécessaire (ou\n2 à 45°), la longueur (L) doit être réduite de 1 m.\n0020130774_02 - 09/12 - Saunier Duval\n- 15 -",
    "_60100_mm_installation_de_type": "b\nAttention ! Les liaisons au conduit seront réalisées à\nl'aide de l'accessoire spécialement développé par le\nfabricant de l'appareil.\nb",
    "une_chaudire_raccorde_une_inst": "doit être connectée uniquement sur des cheminées à\ntirage naturel.\nb\nL'écoulement des condensats provenant des\nsystèmes de conduit collectif n'est pas autorisé dans\nla chaudière.\nB\nA\n1\n2\n3\n4\n5\nL\nLégende",
    "trappe_de_visite": "A    Dernier étage\nB    Ré de chaussée\nL      Longueur max.\nTypeLongueur max.\nØ 60/10010 m\nChaque fois qu‘un coude 90° supplémentaire est nécessaire (ou 2\nà 45°), la longueur (L) doit être réduite de 1 m.\n8.2.4 Système ventouse pour conduit collectif sous",
    "pression_80125_mm_installation": "C43P)\na\nAttention ! Lors de la pose ou de la dépose de\nl'appareil, il y a risque de pollution dans la pièce par\nles produits de combustion.\nAssurez-vous de l'étanchéité du conduit.\nb\nAttention ! Les liaisons au conduit seront réalisées à\nl'aide de l'accessoire spécialement développé par le\nfabricant de l'appareil.\nL\n153\n1\nLégende",
    "clapet_0020081283": "Si d’autres appareils raccordés au conduit collectif sont en\nfonctionnement, le clapet (1) dans le circuit de combustion évite\nla circulation inverse des fumées quand l'appareil est arrêté.\nChaque fois qu’un coude à 90° supplémentaire est nécessaire (ou\n2 à 45°), la longueur (L) doit être réduite de 1 m.\n•\tReportez-vous au chapitre \" Réglages spécifiques ▸ Réglages",
    "_linstallation_et_renseignez_l": "valeur indiquée dans les tableaux suivant.\nDescriptionUnitéF 25\nGazG20\nMode\nQnkW5,616,823,5\nPu (80/60)kW5,316,4-\nPu (50/30)kW617,8-\nPukW--23,5\nCO2%8,99,29,2\nDébit massique des fuméesg/s2,67,610,6\nTempérature des fumées (80°C/60°C)°C6364-\nTempérature des fumées (50°C/30°C)°C4950-\nTempérature des fumées °C--71\nPression sortie de chaudièrePa2980136\nParamètre d.85kW7\n0020130774_02 - 09/12 - Saunier Duval\n- 16 -",
    "chemine_installation_de_type_c": "Cette configuration permet de réutiliser un ancien conduit de\nfumée ou de ventilation pour l’implantation d’un conduit de\nchaudière étanche. La longueur du conduit vertical (L2) est un\nflexible d’évacuation des fumées Ø 80 mm.\nb\nPour éviter que toutes les impuretés de la cheminée\nsoient récupérées par l’aspiration de la chaudière :\nNe raccordez pas l’appareil directement en sortie\nverticale.\nNe raccordez pas l’appareil sur une cheminée ayant\névacuée des produits fuels.\nL2\nL1\nS\nS\nD\nA\nB\nLégende\nL1    Longueur du conduit concentrique horizontal\nL2     Longueur du conduit vertical\nD     Diamètre intérieur de la cheminée\nS     Largeur intérieure de la cheminée\nA    Coude du terminal ventouse horizontal\nB    Coude du conduit flexible\nL1: Longueur du conduit concentrique horizontal. Cette valeur\nprend en compte la perte de charge générée par le coude A.\nL2: Longueur du conduit vertical. Cette valeur prend en compte\nla perte de charge générée par le Coude B et le terminal de la\ncheminée.\nLa prise d’air se fait par le conduit de cheminée (intervalle entre\nles deux conduits). En conséquence, la valeur (L2) évolue en\nfonction de la section de cheminée et des caractéristiques de la\nchaudière selon le tableau ci dessous.\n0020130774_02 - 09/12 - Saunier Duval\n- 17 -",
    "installation_de_type_b23p": "b\nDans cette configuration, les conditions\nréglementaires concernant les aérations doivent être\nrespectées.\nCette configuration permet de réutiliser un ancien conduit de\nfumée ou de ventilation pour l’implantation d’un conduit de\nchaudière étanche. La longueur du conduit horizontal (L1) est de\ntype concentrique Ø 60/100. La longueur du conduit vertical (L2)\nest un flexible d’évacuation des fumées Ø 80 mm.\nL’air frais est pris dans la pièce où est installé l'appareil par\nl'intermédiaire du coude du terminal ventouse horizontal (A).\nL2\nL1\nA\nB\nLégende\nL1    Longueur du conduit concentrique horizontal\nL2    Longueur du conduit vertical\nA    Coude du terminal ventouse horizontal\nB    Coude du conduit flexible\nTypeLongueur L1 min.\nLongueur L2 min.\nLongueur\nL1 + L2 max.\nØ 60/1000.5 m-\n18\nØ 80-1 m\nChaque fois qu’un coude à 90° supplémentaire est nécessaire (ou\n2 à 45°), la longueur (L1+L2) doit être réduite de 1 m.\n0020130774_02 - 09/12 - Saunier Duval\n- 18 -",
    "connexion_lectrique": "e",
    "linstallation_doit_tre_munie_d": "•\tRaccordez le câble d’alimentation de l'appareil au réseau 230\nV monophasé + terre.\n•\tRespectez le raccordement phase et neutre sur l'appareil.\n•\tN’utilisez pas du câble supérieur à 10 mm de diamètre pour\nles raccordements électriques.\nSelon les normes en vigueur, ce raccordement doit être réalisé\npar l’intermédiaire d’un interrupteur bipolaire avec une\nséparation d’au moins 3 mm entre chaque contact.\n9.1 Accès au tableau principal\n1\n2\n3\n4\nLégende",
    "accs_pour_raccordement_230_v": "9.2 Carte principale\n1\n2\n3\nLégende",
    "gaine": "Lorsque vous raccordez des câbles électriques sur un connecteur\nde la carte électronique :\n•\tConservez une distance de 30 mm maximum entre le\nconnecteur (1) et la gaine dénudée (3).\n•\tDans le cas contraire, attachez les fils électriques (2) ensemble\nà l’aide d’un collier plastique.\n•\tFixez les câbles dans le serre-câbles du boîtier électrique.\n9.3 Accessoires externes\n230\nV\nX17\nX18\nRT 24VT° extBUS\nBUS",
    "v": "X2\nX30\nX90\nX32\nX40\nX51\nX31\nX25\nX21\nX13",
    "connecteur_scurit_de_surchauff": "0020130774_02 - 09/12 - Saunier Duval\n- 19 -",
    "vac": "LN\nX12\nX101\nFUS\nX14\nX20\nX18\nX17\nX17\n1 2 3\n1\n4\n2\n5\n3\n6\n10 9 8 7 6 5 4 3 2 1\n1920  18 17 16 1514 13 12 11\n1 234   2 1\nX2\n1 23452 11111...892 1\n1\n10\n2\n11\n3\n12\n4\n13\n5\n14\n6\n15\n7\n16\n8\n17\n9\n18\nX20\n1 2\n3 4\n1\n1 2\n1\nX21\n1918171615\n1\n2\n3\n4\n5\n8\n9\n6\n7\n1011121314\nLégende",
    "connecteur_pour_capteur_de_tem": "solaire optionnel",
    "dtecteur_de_pression_du_circui": "0020130774_02 - 09/12 - Saunier Duval\n- 20 -",
    "mise_en_service": "10.1 Première mise en fonctionnement\n•\tAppuyez sur le bouton marche/arrêt pour mettre en service\nl’appareil.\n•\tAssurez-vous que les fonctions sanitaire et chauffage de votre\nappareil sont désactivées.",
    "linstallation_est_ouvert": "•\tOuvrez les robinets d’arrêt situés sur les raccordements : ils\ndoivent être positionnés dans le sens de l’écoulement.\n4\n3\n2\n1\nLégende",
    "bouchon_du_purgeur_de_la_pompe": "•\tOuvrez le bouchon du purgeur situé sur la pompe ainsi que les",
    "purgeurs_automatiques_de_linst": "•\tOuvrez le robinet de remplissage situé sous l'appareil jusqu’à\nlire 0.8 bar sur l’indicateur de pression.\ni\nUne routine de dégazage se lance automatiquement\npendant 5 minutes dès que l'appareil atteint 0.5\nbar de pression. Pendant ce temps, les fonctions\nchauffage et eau chaude sanitaire ne peuvent pas être\nactivées.\n•\tPurgez chaque radiateur jusqu’à écoulement normal de l’eau",
    "puis_refermez_les_purgeurs_de_": "•\tLaissez le bouchon du purgeur de la pompe ouvert.\ni\nLes deux opérations suivantes permettent de\ndébloquer le moteur de la pompe suite à un\nstockage prolongé et de purger l’air du circuit de\nrefroidissement de la pompe.\n•\tRetirez la vis de l'arbre de la pompe et introduisez un tournevis\nplat. Un filet d’eau sans pression doit normalement sortir de la\npompe.\n•\tEntraînez l’arbre de la pompe sur quelques tours, puis\nremettez en place la vis.\n10.3 Remplissage du circuit d’eau chaude sanitaire\n•\tOuvrez les différents robinets d’eau chaude pour remplir le\ncircuit sanitaire.\n10.4 Remise en pression du système\n1\n1\n\u0015\nLégende",
    "ou_gale_50c_non_applicable_pou": "plancher chauffant).\n•\tPurgez à nouveau chaque radiateur jusqu’à écoulement\nnormal de l’eau puis refermez les purgeurs.\n•\tSi vous rencontrez des difficultés de dégazage, lancez les\nprogrammes de dégazage du circuit chauffage (reportez-vous\nau chapitre \"Réglages techniques de l’appareil et liste des\nparamètres\").\n•\tAssurez-vous que l’indicateur de pression affiche une valeur\nde 0.8 bar; sinon, remplissez à nouveau l'appareil.\n0020130774_02 - 09/12 - Saunier Duval\n- 21 -",
    "yyyy_vitesse_max_du_ventilateu": "•\tPour connaître les vitesses min. (1) et max. (2) du ventilateur,\nconsultez l'étiquette collée sur le silencieux de l'appareil.\n10.5.1 Vérification de la vitesse max. du ventilateur\n•\tRéglez l'appareil sur le mode de test \"P.03 : forçage brûleur à\nP. max.\". Reportez-vous au chapitre \"Modes de test\".\n•\tDès que le mode de forçage du brûleur est activé, appuyez sur\nla touche  pendant plus de 7 secondes pour basculer\ndans le mode paramétrage. L’écran affiche \"0\".\n•\tPour vérifier la vitesse max. du ventilateur, reportez-vous au",
    "chapitre_rglages_linstallation": "•\tSi la valeur affichée à l'écran correspond à ± 200 tr/min à la\nvaleur \"XXXX\" indiquée sur l'étiquette, les débits de gaz sont\ncorrects.\n•\tSi ce n'est pas le cas, contactez le service après-vente.\n•\tAppuyer sur la touche RESET  pour quitter le menu de test\nou appuyer sur la touche  pendant plus de 3 secondes\npour basculer dans le mode test.\n10.6 Test du système de chauffage\n•\tAssurez-vous que les organes de régulation externes\n(thermostat d'ambiance, sonde extérieure, ...) envoient une\ndemande de chauffage à l'appareil.\n•\tAssurez-vous que toutes les vannes thermostatiques des\nradiateurs sont ouvertes.\n•\tActivez la fonction chauffage sur le tableau de bord de\nl'appareil.\n•\tÉquilibrez les émetteurs de chaleur si nécessaire.\n10.7 Test du système d'eau chaude sanitaire\n•\tOuvrez un robinet d'eau chaude.\n•\tVérifiez que la température obtenue est conforme au réglage\neffectué sur l'appareil.\n10.8 Finalisation\n•\tAssurez-vous que le magnet est placé sur la façade de\nl'appareil.",
    "rglages_spcifiques": "11.1 Réglage du circuit de chauffage\nIl est nécessaire d’adapter ce débit en fonction du calcul de",
    "linstallation_a_la_livraison_l": "ouverte de ½ tour.\n1\nLégende",
    "vis_du_bypass": "•\tEn fonction des besoins, effectuez la rotation de cette\nvis (par exemple, vissez pour fermer) pour adapter la\nhauteur manométrique disponible à la perte de charge de",
    "linstallation": "•\tPour vidanger uniquement l’eau du circuit chauffage présente\ndans l’appareil, fermez tout d’abord les robinets d’arrêt départ\net retour chauffage.\n15.2 Circuit d’eau chaude sanitaire",
    "vitesse_max": "11.2 Réglages techniques de l’appareil et liste des\nparamètres\nL’accès aux données techniques de l'appareil permet d’effectuer\ncertains réglages et d’analyser d’éventuels dysfonctionnements.\nNota : la diminution de la puissance en chauffage n’a aucune\nincidence sur la puissance en eau chaude sanitaire.",
    "21_rglages_linstallation": "•\tAppuyez pendant plus de 7 secondes sur la touche  pour\naccéder au menu de paramétrage. L’écran affiche \"0\".\n•\tAppuyez 4 fois sur la touche .\nL’écran affiche \"96\", c’est le mot de passe installateur.\n•\tAppuyez sur  pour valider. L’ecran affiche le paramètre\n\"d.00\" et sa valeur \"XX\".\n•\tAppuyez sur la touche  ou  du mode  pour accéder au\nparamètre à modifier.\n•\tAppuyez sur la touche  ou  du mode  pour modifier la\nvaleur du paramètre.\n•\tRépéter les deux phases précédentes pour chaque paramètre\nqui nécessite d’être modifié.\n•\tAppuyez pendant plus de 3 secondes sur la touche  pour\nsortir du menu de paramétrage.\n0020130774_02 - 09/12 - Saunier Duval\n- 23 -",
    "de_linstallation_de_chauffage_": "consigne du chauffage :\n- à 80°C, la durée est fixe (2 minutes)\n- à 10°C, la durée est réglable : choisissez une valeur comprise entre\n2 et 60 minutes.\n20oui\nd.04Température de l'eau du ballon°CAffichage de la température de l'eau du ballon.-non\nd.18Fonctionnement de la pompe-\nMode de fonctionnement :\n0 = Discontinu avec brûleur\n1 = Continu avec T.A.\n2 = Permanent\n1oui\nd.19Vitesse de la pompe-\nMode de fonctionnement :\n0 = Automatique : vitesse max. lorsque le brûleur est allumé\n1 = Vitesse min.\n2 =  Automatique : vitesse automatique lorsque le brûleur est allumé\n3 = Vitesse max.\n2oui\nd.20\nTempérature de consigne de l'eau\nchaude sanitaire max.\n°C\nLa température de consigne de l'eau chaude sanitaire max. conseillée\nest de 60°C. Choisissez une valeur entre 50°C et 60°C.\n60oui\nLes 2 menus suivants s'affichent si une carte option (non fournie) est installée sur l'appareil.\nd.27Fonction relais 1-\nAffectation d’une fonction au relais 1 de la carte option :\n1 = Pompe de recirculation sanitaire\n2 = Pompe chauffage additionnelle\n3 = Pompe de charge ballon\n4 = Clapet fumées / ventilateur cheminée\n5 = Vanne gaz externe\n6 = message d’erreur externe\n1oui\nd.28Fonction relais 2-\nAffectation d’une fonction au relais 2 de la carte option :\n1 = Pompe de recirculation sanitaire\n2 = Pompe chauffage additionnelle\n3 = Pompe de charge ballon\n4 = Clapet fumées / ventilateur hotte\n5 = Vanne gaz externe\n6 = message d’erreur externe\n2oui\nLe menu suivant s'affiche si un kit de remplissage automatique du circuit chauffage (non fourni) est installé sur l'appareil.\nd.31Mode de remplissage-\nMode de fonctionnement :\n0 = Manuel\n1 = Semi-automatique\n2 = Automatique\n0oui\nd.34Vitesse du ventilateur\ntr/\nmin.\nAffichage de la vitesse du ventilateur entre 0 et 99.\nMultipliez la valeur affichée par 100.\n-non\nd.35Position de la vanne 3 voies-\n0 = Position chauffage\n100 = Position eau chaude sanitaire\n-non\nd.36Débit d'eau chaude sanitaire\nl/\nmin.\nAffichage du débit d'eau chaude sanitaire. -non\nLe menu suivant s'affiche si un système solaire (non fourni) est raccordé sur l'appareil.\nd.39Température de l'eau du circuit solaire°C\nAffiche la température de l'eau du circuit solaire mesurée par la\nsonde située en amont du mitigeur.\n-non\nd.40Température départ chauffage°CAffichage de la température départ chauffage.-non\nd.41Température retour chauffage°CAffichage de la température retour chauffage.-non\nd.43Courbe chauffageK\nReportez-vous à la notice de la sonde extérieure raccordée\nsur l'appareil.\n1.2oui\nd.45Pied de courbe chauffage°C20oui\n0020130774_02 - 09/12 - Saunier Duval\n- 24 -",
    "cycle_dattente_manque_deau_dan": "température entre le départ et le retour chauffage trop élevée.\nS.96Test du capteur de température du retour chauffage.\nS.98\nTest des capteurs de température départ et retour chauffage ou\nl'appareil est en défaut.\nS.99Remplissage automatique en cours\n11.2.3 Modes de test\nEn activant ces différents modes de test, vous pouvez déclencher\ndes fonctions spéciales sur l'appareil.\n•\tAppuyez sur le bouton marche/arrêt pour éteindre l'appareil.\n•\tTout en maintenant la touche  enfoncée pendant plus de\n5 secondes, appuyez sur le bouton marche/arrêt.\nL’écran affiche le premier mode de test \"P01\" et \"Off\".\n•\tAppuyez sur la touche  ou  du mode  pour choisir le\nmode de test que vous souhaitez lancer.\n0020130774_02 - 09/12 - Saunier Duval\n- 25 -",
    "bouchon": "•\tEnlevez tout d’abord la façade étanche.\n•\tEnlevez le bouchon (3) puis raccordez un analyseur de CO2 par\nla prise de mesure (2).\n14.1.1 Réglage du mécanisme gaz\n•\tAppuyez sur le bouton marche/arrêt pour mettre hors service\nl’appareil.\n•\tTournez la vis en respectant le sens et le nombre de tours\nindiqués dans le tableau ci-après.\nRéglage\nchangement\nde gaz\nModèleG20 ▸ G25G20 ▸ G31G31 ▸ G20\nF251.5 tour2 tours\nF30\n1.5 tour\n3 tours\nF351.5 tour2.5 tours\nF25\n2 tours\nF303 tours\nF352.5 tours\n14.1.2 Réglage de la puissance maximale\n•\tRéglez l'appareil sur le mode de test \"P.03 : forçage brûleur à\nP. max.\". Reportez-vous au chapitre \"Modes de test\".\n•\tAttendez environ 5 minutes pour lire une valeur de CO2\nstabilisée.\n•\tComparez la valeur mesurée avec les valeurs indiquée dans le\ntableau ci-après.\nRéglage changement\nde gaz\nG20 ▸ G25G20 ▸ G31G31 ▸ G20\nCO2 façade ouverte8.8 ± 0.2 %10.1 ± 0.2 %9 ± 0.2 %\nCO2 façade fermée9 ± 0.3 %10.3 ± 0.3 %9.2 ± 0.3 %\n•\tVérifiez le taux de CO dans les produits de combustion et\ncomparez-le avec les valeurs indiquées au chapitre \"Données\ntechniques\" (il doit être inférieur à 500 ppm).\n0020130774_02 - 09/12 - Saunier Duval\n- 29 -",
    "linstallation_et_utilisez_le_c": "•\tVérifiez l'étanchéité de l'appareil (gaz et eau) et éliminez les\nfuites éventuelles.\n•\tVérifiez que les fumées sont évacuées correctement.\n•\tContrôlez l'ensemble des dispositif de commande et de\nsécurité, leurs réglages et leurs états de fonctionnement.",
    "au_terme_de_linstallation_lins": "-expliquer à l’utilisateur le fonctionnement de l’appareil,\ndes dispositifs de sécurité et, si nécessaire, faire une\ndémonstration et répondre aux questions\n-donner à l’utilisateur tous les documents relatifs à l'appareil\n-remplir les documents, le cas échéant\n-informer l’utilisateur sur les précautions à prendre pour ne pas\nendommager le système, l’appareil et le local.\n-rappeler à l’utilisateur de faire effectuer un entretien annuel.\n-expliquer à l'utilisateur comment vidanger l'appareil et lui\nmontrer les éléments à manipuler.\n0020130774_02 - 09/12 - Saunier Duval\n- 26 -",
    "maintenance": "FR\n16.6.1 Démontage de l’ensemble brûleur\n•\tDémontez le silencieux (reportez-vous au chapitre \"Démontage\ndu silencieux\").\n•\tDéconnectez le connecteur de l’électrode d’allumage et de\ncontrôle de flamme (3) à partir de l’allumeur.\n•\tEnlevez la tubulure gaz (16).\n•\tRetirez les connecteurs du mécanisme gaz (1) et du ventilateur\n(15).\n•\tDesserrez les 4 écrous (5).\n•\tRetirez l’ensemble brûleur du corps de chauffe (10).\nLes vis (6) soudées sur le corps de chauffe ne doivent pas être\nendommagées. Dans le cas contraire, remplacez le corps de\nchauffe.\nL’isolation de la porte du brûleur sur l’ensemble brûleur ne doit\npas être endommagée. Dans le cas contraire, remplacez-la.\n16.6.2 Nettoyage du corps de chauffe\n•\tNettoyez le serpentin (9) du corps de chauffe (10) avec de\nl’eau.\n16.6.3 Contrôle du brûleur\nLe brûleur (12) ne nécessite aucun entretien et n’a pas besoin\nd’être nettoyé.\n•\tVérifiez que sa surface n’est pas endommagée. Remplacez le\nbrûleur si nécessaire.\n•\tAprès le contrôle ou le remplacement du brûleur, montez\nl’ensemble brûleur comme décrit au chapitre suivant.\n16.6.4 Montage de l’ensemble brûleur\nb\nAttention : A chaque démontage du brûleur, il est\nobligatoire de remplacer le joint (11) et au minimum\ntous les 5 ans..\n•\tPlacez l’ensemble brûleur sur le corps de chauffe (10).\n•\tSerrez progressivement les 4 écrous (5) dans un ordre croisé.\n•\tRemontez le silencieux.\n•\tRaccordez la tubulure gaz (16) avec un joint neuf sur\nl’ensemble brûleur.\n•\tBranchez le connecteur de l’électrode d’allumage et de\ncontrôle de flamme (3) sur l’allumeur.\n•\tBranchez le connecteur du mécanisme gaz (1) et du ventilateur\n(15).\n•\tOuvrez l’arrivée de gaz de l’appareil.\n•\tVérifiez l’étanchéité sur le raccord de gaz.\n16.7 Remplacement du câble d'alimentation\ne\nLe câble d'alimentation de l'appareil doit être\nremplacé par le fabricant, son service après-vente ou\ndes personnes de qualification similaire afin d'éviter\nun danger.\n•\tSi le câble d'alimentation est endommagé, remplacez-le en\nsuivant les recommandations du chapitre \"électrique\".",
    "dpannage": "13.1 Diagnostic de pannes\n•\tAvant de procéder à un diagnostic spécifique, procédez aux\nvérifications suivantes :\n-Vérifiez qu’il n’y a pas de coupure du réseau électrique et que\nl’appareil est correctement branché.\n-Vérifiez l'alimentation en gaz de l'appareil.\n-Assurez-vous que les robinets d'arrêt soient ouverts.\n-Assurez-vous que l’indicateur de pression affiche une valeur\nde 0.8 bar; sinon, remplissez l'appareil.\n-Vérifiez le bon fonctionnement des organes de régulation\nexternes (thermostat d'ambiance, sonde extérieure, ...).\n-Si le symbole  et le message \"rE SEt\" s'affichent à l'écran,\nappuyez sur le bouton reset  pour redémarrer l'appareil.\n13.2 Historique des codes défauts\nCe menu permet d'afficher les 5 derniers codes défauts apparus\nsur l'appareil.\n•\tPour afficher l'historique des codes défauts, appuyez\nsimultanément sur les touches  et  du mode  pendant\nplus de 7 secondes.\nL'écran affiche le premier défaut \"01   XX\".\n•\tPour afficher les autres défauts apparus sur l'appareil,\nappuyez sur la touche  ou  du mode .\n•\tAppuyez sur la touche  pendant plus de 3 secondes pour\nsortir de ce menu.\nHistorique\nCode\ndéfaut\nDescription\n01XXReportez-vous au chapitre \"Codes défauts\".\n02XXReportez-vous au chapitre \"Codes défauts\".\n03XXReportez-vous au chapitre \"Codes défauts\".\n04XXReportez-vous au chapitre \"Codes défauts\".\n05XXReportez-vous au chapitre \"Codes défauts\".\n06XXReportez-vous au chapitre \"Codes défauts\".\n07XXReportez-vous au chapitre \"Codes défauts\".\n08XXReportez-vous au chapitre \"Codes défauts\".\n09XXReportez-vous au chapitre \"Codes défauts\".\n10XXReportez-vous au chapitre \"Codes défauts\".\n•\tPour effacer l'historique des codes défauts apparus sur",
    "lappareil_reportezvous_au_chap": "et utilisez le code \"d.94\".\n0020130774_02 - 09/12 - Saunier Duval\n- 27 -",
    "manque_deau_dans_linstallation": "(<0.3 bar)\nF22\nRobinet d’arrivée d'eau fermé\nPompe déconnectée",
    "_purgez_linstallation": "• Vérifiez les connexions de la pompe.\n• Vérifiez les connexions des capteurs départ et retour\nchauffage.\n• Vérifiez qu'il n'y a pas de fuite.",
    "absence_deau_dans_linstallatio": "pas d'élévation de température\nmais le brûleur est allumé\nF83\nDéfaut d’allumageF28\nPas d’arrivée de gaz / Débit gaz insuffisant\nMauvais réglage du mécanisme gaz\nElectrode d’allumage et de contrôle de flamme\ndéfectueuses\nAllumeur défectueux\n• Vérifiez le circuit d’arrivée gaz (robinet gaz ouvert).\n• Vérifiez le réglage du mécanisme gaz.\n• Vérifiez les connexions de l’allumeur.\n• Vérifiez l’état de l'électrode (corrosion).\nPerte de flamme en fonctionnementF29\nFluctuation du signal de la flammeF 68\nDéfaut d’extraction ou de\nl’aspiration de l’air\nF32Vitesse du ventilateur incorrecte\n• Vérifiez l’arrivée d’air et l’évacuation des fumées.\n• Vérifiez les connections électriques du ventilateur.\nDéfaut de surchauffe\nF20Sécurité de surchauffe activée (97°C)\n• Vérifiez le fonctionnement de la pompe.\n• Vérifiez que les robinets d'arrêt départ et retour\nchauffage sont ouverts.\n-Mauvais dégazage\nDéfaut du capteur de température\ndépart chauffage\nF00Capteur déconnecté\n• Vérifiez les connexions du capteur.\n• Vérifiez les câbles du capteur.\n• Vérifiez le capteur.\nF10Court-circuit du capteur\nDéfaut du capteur de température\ndu ballon\nF13Court-circuit du capteur de température du ballon\nF79Défaut capteur de température du ballon\nDéfaut du capteur de pression\ncircuit chauffage\nF73Capteur de pression en court-circuit ou déconnecté\n• Vérifiez les connexions du capteur.\n• Vérifiez le capteur.\nF74Capteur de pression en défaut\nDéfaut capteur de température\nretour chauffage\nF01\nCapteur de température retour chauffage\ndéconnecté\n• Vérifiez les connexions du capteur.\n• Vérifiez les câbles du capteur.\n• Vérifiez le capteur.\nF11\nCourt-circuit du capteur de température retour\nchauffage\nDéfaut de tension EBUSF49\nDéfaut sur la ligne EBUS\nCourt circuit sur le connecteur EBUS\n• Vérifiez la charge sur la ligne EBUS.\nDéfaut de la carte principale\nF61Défaut de commande de la vanne gaz\n• Vérifiez l’ensemble des connexions de la carte\nprincipale.\n• Vérifiez la carte électronique.\n• Vérifiez le code produit.\n• Faites un reset de l’appareil.\nF62Défaut de fermeture de la vanne gaz\nF63Défaut de mémoire de la carte principale\nF64\nFluctuation rapide du capteur départ ou retour\nchauffage\nF65Température de la carte principale trop élevée\nF67Défaut du signal de flamme sur la carte principale\nDéfaut du moteur du mécanisme\ngaz\n-Court-circuit du moteur mécanisme gaz\n• Vérifiez les connexions du mécanisme gaz.\n• Vérifiez le fonctionnement du mécanisme gaz.\n• Vérifiez le fonctionnement de la pompe à\ncondensats (en option)\nF26Câbles déconnectés ou défectueux\nF77\nMécanisme gaz défectueux\nPompe à condensats défectueuse (en option)\nDéfaut de détection de flamme\nF27Détection de flamme anormale\n• Vérifiez l’électrode de détection de flamme.\n• Vérifiez la carte principale.\n• Vérifiez l'allumeur.\n-Mécanisme gaz défectueux\nDéfaut de l'interface utilisateur-Carte interface défectueuse• Remplacez la carte interface.\nDéfaut du capteur de température\ndépart chauffage\nF71\nCapteur de température départ chauffage déclipsé\nou défectueux (pas de variation de température)\n• Vérifiez les connexions du capteur.\n• Assurez-vous que le capteur est clipsé sur la\ntubulure.\nInterface utilisateur incompatible\navec la carte principale\nF70Mauvais code produit\n• Vérifiez que le code produit affiché à l'écran\ncorrespond au code produit de la plaque signalétique\n(en cas de défaut, le code produit ne s'affiche pas,\nreportez-vous au menu.d.93 réservé aux SAV).\n• Vérifiez la référence de la carte.\nDéfaut de circulation d’eauF24\nMauvais fonctionnement de la pompe (montée en\ntempérature trop rapide)\n• Vérifiez que les robinets d'arrêt départ et retour\nchauffage sont ouverts.\n0020130774_02 - 09/12 - Saunier Duval\n- 28 -",
    "changement_de_gaz": "b\nTout scellage détruit doit être reconstitué.\nPour un fonctionnement avec un gaz autre que celui prévu en\nusine, il faut effectuer certains réglages au niveau du mécanisme\ngaz.\n14.1 Réglages\n24\n1\n2\n3\nLégende",
    "vidange": "15.1 Circuit de chauffage\n1\nLégende",
    "robinet_de_vidange_chauffage": "•\tOuvrez le robinet de vidange (1) situé en dessous de la\nchaudière.\n•\tFaites une prise d’air en ouvrant, par exemple, un purgeur de",
    "_fermez_le_robinet_darrive_dea": "•\tFaites une prise d’air en ouvrant un robinet d’eau chaude.",
    "_une_fois_les_oprations_de_mai": "vous au chapitre \"Mise en service\" pour redémarrer l'appareil.",
    "1_maintenance_annuelle": "16.1.1 Vérification des composants\n•\tVérifiez que le capteur de débit fonctionne correctement.\n•\tVérifiez que le mécanisme gaz module correctement.\n•\tVérifiez que les capteurs de température fonctionnent\ncorrectement.\n•\tVérifiez la qualité de l'ionisation.\n•\tVérifiez que le fusible thermique assure la protection de\nl'appareil contre les surchauffes.\n•\tVérifiez que le détecteur de pression fonctionne correctement.\n•\tVérifiez la pression du vase d'expansion.\n16.1.2 Autres vérifications\n•\tVérifiez le taux de CO2 dans les produits de combustion et\ncomparez-le avec les valeurs indiquées au chapitre \"Mesure\ndu CO2\".\n•\tVérifiez qu'il n'y a pas de fuites au niveau des joints, des\nsoupapes de sécurité et du disconnecteur.\n•\tVérifiez qu'il n'y a pas de fuites de gaz.\n•\tVérifiez l'état du joint du conduit d'évacuation des produits de\ncombustion.\n•\tVérifiez le raccordement à la terre de l'appareil.\n0020130774_02 - 09/12 - Saunier Duval\n- 30 -",
    "lectriques_entre_les_diffrents": "Il évitera aussi par voie de conséquence la formation de gaz qui\npourraient se produire lors des réactions chimiques.\nLe traitement d’eau est particulièrement important sur les\nplanchers chauffants car la basse température est favorable à\nla prolifération bactérienne. Il peut en résulter des boues qui\npeuvent boucher tout ou partie des circuits.\nLe dosage de ces produits nécessite de connaître le volume d’eau",
    "dans_linstallation_il_est_reco": "futurs besoins.\nLes inhibiteurs doivent être compatibles avec les matériaux",
    "utiliss_dans_linstallation": "16.2 Démontage de la façade avant\n24\nV\n230\nV\n2\n1\nC\nA\nA\nB\nLégende",
    "vis_de_fixation_de_la_faade_av": "•\tRetirez la façade avant de l'appareil en respectant l’ordre des\nopérations (A) à (C).\n16.3 Démontage du silencieux\n24\nV\n230\nV\n2\n1\nB\nC\nA\nLégende",
    "silencieux": "•\tRetirez la vis de fixation du silencieux (1).\n•\tEnlevez le silencieux (2).\n•\tNettoyez l’intérieur du silencieux avec un chiffon sec si\nnécessaire en prenant soin de ne pas abîmer la mousse\nintérieure.\n•\tProcédez dans l’ordre inverse des opérations pour remonter le\nsilencieux.\n16.4 Vase d'expansion\n24\nV\n230\nV\n1\nLégende",
    "vase_dexpansion": "•\tContrôlez la pression d’alimentation du vase d’expansion (voir\nchapitre \"Données techniques\") par la prise de pression située\nau-dessous du vase d'expansion et adaptez-la si nécessaire.\n•\tAprès le montage d’un vase d’expansion neuf, remplissez et",
    "purgez_lappareil_ou_linstallat": "0020130774_02 - 09/12 - Saunier Duval\n- 31 -",
    "bouchon_du_rcuprateur_de_conde": "0020130774_02 - 09/12 - Saunier Duval\n- 32 -",
    "tubulure_gaz": "0020130774_02 - 09/12 - Saunier Duval\n- 34 -",
    "pices_de_rechange": "Afin de garantir la sécurité du fonctionnement de l’appareil ainsi\nque sa longévité, utilisez des pièces d’origine agréées par le\nfabricant.\ni\nCet appareil porte le marquage CE de conformité.\nUtilisez uniquement des pièces détachées d’origine,\nneuves et agréées par le fabricant.\n•\tAssurez-vous que les pièces détachées sont correctement\ninstallées et positionnées dans le bon sens. Après toute",
    "installation_de_pice_et_tout_e": "vérifiez qu’il fonctionne correctement.\n0020130774_02 - 09/12 - Saunier Duval\n- 35 -\nDONNÉES TECHNIQUES\nFR\nDONNÉES TECHNIQUES",
    "donnes_techniques": "Chaudière type C13, C33, C43, C43P, C93, B23P\nDescriptionUnitéF 25 F 30F35\nCatégorie gazll\n2Esi3P\nll\n2Esi3P\nll\n2Esi3P\nChauffage\nPuissance utile min. à 80°C/60°C (P min.)\nkW4.95.98.5\nPuissance utile max. à 80°C/60°C (P max.)\nkW18.124.530\nPuissance utile min. à 50°C/30°C (P min.)kW5.46.69.3\nPuissance utile max. à 50°C/30°C (P max.)kW19.626.732.8\nRendement sur P.C.I. à 80°C/60°C%97.797.798.3\nRendement sur P.C.I. à 50°C/30°C\n%106.2106.8 107.1\nRendement à charge partielle (30%) sur P.C.I. à 40°C/30°C%108.4109.2109.2\nNiveau de rendement selon la Directive Européenne 92/42-Condensation\nDébit calorifique minimal (Q min.)kW5.16.18.7\nDébit calorifique maximal (Q max.)kW18.52530.6\nDébit minimum de chauffagel/h400400400\nTempérature départ chauffage min.°C101010\nTempérature départ chauffage max. °C808080\nVase d’expansion, capacité utilel888\nPression de prégonflage du vase d’expansionbar0.750.750.75",
    "capacit_maxi_de_linstallation_": "Soupape de sécurité, pression maximale de service (PMS)bar333\nSanitaire\nPuissance utile min. (P min.)\nkW5.16.18.7\nPuissance utile max. (P max.)\nkW25.530.635.7\nDébit calorifique min. (Q min.)kW5.16.18.7\nDébit calorifique max. (Q max.)kW25.530.635.7\nTempérature eau chaude min.°C383838\nTempérature eau chaude max.°C606060\nDébit spécifique (D) selon EN 13203l/min12.214.617\nDébit spécifique selon EN 625l/min---\nConfort sanitaire selon EN 13203-*********\nDébit seuil de fonctionnementl/min1.91.91.9\nCapacité micro-accumulationl333\nLimiteur de débit eau froidel/min81010\nSoupape de sécurité, pression maximale de service (PMW)bar101010\nPression d’alimentation min.bar0.30.30.3\nPression d’alimentation conseillée (*)bar222\nPression d’alimentation max. (**)bar101010",
    "_rglage_conseill_pour_le_rempl": "(**) Pour une pression d'alimentation supérieure à 3 bar, il est conseillé d'installer un réducteur de pression.\n0020130774_02 - 09/12 - Saunier Duval\n- 36 -\nDONNÉES TECHNIQUES\nFR\nDescriptionUnitéF 25 F 30F35\nCombustion\nDébit d’air neuf (1013 mbar - 0°C)\nm\n3\n/h\n22.129.836.5\nDébit d’évacuation des gaz brûlés à Pmin.g/s2.32.84\nDébit d’évacuation des gaz brûlés à Pmax.g/s8.311.313.8\nDébit d’évacuation des gaz brûlés en mode eau chaude sanitaireg/s11.513.816\nTempérature fumées à P min. 80°C/60°C°C66.859.672\nTempérature fumées à P min. 50°C/30°C°C47.139.347.4\nTempérature fumées à P max. 80°C/60°C°C65.763.472\nTempérature fumées à P max. 50°C/30°C°C48.84455.8\nTempérature des fumées en surchauffe°C10595104\nTempérature des fumées en mode eau chaude sanitaire°C70.76875\nValeurs des produits de la combustion (mesurée au débit calorifique nominal et avec le gaz de référence G20, en chauffage) :\nCO\nppm 98.3103.680\nmg/kWh105110.685.3\nCO2 %9.29.29.2\nNOx pondéré\nppm 22.621.918.4\nmg/kWh39.938.632.6\nElectrique\nTension d’alimentationV/Hz\n230V\n50Hz\n230V\n50Hz\n230V\n50Hz\nPuissance maximale absorbéeW181181181\nIntensitéA0.790.790.79\nFusibleT 2A/250VT 2A/250VT 2A/250V\nProtection électriqueIPX4DIPX4DIPX4D\nClasse électriqueIII\nDescriptionUnitéF 25F 30F35\nDimensions :\nHauteurmm740740740\nLargeurmm418418418\nProfondeurmm344344344\nPoids netkg38.43939.6\nNuméro CE\n1312\nBU 5334\n1312\nBU 5335\n1312\nBV 5336\nDescriptionUnitéF 25F 30F35\nGaz naturel G 20 (*)\nDébit gaz à puissance maximale sanitaire\nm\n3\n/h\n2.703.243.77\nDébit gaz à puissance maximale chauffage\nm\n3\n/h\n1.962.653.24\nDébit gaz à puissance minimale\nm\n3\n/h\n0.540.650.92\nPression d’alimentation en gazmbar202020\nGaz naturel G 25 (*)\nDébit gaz à puissance maximale sanitaire\nm\n3\n/h\n3.143.774.39\nDébit gaz à puissance maximale chauffage\nm\n3\n/h\n2.283.083.76\nDébit gaz à puissance minimale\nm\n3\n/h\n0.630.751.07\nPression d’alimentation en gazmbar252525\nGaz liquide G 31 (*)\nDébit gaz à puissance maximale sanitairekg/h1.982.382.77\nDébit gaz à puissance maximale chauffagekg/h1.441.942.37\nDébit gaz à puissance minimalekg/h0.400.470.67\nPression d’alimentation en gaz mbar373737\n(*) réf. 15°C - 1013 mbar gaz sec\n0020130774_02 - 09/12\nSous réserve de modifications techniques",
    "vaillant_group_france_sa": "«Le Technipole» - 8, avenue Pablo Picasso",
    "fontenaysousbois_cedex_france": "Téléphone : 01 49 74 11 11\nTélécopie : 01 48 76 89 32\nSA au capital de 7.328.460 Euros\n301 917 233 RCS CRETEIL\nwww.saunierduval.fr"
  },
  "codes_erreur": [
    {
      "code": "O2",
      "description": ".................................................................................................25",
      "context": "hniques de l’appareil et liste des paramètres ...................................22\n11.3 Mesure du CO2 ................................................................................................."
    },
    {
      "code": "G20",
      "description": "ou G31, mais elle peut être adaptée pour être raccordée aux G20,",
      "context": "plaque signalétique.\n2.3 Classe de gaz \nCette chaudière est dédiée pour fonctionner uniquement aux G20 \nou G31, mais elle peut être adaptée pour être raccordée aux G20, \nG25 et G31.\n•\tConsultez la pl"
    },
    {
      "code": "G25",
      "description": "•\tPour adapter l'appareil à un autre type de gaz, reportez-vous",
      "context": "l'appareil a été réglé en usine.\nGaz réglé en usineChangements de gaz possibles\nG20G25, G31\nG31G20, G25\n•\tPour adapter l'appareil à un autre type de gaz, reportez-vous \nau chapitre \"Changement de gaz\""
    },
    {
      "code": "e600",
      "description": "BSous une bouche d’aération600",
      "context": "N\n2000\nF\nG\nE\nE\nI\nH\nM\nL\nD\nA\nC\nB\nP\nO\nRepèrePositionnement des terminaux de ventousemm\nASous une fenêtre600\nBSous une bouche d’aération600\nCSous une gouttière300\nDSous un balcon300\nED’une fenêtre adjacen"
    },
    {
      "code": "n300",
      "description": "ED’une fenêtre adjacente400",
      "context": "ventousemm\nASous une fenêtre600\nBSous une bouche d’aération600\nCSous une gouttière300\nDSous un balcon300\nED’une fenêtre adjacente400\nFD’une bouche d’aération adjacente600\nGDe tubes d’évacuation vertic"
    },
    {
      "code": "e600",
      "description": "GDe tubes d’évacuation verticaux ou horizontaux600",
      "context": "us une gouttière300\nDSous un balcon300\nED’une fenêtre adjacente400\nFD’une bouche d’aération adjacente600\nGDe tubes d’évacuation verticaux ou horizontaux600\nHD’un angle de l’édifice300\nID’un angle rent"
    },
    {
      "code": "e300",
      "description": "ID’un angle rentrant de l’édifice1000",
      "context": "e d’aération adjacente600\nGDe tubes d’évacuation verticaux ou horizontaux600\nHD’un angle de l’édifice300\nID’un angle rentrant de l’édifice1000\nRepèrePositionnement des terminaux de ventousemm\nLDu sol"
    },
    {
      "code": "e1800",
      "description": "MEntre 2 terminaux verticaux1500",
      "context": "entrant de l’édifice1000\nRepèrePositionnement des terminaux de ventousemm\nLDu sol ou d’un autre étage1800\nMEntre 2 terminaux verticaux1500\nNEntre 2 terminaux horizontaux600\nOD’une bouche d’aération ad"
    },
    {
      "code": "x600",
      "description": "OD’une bouche d’aération adjacente600",
      "context": "usemm\nLDu sol ou d’un autre étage1800\nMEntre 2 terminaux verticaux1500\nNEntre 2 terminaux horizontaux600\nOD’une bouche d’aération adjacente600\nPD’une fenêtre de toit adjacente400\n\n0020130774_02 - 09/1"
    },
    {
      "code": "e400",
      "description": "0020130774_02 - 09/12 - Saunier Duval",
      "context": "tre 2 terminaux horizontaux600\nOD’une bouche d’aération adjacente600\nPD’une fenêtre de toit adjacente400\n\n0020130774_02 - 09/12 - Saunier Duval\n- 14 -\nINSTALLATION\nFR\n8.2 Description de la configurati"
    },
    {
      "code": "C4",
      "description": "doit être connectée uniquement sur des cheminées à",
      "context": "ent développé par le \nfabricant de l'appareil.\nb\nUne chaudière raccordée à une installation de type C4 \ndoit être connectée uniquement sur des cheminées à \ntirage naturel.\nb\nL'écoulement des condensat"
    },
    {
      "code": "W7",
      "description": "0020130774_02 - 09/12 - Saunier Duval",
      "context": "0°C/30°C)°C4950-\nTempérature des fumées °C--71\nPression sortie de chaudièrePa2980136\nParamètre d.85kW7\n\n0020130774_02 - 09/12 - Saunier Duval\n- 16 -\nINSTALLATION\nFR\nDescriptionUnitéF 30\nGazG20\nMode\nQn"
    },
    {
      "code": "W8",
      "description": "DescriptionUnitéF 35",
      "context": "0°C/30°C)°C4855-\nTempérature des fumées °C--72\nPression sortie de chaudièrePa2791150\nParamètre d.85kW8\nDescriptionUnitéF 35\nGazG20\nMode\nQnkW8,2128,3532,46\nPu (80/60)kW7,727,1931,81\nPu (50/30)kW8,7730,"
    },
    {
      "code": "W10",
      "description": "8.2.5 Système flexible ventouse pour raccordement",
      "context": "°C/30°C)°C4547-\nTempérature des fumées °C--65\nPression sortie de chaudièrePa27129175\nParamètre d.85kW10\n8.2.5 Système flexible ventouse pour raccordement \ncheminée (installation de type C93)\nCette con"
    },
    {
      "code": "L1",
      "description": "Longueur du conduit concentrique horizontal",
      "context": "ccordez pas l’appareil sur une cheminée ayant \névacuée des produits fuels. \nL2\nL1\nS\nS\nD\nA\nB\nLégende\nL1    Longueur du conduit concentrique horizontal\nL2     Longueur du conduit vertical\nD     Diamètre"
    },
    {
      "code": "L2",
      "description": "Longueur du conduit vertical",
      "context": "cuée des produits fuels. \nL2\nL1\nS\nS\nD\nA\nB\nLégende\nL1    Longueur du conduit concentrique horizontal\nL2     Longueur du conduit vertical\nD     Diamètre intérieur de la cheminée\nS     Largeur intérieure"
    },
    {
      "code": "L1",
      "description": "Longueur du conduit concentrique horizontal. Cette valeur",
      "context": "intérieure de la cheminée\nA    Coude du terminal ventouse horizontal\nB    Coude du conduit flexible\nL1: Longueur du conduit concentrique horizontal. Cette valeur \nprend en compte la perte de charge gé"
    },
    {
      "code": "L2",
      "description": "Longueur du conduit vertical. Cette valeur prend en compte",
      "context": "t concentrique horizontal. Cette valeur \nprend en compte la perte de charge générée par le coude A.\nL2: Longueur du conduit vertical. Cette valeur prend en compte \nla perte de charge générée par le Co"
    },
    {
      "code": "L1",
      "description": "+L2) doit être réduite de 1 m.",
      "context": "2 (m)103231\nChaque fois qu’un coude à 90° supplémentaire est nécessaire (ou \n2 à 45°), la longueur (L1+L2) doit être réduite de 1 m.\nb\nLa longueur du conduit concentrique horizontal (L1) \nne doit jama"
    },
    {
      "code": "L1",
      "description": ") est supérieure à 1m la longueur majorée doit",
      "context": "b\nLa longueur du conduit concentrique horizontal (L1) \nne doit jamais être supérieure à 3 m.\ni\nSi (L1) est supérieure à 1m la longueur majorée doit \nêtre retranchée de (L2).\n8.2.6 Système flexible co"
    },
    {
      "code": "L1",
      "description": "Longueur du conduit concentrique horizontal",
      "context": "llé l'appareil par \nl'intermédiaire du coude du terminal ventouse horizontal (A).\nL2\nL1\nA\nB\nLégende\nL1    Longueur du conduit concentrique horizontal\nL2    Longueur du conduit vertical\nA    Coude du t"
    },
    {
      "code": "L2",
      "description": "Longueur du conduit vertical",
      "context": "rminal ventouse horizontal (A).\nL2\nL1\nA\nB\nLégende\nL1    Longueur du conduit concentrique horizontal\nL2    Longueur du conduit vertical\nA    Coude du terminal ventouse horizontal\nB    Coude du conduit"
    },
    {
      "code": "L1",
      "description": "+L2) doit être réduite de 1 m.",
      "context": "18\nØ 80-1 m\nChaque fois qu’un coude à 90° supplémentaire est nécessaire (ou \n2 à 45°), la longueur (L1+L2) doit être réduite de 1 m.\n\n0020130774_02 - 09/12 - Saunier Duval\n- 18 -\nINSTALLATION\nFR\n9 Con"
    },
    {
      "code": "X2",
      "description": "1 23452 11111...892 1",
      "context": "X14\nX20\nX18\nX17\nX17\n1 2 3\n1\n4\n2\n5\n3\n6\n10 9 8 7 6 5 4 3 2 1\n1920  18 17 16 1514 13 12 11\n1 234   2 1\nX2\n1 23452 11111...892 1\n1\n10\n2\n11\n3\n12\n4\n13\n5\n14\n6\n15\n7\n16\n8\n17\n9\n18\nX20\n1 2\n3 4\n1\n1 2\n1\nX21\n191817"
    },
    {
      "code": "O2",
      "description": "et de la vitesse du",
      "context": "2 - Saunier Duval\n- 21 -\nINSTALLATION\nFR\n10.5 Débits de gaz\nLes débits de gaz dépendent du taux de CO2 et de la vitesse du \nventilateur.\n•\tVérifiez le taux de CO2 dans les produits de combustion et \nc"
    },
    {
      "code": "O2",
      "description": "dans les produits de combustion et",
      "context": "Les débits de gaz dépendent du taux de CO2 et de la vitesse du \nventilateur.\n•\tVérifiez le taux de CO2 dans les produits de combustion et \ncomparez-le avec les valeurs indiquées au chapitre \"Mesure \nd"
    },
    {
      "code": "O2",
      "description": "indiquée dans le tableau ci-après.",
      "context": "pas correcte, ajustez progressivement le \nréglage en tournant la vis (1) pour obtenir la valeur de CO2 \nindiquée dans le tableau ci-après.\nb\nTout scellage détruit doit être reconstitué.\nRéglageG25G31G"
    },
    {
      "code": "G20",
      "description": "CO2 façade ouverte8.8 +/- 0.2 10.1 +/- 0.29 +/- 0.2",
      "context": "CO2 \nindiquée dans le tableau ci-après.\nb\nTout scellage détruit doit être reconstitué.\nRéglageG25G31G20\nCO2 façade ouverte8.8 +/- 0.2 10.1 +/- 0.29 +/- 0.2 \nCO2 façade fermée9 +/- 0.310.3 +/- 0.39.2 +"
    },
    {
      "code": "O2",
      "description": "façade fermée9 +/- 0.310.3 +/- 0.39.2 +/- 0.3",
      "context": "truit doit être reconstitué.\nRéglageG25G31G20\nCO2 façade ouverte8.8 +/- 0.2 10.1 +/- 0.29 +/- 0.2 \nCO2 façade fermée9 +/- 0.310.3 +/- 0.39.2 +/- 0.3\n11.4 Nouvelle vérification et remise en \nfonctionne"
    },
    {
      "code": "F22",
      "description": "Robinet d’arrivée d'eau fermé",
      "context": "ce après-vente.\nDescription\nCode \ndéfaut\nCauseSolution\nManque d'eau dans l'installation \n(<0.3 bar)\nF22\nRobinet d’arrivée d'eau fermé\nPompe déconnectée \nFuite dans l'installation\n• Remplissez l'instal"
    },
    {
      "code": "F83",
      "description": "Défaut d’allumageF28",
      "context": "te.\nAbsence d'eau dans l'installation : \npas d'élévation de température \nmais le brûleur est allumé\nF83\nDéfaut d’allumageF28\nPas d’arrivée de gaz / Débit gaz insuffisant \nMauvais réglage du mécanisme"
    },
    {
      "code": "F29",
      "description": "Fluctuation du signal de la flammeF 68",
      "context": "xions de l’allumeur.\n• Vérifiez l’état de l'électrode (corrosion).\nPerte de flamme en fonctionnementF29\nFluctuation du signal de la flammeF 68\nDéfaut d’extraction ou de \nl’aspiration de l’air\nF32Vites"
    },
    {
      "code": "F32",
      "description": "Vitesse du ventilateur incorrecte",
      "context": "onnementF29\nFluctuation du signal de la flammeF 68\nDéfaut d’extraction ou de \nl’aspiration de l’air\nF32Vitesse du ventilateur incorrecte \n• Vérifiez l’arrivée d’air et l’évacuation des fumées.\n• Vérif"
    },
    {
      "code": "F20",
      "description": "Sécurité de surchauffe activée (97°C)",
      "context": "’évacuation des fumées.\n• Vérifiez les connections électriques du ventilateur.\nDéfaut de surchauffe\nF20Sécurité de surchauffe activée (97°C)\n• Vérifiez le fonctionnement de la pompe. \n• Vérifiez que l"
    },
    {
      "code": "F10",
      "description": "Court-circuit du capteur",
      "context": "ecté\n• Vérifiez les connexions du capteur.\n• Vérifiez les câbles du capteur.\n• Vérifiez le capteur.\nF10Court-circuit du capteur\nDéfaut du capteur de température \ndu ballon\nF13Court-circuit du capteur"
    },
    {
      "code": "F13",
      "description": "Court-circuit du capteur de température du ballon",
      "context": "eur.\n• Vérifiez le capteur.\nF10Court-circuit du capteur\nDéfaut du capteur de température \ndu ballon\nF13Court-circuit du capteur de température du ballon\nF79Défaut capteur de température du ballon\nDéfa"
    },
    {
      "code": "F79",
      "description": "Défaut capteur de température du ballon",
      "context": "ur\nDéfaut du capteur de température \ndu ballon\nF13Court-circuit du capteur de température du ballon\nF79Défaut capteur de température du ballon\nDéfaut du capteur de pression \ncircuit chauffage\nF73Capte"
    },
    {
      "code": "F73",
      "description": "Capteur de pression en court-circuit ou déconnecté",
      "context": "ballon\nF79Défaut capteur de température du ballon\nDéfaut du capteur de pression \ncircuit chauffage\nF73Capteur de pression en court-circuit ou déconnecté\n• Vérifiez les connexions du capteur.\n• Vérifi"
    },
    {
      "code": "F74",
      "description": "Capteur de pression en défaut",
      "context": "ression en court-circuit ou déconnecté\n• Vérifiez les connexions du capteur.\n• Vérifiez le capteur.\nF74Capteur de pression en défaut\nDéfaut capteur de température \nretour chauffage\nF01\nCapteur de temp"
    },
    {
      "code": "F01",
      "description": "Capteur de température retour chauffage",
      "context": "rifiez le capteur.\nF74Capteur de pression en défaut\nDéfaut capteur de température \nretour chauffage\nF01\nCapteur de température retour chauffage \ndéconnecté\n• Vérifiez les connexions du capteur. \n• Vér"
    },
    {
      "code": "F11",
      "description": "Court-circuit du capteur de température retour",
      "context": "té\n• Vérifiez les connexions du capteur. \n• Vérifiez les câbles du capteur. \n• Vérifiez le capteur.\nF11\nCourt-circuit du capteur de température retour \nchauffage\nDéfaut de tension EBUSF49\nDéfaut sur l"
    },
    {
      "code": "F49",
      "description": "Défaut sur la ligne EBUS",
      "context": "iez le capteur.\nF11\nCourt-circuit du capteur de température retour \nchauffage\nDéfaut de tension EBUSF49\nDéfaut sur la ligne EBUS \nCourt circuit sur le connecteur EBUS\n• Vérifiez la charge sur la ligne"
    },
    {
      "code": "F61",
      "description": "Défaut de commande de la vanne gaz",
      "context": "ircuit sur le connecteur EBUS\n• Vérifiez la charge sur la ligne EBUS.\nDéfaut de la carte principale\nF61Défaut de commande de la vanne gaz\n• Vérifiez l’ensemble des connexions de la carte \nprincipale."
    },
    {
      "code": "F62",
      "description": "Défaut de fermeture de la vanne gaz",
      "context": "ale.\n• Vérifiez la carte électronique.\n• Vérifiez le code produit.\n• Faites un reset de l’appareil.\nF62Défaut de fermeture de la vanne gaz\nF63Défaut de mémoire de la carte principale\nF64\nFluctuation r"
    },
    {
      "code": "F63",
      "description": "Défaut de mémoire de la carte principale",
      "context": "• Vérifiez le code produit.\n• Faites un reset de l’appareil.\nF62Défaut de fermeture de la vanne gaz\nF63Défaut de mémoire de la carte principale\nF64\nFluctuation rapide du capteur départ ou retour \nchau"
    },
    {
      "code": "F64",
      "description": "Fluctuation rapide du capteur départ ou retour",
      "context": "t de l’appareil.\nF62Défaut de fermeture de la vanne gaz\nF63Défaut de mémoire de la carte principale\nF64\nFluctuation rapide du capteur départ ou retour \nchauffage\nF65Température de la carte principale"
    },
    {
      "code": "F65",
      "description": "Température de la carte principale trop élevée",
      "context": "aut de mémoire de la carte principale\nF64\nFluctuation rapide du capteur départ ou retour \nchauffage\nF65Température de la carte principale trop élevée\nF67Défaut du signal de flamme sur la carte princip"
    },
    {
      "code": "F67",
      "description": "Défaut du signal de flamme sur la carte principale",
      "context": "ion rapide du capteur départ ou retour \nchauffage\nF65Température de la carte principale trop élevée\nF67Défaut du signal de flamme sur la carte principale\nDéfaut du moteur du mécanisme \ngaz\n-Court-circ"
    },
    {
      "code": "F26",
      "description": "Câbles déconnectés ou défectueux",
      "context": "fonctionnement du mécanisme gaz.\n• Vérifiez le fonctionnement de la pompe à \ncondensats (en option)\nF26Câbles déconnectés ou défectueux\nF77\nMécanisme gaz défectueux\nPompe à condensats défectueuse (en"
    },
    {
      "code": "F77",
      "description": "Mécanisme gaz défectueux",
      "context": "érifiez le fonctionnement de la pompe à \ncondensats (en option)\nF26Câbles déconnectés ou défectueux\nF77\nMécanisme gaz défectueux\nPompe à condensats défectueuse (en option)\nDéfaut de détection de flamm"
    },
    {
      "code": "F27",
      "description": "Détection de flamme anormale",
      "context": "7\nMécanisme gaz défectueux\nPompe à condensats défectueuse (en option)\nDéfaut de détection de flamme\nF27Détection de flamme anormale\n• Vérifiez l’électrode de détection de flamme. \n• Vérifiez la carte"
    },
    {
      "code": "F71",
      "description": "Capteur de température départ chauffage déclipsé",
      "context": "rface défectueuse• Remplacez la carte interface.\nDéfaut du capteur de température \ndépart chauffage\nF71\nCapteur de température départ chauffage déclipsé \nou défectueux (pas de variation de température"
    },
    {
      "code": "F70",
      "description": "Mauvais code produit",
      "context": "e capteur est clipsé sur la \ntubulure.\nInterface utilisateur incompatible \navec la carte principale\nF70Mauvais code produit\n• Vérifiez que le code produit affiché à l'écran \ncorrespond au code produit"
    },
    {
      "code": "F24",
      "description": "Mauvais fonctionnement de la pompe (montée en",
      "context": "ous au menu.d.93 réservé aux SAV). \n• Vérifiez la référence de la carte.\nDéfaut de circulation d’eauF24\nMauvais fonctionnement de la pompe (montée en \ntempérature trop rapide)\n• Vérifiez que les robin"
    },
    {
      "code": "F23",
      "description": "Problème de circulation d’eau",
      "context": "Code \ndéfaut\nCauseSolution\nEcart de température maximum \natteint entre départ et retour \nchauffage\nF23Problème de circulation d’eau\n• Vérifiez la connexion des capteurs départ et retour \nchauffage."
    },
    {
      "code": "F72",
      "description": "Incohérence entre les températures départ et",
      "context": "vitesse de la pompe.\nEcart de température permanent \nentre les capteurs départ et retour \nchauffage\nF72\nIncohérence entre les températures départ et \nretour chauffage (écart permanent)\n• Vérifiez les"
    },
    {
      "code": "F84",
      "description": "Capteurs de température départ et retour",
      "context": "anent)\n• Vérifiez les connexions des capteurs de \ntempérature.\n• Remplacez les capteurs défectueux.\nF84\nCapteurs de température départ et retour \nchauffage inversés ou déconnectés\nCapteurs de températ"
    },
    {
      "code": "F76",
      "description": "Fusible thermique déconnecté",
      "context": "ur \nchauffage inversés ou déconnectés\nCapteurs de température défectueux\nDéfaut du fusible thermiqueF76\nFusible thermique déconnecté\nFusible thermique défectueux\n• Vérifiez les connexions du fusible."
    },
    {
      "code": "F85",
      "description": "Capteurs de température départ et retour",
      "context": "exions du fusible.\n• Remplacez le corps de chauffe.\nDéfaut des capteurs départ et retour \nchauffage\nF85\nCapteurs de température départ et retour \nchauffage connectés sur la même tubulure\n• Vérifiez le"
    },
    {
      "code": "F86",
      "description": "Contact plancher chauffant ouvert",
      "context": "e tubulure\n• Vérifiez les connexions des capteurs de \ntempérature.\nDéfaut contact plancher chauffantF86\nContact plancher chauffant ouvert\nCapteur déconnecté ou défectueux\n• Vérifiez les connexions du"
    },
    {
      "code": "G20",
      "description": "▸ G25G20 ▸ G31G31 ▸ G20",
      "context": "le sens et le nombre de tours \nindiqués dans le tableau ci-après.\nRéglage \nchangement \nde gaz\nModèleG20 ▸ G25G20 ▸ G31G31 ▸ G20\nF251.5 tour2 tours\nF30\n1.5 tour\n3 tours\nF351.5 tour2.5 tours\nF25\n2 tours"
    },
    {
      "code": "G20",
      "description": "▸ G25G20 ▸ G31G31 ▸ G20",
      "context": "z la valeur mesurée avec les valeurs indiquée dans le \ntableau ci-après.\nRéglage changement \nde gaz\nG20 ▸ G25G20 ▸ G31G31 ▸ G20\nCO2 façade ouverte8.8 ± 0.2 %10.1 ± 0.2 %9 ± 0.2 %\nCO2 façade fermée9 ±"
    },
    {
      "code": "O2",
      "description": "façade ouverte8.8 ± 0.2 %10.1 ± 0.2 %9 ± 0.2 %",
      "context": "valeurs indiquée dans le \ntableau ci-après.\nRéglage changement \nde gaz\nG20 ▸ G25G20 ▸ G31G31 ▸ G20\nCO2 façade ouverte8.8 ± 0.2 %10.1 ± 0.2 %9 ± 0.2 %\nCO2 façade fermée9 ± 0.3 %10.3 ± 0.3 %9.2 ± 0.3 %"
    },
    {
      "code": "O2",
      "description": "façade fermée9 ± 0.3 %10.3 ± 0.3 %9.2 ± 0.3 %",
      "context": "changement \nde gaz\nG20 ▸ G25G20 ▸ G31G31 ▸ G20\nCO2 façade ouverte8.8 ± 0.2 %10.1 ± 0.2 %9 ± 0.2 %\nCO2 façade fermée9 ± 0.3 %10.3 ± 0.3 %9.2 ± 0.3 %\n•\tVérifiez le taux de CO dans les produits de combu"
    },
    {
      "code": "O2",
      "description": "change et doit correspondre à celle indiquée dans le tableau ci-",
      "context": "emontez la façade étanche de l’appareil.\nNota : après remontage de la façade étanche, la valeur de CO2 \nchange et doit correspondre à celle indiquée dans le tableau ci-\ndessus.\n1\n\u0015\nLégende\n1    Emplac"
    },
    {
      "code": "O2",
      "description": "dans les produits de combustion et",
      "context": "ent.\n•\tVérifiez la pression du vase d'expansion.\n16.1.2 Autres vérifications\n•\tVérifiez le taux de CO2 dans les produits de combustion et \ncomparez-le avec les valeurs indiquées au chapitre \"Mesure \nd"
    },
    {
      "code": "C13",
      "description": ", C33, C43, C43P, C93, B23P",
      "context": "Saunier Duval\n- 35 -\nDONNÉES TECHNIQUES\nFR\nDONNÉES TECHNIQUES\n18 Données techniques\nChaudière type C13, C33, C43, C43P, C93, B23P\nDescriptionUnitéF 25 F 30F35\nCatégorie gazll\n2Esi3P\nll\n2Esi3P\nll\n2Esi"
    },
    {
      "code": "h400400400",
      "description": "Température départ chauffage min.°C101010",
      "context": "imal (Q min.)kW5.16.18.7\nDébit calorifique maximal (Q max.)kW18.52530.6\nDébit minimum de chauffagel/h400400400\nTempérature départ chauffage min.°C101010\nTempérature départ chauffage max. °C808080\nVase"
    },
    {
      "code": "C808080",
      "description": "Vase d’expansion, capacité utilel888",
      "context": "chauffagel/h400400400\nTempérature départ chauffage min.°C101010\nTempérature départ chauffage max. °C808080\nVase d’expansion, capacité utilel888\nPression de prégonflage du vase d’expansionbar0.750.750"
    },
    {
      "code": "l160160160",
      "description": "Soupape de sécurité, pression maximale de service (PMS)bar333",
      "context": "8\nPression de prégonflage du vase d’expansionbar0.750.750.75\nCapacité maxi. de l’installation à 75°Cl160160160\nSoupape de sécurité, pression maximale de service (PMS)bar333\nSanitaire\nPuissance utile m"
    },
    {
      "code": "C383838",
      "description": "Température eau chaude max.°C606060",
      "context": "min. (Q min.)kW5.16.18.7\nDébit calorifique max. (Q max.)kW25.530.635.7\nTempérature eau chaude min.°C383838\nTempérature eau chaude max.°C606060\nDébit spécifique (D) selon EN 13203l/min12.214.617\nDébit"
    },
    {
      "code": "l333",
      "description": "Limiteur de débit eau froidel/min81010",
      "context": "ire selon EN 13203-*********\nDébit seuil de fonctionnementl/min1.91.91.9\nCapacité micro-accumulationl333\nLimiteur de débit eau froidel/min81010\nSoupape de sécurité, pression maximale de service (PMW)b"
    },
    {
      "code": "r101010",
      "description": "Pression d’alimentation min.bar0.30.30.3",
      "context": "333\nLimiteur de débit eau froidel/min81010\nSoupape de sécurité, pression maximale de service (PMW)bar101010\nPression d’alimentation min.bar0.30.30.3\nPression d’alimentation conseillée (*)bar222\nPressi"
    },
    {
      "code": "r222",
      "description": "Pression d’alimentation max. (**)bar101010",
      "context": "ice (PMW)bar101010\nPression d’alimentation min.bar0.30.30.3\nPression d’alimentation conseillée (*)bar222\nPression d’alimentation max. (**)bar101010\n(*) Réglage conseillé pour le remplissage de l’insta"
    },
    {
      "code": "C10595104",
      "description": "Température des fumées en mode eau chaude sanitaire°C70.76875",
      "context": "°C65.763.472\nTempérature fumées à P max. 50°C/30°C°C48.84455.8\nTempérature des fumées en surchauffe°C10595104\nTempérature des fumées en mode eau chaude sanitaire°C70.76875\nValeurs des produits de la c"
    },
    {
      "code": "W181181181",
      "description": "IntensitéA0.790.790.79",
      "context": "6\nElectrique\nTension d’alimentationV/Hz\n230V \n50Hz\n230V \n50Hz\n230V \n50Hz\nPuissance maximale absorbéeW181181181\nIntensitéA0.790.790.79\nFusibleT 2A/250VT 2A/250VT 2A/250V\nProtection électriqueIPX4DIPX4D"
    },
    {
      "code": "m418418418",
      "description": "Profondeurmm344344344",
      "context": "IPX4DIPX4D\nClasse électriqueIII\nDescriptionUnitéF 25F 30F35\nDimensions :\nHauteurmm740740740\nLargeurmm418418418\nProfondeurmm344344344\nPoids netkg38.43939.6\nNuméro CE\n1312 \nBU 5334\n1312\nBU 5335\n1312\nBV"
    },
    {
      "code": "F35",
      "description": "Gaz naturel G 20 (*)",
      "context": "44\nPoids netkg38.43939.6\nNuméro CE\n1312 \nBU 5334\n1312\nBU 5335\n1312\nBV 5336 \nDescriptionUnitéF 25F 30F35\nGaz naturel G 20 (*)\nDébit gaz à puissance maximale sanitaire\nm\n3\n/h\n2.703.243.77\nDébit gaz à pu"
    },
    {
      "code": "r202020",
      "description": "Gaz naturel G 25 (*)",
      "context": "/h\n1.962.653.24\nDébit gaz à puissance minimale\nm\n3\n/h\n0.540.650.92\nPression d’alimentation en gazmbar202020\nGaz naturel G 25 (*)\nDébit gaz à puissance maximale sanitaire\nm\n3\n/h\n3.143.774.39\nDébit gaz"
    },
    {
      "code": "r252525",
      "description": "Gaz liquide G 31 (*)",
      "context": "/h\n2.283.083.76\nDébit gaz à puissance minimale\nm\n3\n/h\n0.630.751.07\nPression d’alimentation en gazmbar252525\nGaz liquide G 31 (*)\nDébit gaz à puissance maximale sanitairekg/h1.982.382.77\nDébit gaz à pu"
    },
    {
      "code": "r373737",
      "description": "(*) réf. 15°C - 1013 mbar gaz sec",
      "context": "gekg/h1.441.942.37\nDébit gaz à puissance minimalekg/h0.400.470.67\nPression d’alimentation en gaz mbar373737\n(*) réf. 15°C - 1013 mbar gaz sec\n\n\n\n0020130774_02 - 09/12\nSous réserve de modifications tec"
    }
  ],
  "procedures": [
    {
      "title": "Manuel d’installation",
      "steps": [
        "- 1 -",
        "- 2 -"
      ]
    },
    {
      "title": "MAINTENANCE",
      "steps": [
        "- 3 -"
      ]
    },
    {
      "title": "Le manuel fait partie intégrante de l’appareil et doit être remis",
      "steps": [
        "•\tLisez ce manuel attentivement afin de comprendre l’intégralité"
      ]
    },
    {
      "title": "Pendant les périodes de gel, il est possible que de la glace se",
      "steps": [
        "- 4 -"
      ]
    },
    {
      "title": "Cette chaudière est dédiée pour fonctionner uniquement aux G20",
      "steps": [
        "•\tConsultez la plaque signalétique pour connaître le type de gaz"
      ]
    },
    {
      "title": "Gaz réglé en usineChangements de gaz possibles",
      "steps": [
        "•\tPour adapter l'appareil à un autre type de gaz, reportez-vous"
      ]
    },
    {
      "title": "Conseil relative à la basse tension",
      "steps": [
        "- 5 -"
      ]
    },
    {
      "title": "F   Evacuation des condensats",
      "steps": [
        "- 6 -"
      ]
    },
    {
      "title": "Une installation incorrecte peut provoquer un choc",
      "steps": [
        "•\tNe désactivez jamais les dispositifs de sécurité et n’essayez",
        "•\tPrenez impérativement en considération les techniques et",
        "•\tAssurez-vous que les techniques utilisées pour soulever",
        "•\tL’utilisateur ne doit en aucun cas toucher ni régler les",
        "•\tLors des branchements, positionnez correctement les joints",
        "•\tL'appareil contient des pièces métalliques (composants). Elles",
        "•\tRespectez les consignes de sécurité de base avant de procéder à"
      ]
    },
    {
      "title": "Un dispositif de sécurité indépendant de la régulation, avec",
      "steps": [
        "- Systèmes d’évacuation des produits de combustion",
        "- 7 -"
      ]
    },
    {
      "title": "Ce symbole signifie que cet appareil ne doit pas être",
      "steps": [
        "•\tConfiez l’appareil à un point de collecte approprié pour le"
      ]
    },
    {
      "title": "Nous vous conseillons de recycler l’emballage de l’appareil de",
      "steps": [
        "•\tTriez les déchets de manière à séparer ceux qui peuvent être",
        "•\tEliminez ces déchets conformément à la réglementation en",
        "- 8 -"
      ]
    },
    {
      "title": "Toutes les dimensions des illustrations sont exprimées",
      "steps": [
        "•\tAvant de choisir l’emplacement de l’appareil, lisez",
        "•\tVérifiez que la structure du mur sur lequel doit être installé",
        "•\tVérifiez que l’espace dans lequel doit être posé l’appareil",
        "•\tExpliquez ces exigences à l’utilisateur.",
        "•\tN’installez pas l’appareil au-dessus d’un autre appareil",
        "•\tL’emplacement de montage doit être à l’abri du gel toute",
        "•\tPour permettre un entretien périodique, respectez les"
      ]
    },
    {
      "title": "Les colis de ventouse seront commandés en fonction",
      "steps": [
        "•\tVérifiez le contenu des colis.",
        "- 9 -",
        "- Joint plat ½\"(x2)",
        "- Joint plat ¾\" (x5)",
        "- Joint pour arrivée eau foride ¾\" (x4)",
        "- Douille retour chauffage(x1)",
        "- Douille arrivée eau froide(x1)",
        "- Douille départ chauffage(x1)",
        "- Douille eau chaude sanitaire (x1)",
        "- Douille gaz(x1)"
      ]
    },
    {
      "title": "Dans le cas d’utilisation de robinets thermostatiques, il est",
      "steps": [
        "•\tS’il s’agit d’une ancienne installation, il est indispensable de",
        "- 10 -",
        "•\tSi l'appareil n’est pas mis en place immédiatement, protégez",
        "•\tAssurez-vous que les matériaux utilisés pour la réalisation de",
        "•\tDéterminez l’emplacement de montage. Reportez-vous au"
      ]
    },
    {
      "title": "La fixation de la barrette devra être adaptée aux caractéristiques",
      "steps": [
        "•\tPercez les trous des vis de fixation conformément au gabarit",
        "- 11 -",
        "•\tPositionnez l'appareil sur la barrette de fixation.",
        "•\tMettez en place les joints sur les différents raccords.",
        "•\tAvant d’effectuer toute opération, procédez à un nettoyage",
        "•\tN’utilisez pas de produit solvant à cause du risque",
        "•\tNe brasez pas les tubulures montées en place : cette opération",
        "•\tN'utilisez que les joints d'origine fournis avec l'appareil.",
        "•\tVérifiez qu’il n’y a pas de fuite. Réparez si nécessaire."
      ]
    },
    {
      "title": "Le flexible (2) permet de faire les tests d’étanchéité sur le circuit",
      "steps": [
        "•\tRaccordez les soupapes de sécurité et le disconnecteur à un",
        "•\tEmboîtez la rallonge bleue (3) sur le robinet de remplissage (4).",
        "- 12 -"
      ]
    },
    {
      "title": "Ce volume est négligeable comparé au volume d'eaux",
      "steps": [
        "•\tRaccordez le flexible d’évacuation des condensats (2) à un",
        "•\tAssurez-vous que les condensats ne stagnent pas dans le",
        "•\tUtilisez du PVC ou d'autres matériaux adaptés pour évacuer",
        "•\tSi les matériaux du dispositif d'évacuation ne sont pas"
      ]
    },
    {
      "title": "Seuls les accessoires d'évacuation des gaz de",
      "steps": [
        "•\tN’hésitez pas à consulter votre revendeur pour obtenir des",
        "•\tRespectez une pente minimum de 5% entre le coude et"
      ]
    },
    {
      "title": "La longueur maximale de la ventouse est définie en fonction de",
      "steps": [
        "•\tQuel que soit le type de ventouse sélectionné, respectez les",
        "•\tInstallez le conduit d'évacuation des gaz de combustion à",
        "•\tExpliquez ces exigences à l’utilisateur de l’appareil.",
        "- 13 -"
      ]
    },
    {
      "title": "PD’une fenêtre de toit adjacente400",
      "steps": [
        "- 14 -"
      ]
    },
    {
      "title": "Chaque fois qu’un coude à 90° supplémentaire est nécessaire (ou",
      "steps": [
        "- 15 -"
      ]
    },
    {
      "title": "Chaque fois qu’un coude à 90° supplémentaire est nécessaire (ou",
      "steps": [
        "•\tReportez-vous au chapitre \" Réglages spécifiques ▸ Réglages"
      ]
    },
    {
      "title": "Pression sortie de chaudièrePa2980136",
      "steps": [
        "- 16 -"
      ]
    },
    {
      "title": "La prise d’air se fait par le conduit de cheminée (intervalle entre",
      "steps": [
        "- 17 -"
      ]
    },
    {
      "title": "Chaque fois qu’un coude à 90° supplémentaire est nécessaire (ou",
      "steps": [
        "- 18 -"
      ]
    },
    {
      "title": "Des protections supplémentaires peuvent être requises à",
      "steps": [
        "•\tRaccordez le câble d’alimentation de l'appareil au réseau 230",
        "•\tRespectez le raccordement phase et neutre sur l'appareil.",
        "•\tN’utilisez pas du câble supérieur à 10 mm de diamètre pour"
      ]
    },
    {
      "title": "Lorsque vous raccordez des câbles électriques sur un connecteur",
      "steps": [
        "•\tConservez une distance de 30 mm maximum entre le",
        "•\tDans le cas contraire, attachez les fils électriques (2) ensemble",
        "•\tFixez les câbles dans le serre-câbles du boîtier électrique.",
        "- 19 -",
        "- 20 -",
        "•\tAppuyez sur le bouton marche/arrêt pour mettre en service",
        "•\tAssurez-vous que les fonctions sanitaire et chauffage de votre",
        "•\tAssurez-vous que le robinet d'arrivée d'eau froide de",
        "•\tOuvrez les robinets d’arrêt situés sur les raccordements : ils",
        "•\tOuvrez le bouchon du purgeur situé sur la pompe ainsi que les",
        "•\tOuvrez le robinet de remplissage situé sous l'appareil jusqu’à"
      ]
    },
    {
      "title": "Une routine de dégazage se lance automatiquement",
      "steps": [
        "•\tPurgez chaque radiateur jusqu’à écoulement normal de l’eau",
        "•\tLaissez le bouchon du purgeur de la pompe ouvert."
      ]
    },
    {
      "title": "Les deux opérations suivantes permettent de",
      "steps": [
        "•\tRetirez la vis de l'arbre de la pompe et introduisez un tournevis",
        "•\tEntraînez l’arbre de la pompe sur quelques tours, puis",
        "•\tOuvrez les différents robinets d’eau chaude pour remplir le",
        "•\tAmorcez le bouchon (1) du récupérateur de condensats en le",
        "•\tActivez les fonctions sanitaire et chauffage de votre appareil.",
        "•\tFaites fonctionner l’appareil au moins 15 minutes en chauffage",
        "•\tPurgez à nouveau chaque radiateur jusqu’à écoulement",
        "•\tSi vous rencontrez des difficultés de dégazage, lancez les",
        "•\tAssurez-vous que l’indicateur de pression affiche une valeur",
        "- 21 -"
      ]
    },
    {
      "title": "Les débits de gaz dépendent du taux de CO2 et de la vitesse du",
      "steps": [
        "•\tVérifiez le taux de CO2 dans les produits de combustion et",
        "•\tPour connaître les vitesses min. (1) et max. (2) du ventilateur,",
        "•\tRéglez l'appareil sur le mode de test \"P.03 : forçage brûleur à",
        "•\tDès que le mode de forçage du brûleur est activé, appuyez sur",
        "•\tPour vérifier la vitesse max. du ventilateur, reportez-vous au",
        "•\tSi la valeur affichée à l'écran correspond à ± 200 tr/min à la",
        "•\tSi ce n'est pas le cas, contactez le service après-vente.",
        "•\tAppuyer sur la touche RESET  pour quitter le menu de test",
        "•\tActivez le mode de test \"P.01\" et réglez la valeur à \"0\" pour",
        "•\tDès que le mode de forçage du brûleur est activé, appuyez sur",
        "•\tPour vérifier la vitesse min. du ventilateur, reportez-vous au",
        "•\tSi la valeur affichée à l'écran correspond à ± 200 tr/min à la",
        "•\tSi ce n'est pas le cas, contactez le service après-vente.",
        "•\tAppuyer sur la touche RESET  pour quitter le menu de test",
        "•\tAssurez-vous que les organes de régulation externes",
        "•\tAssurez-vous que toutes les vannes thermostatiques des",
        "•\tActivez la fonction chauffage sur le tableau de bord de",
        "•\tÉquilibrez les émetteurs de chaleur si nécessaire.",
        "•\tOuvrez un robinet d'eau chaude.",
        "•\tVérifiez que la température obtenue est conforme au réglage",
        "•\tAssurez-vous que le magnet est placé sur la façade de"
      ]
    },
    {
      "title": "Il est nécessaire d’adapter ce débit en fonction du calcul de",
      "steps": [
        "•\tEn fonction des besoins, effectuez la rotation de cette",
        "- 22 -"
      ]
    },
    {
      "title": "Nota : la diminution de la puissance en chauffage n’a aucune",
      "steps": [
        "•\tAppuyez pendant plus de 7 secondes sur la touche  pour",
        "•\tAppuyez 4 fois sur la touche .",
        "•\tAppuyez sur  pour valider. L’ecran affiche le paramètre",
        "•\tAppuyez sur la touche  ou  du mode  pour accéder au",
        "•\tAppuyez sur la touche  ou  du mode  pour modifier la",
        "•\tRépéter les deux phases précédentes pour chaque paramètre",
        "•\tAppuyez pendant plus de 3 secondes sur la touche  pour",
        "- 23 -"
      ]
    },
    {
      "title": "Afin d’éviter une mise en marche et à l’arrêt fréquentes",
      "steps": [
        "- à 80°C, la durée est fixe (2 minutes)",
        "- à 10°C, la durée est réglable : choisissez une valeur comprise entre"
      ]
    },
    {
      "title": "Reportez-vous à la notice de la sonde extérieure raccordée",
      "steps": [
        "- 24 -"
      ]
    },
    {
      "title": "Cette fonction permet de remettre à zéro la liste des codes défauts",
      "steps": [
        "•\tAppuyez sur la touche  du mode  pendant plus de 3",
        "•\tAppuyez sur la touche  pendant plus de 3 secondes pour"
      ]
    },
    {
      "title": "En activant ces différents modes de test, vous pouvez déclencher",
      "steps": [
        "•\tAppuyez sur le bouton marche/arrêt pour éteindre l'appareil.",
        "•\tTout en maintenant la touche  enfoncée pendant plus de",
        "•\tAppuyez sur la touche  ou  du mode  pour choisir le",
        "- 25 -",
        "•\tMode de test \"P.01\" :",
        "- Appuyez sur  pour afficher le réglage du forçage",
        "- Appuyez sur la touche  ou  du mode  pour modifier",
        "- Appuyez sur  1 seconde pour sortir du sous menu ou",
        "•\tMode de test \"P.02\" à \"P.07\":",
        "- Appuyez sur  pour lancer le mode de test. L’écran",
        "- Le mode de test sera automatiquement arrêté au bout de",
        "•\tLorsque vous avez terminé, appuyer sur RESET  ou faites un"
      ]
    },
    {
      "title": "La fonction est activée pour une durée de 5",
      "steps": [
        "•\tEnlevez tout d’abord la façade étanche.",
        "•\tEnlevez le bouchon (3) puis raccordez un analyseur de CO2 par",
        "•\tActivez le mode de test \"P.01\" et réglez la valeur à 100 pour",
        "•\tAttendez environ 5 minutes pour lire une valeur de CO2",
        "•\tSi la valeur n'est pas correcte, ajustez progressivement le",
        "•\tUne fois que l’appareil est installé, vérifiez son fonctionnement.",
        "•\tMettez l’appareil en fonctionnement pour vous assurer que",
        "•\tEffacez l'historique des codes défauts apparus sur l'appareil."
      ]
    },
    {
      "title": "Pour ce faire, reportez-vous au chapitre \"Réglages à",
      "steps": [
        "•\tVérifiez l'étanchéité de l'appareil (gaz et eau) et éliminez les",
        "•\tVérifiez que les fumées sont évacuées correctement.",
        "•\tContrôlez l'ensemble des dispositif de commande et de"
      ]
    },
    {
      "title": "Au terme de l’installation, l’installateur doit :",
      "steps": [
        "- 26 -"
      ]
    },
    {
      "title": "MAINTENANCE",
      "steps": [
        "•\tAvant de procéder à un diagnostic spécifique, procédez aux"
      ]
    },
    {
      "title": "Ce menu permet d'afficher les 5 derniers codes défauts apparus",
      "steps": [
        "•\tPour afficher l'historique des codes défauts, appuyez",
        "•\tPour afficher les autres défauts apparus sur l'appareil,",
        "•\tAppuyez sur la touche  pendant plus de 3 secondes pour",
        "•\tPour effacer l'historique des codes défauts apparus sur",
        "- 27 -"
      ]
    },
    {
      "title": "Fuite dans l'installation",
      "steps": [
        "• Remplissez l'installation.",
        "• Purgez l'installation.",
        "• Vérifiez les connexions de la pompe.",
        "• Vérifiez les connexions des capteurs départ et retour",
        "• Vérifiez qu'il n'y a pas de fuite."
      ]
    },
    {
      "title": "Electrode d’allumage et de contrôle de flamme",
      "steps": [
        "• Vérifiez le circuit d’arrivée gaz (robinet gaz ouvert).",
        "• Vérifiez le réglage du mécanisme gaz.",
        "• Vérifiez les connexions de l’allumeur.",
        "• Vérifiez l’état de l'électrode (corrosion)."
      ]
    },
    {
      "title": "F32Vitesse du ventilateur incorrecte",
      "steps": [
        "• Vérifiez l’arrivée d’air et l’évacuation des fumées.",
        "• Vérifiez les connections électriques du ventilateur."
      ]
    },
    {
      "title": "F20Sécurité de surchauffe activée (97°C)",
      "steps": [
        "• Vérifiez le fonctionnement de la pompe.",
        "• Vérifiez que les robinets d'arrêt départ et retour"
      ]
    },
    {
      "title": "F00Capteur déconnecté",
      "steps": [
        "• Vérifiez les connexions du capteur.",
        "• Vérifiez les câbles du capteur.",
        "• Vérifiez le capteur."
      ]
    },
    {
      "title": "F73Capteur de pression en court-circuit ou déconnecté",
      "steps": [
        "• Vérifiez les connexions du capteur.",
        "• Vérifiez le capteur."
      ]
    },
    {
      "title": "Capteur de température retour chauffage",
      "steps": [
        "• Vérifiez les connexions du capteur.",
        "• Vérifiez les câbles du capteur.",
        "• Vérifiez le capteur."
      ]
    },
    {
      "title": "Court circuit sur le connecteur EBUS",
      "steps": [
        "• Vérifiez la charge sur la ligne EBUS."
      ]
    },
    {
      "title": "F61Défaut de commande de la vanne gaz",
      "steps": [
        "• Vérifiez l’ensemble des connexions de la carte",
        "• Vérifiez la carte électronique.",
        "• Vérifiez le code produit.",
        "• Faites un reset de l’appareil."
      ]
    },
    {
      "title": "Défaut du moteur du mécanisme",
      "steps": [
        "• Vérifiez les connexions du mécanisme gaz.",
        "• Vérifiez le fonctionnement du mécanisme gaz.",
        "• Vérifiez le fonctionnement de la pompe à"
      ]
    },
    {
      "title": "F27Détection de flamme anormale",
      "steps": [
        "• Vérifiez l’électrode de détection de flamme.",
        "• Vérifiez la carte principale.",
        "• Vérifiez l'allumeur."
      ]
    },
    {
      "title": "Capteur de température départ chauffage déclipsé",
      "steps": [
        "• Vérifiez les connexions du capteur.",
        "• Assurez-vous que le capteur est clipsé sur la"
      ]
    },
    {
      "title": "F70Mauvais code produit",
      "steps": [
        "• Vérifiez que le code produit affiché à l'écran",
        "• Vérifiez la référence de la carte."
      ]
    },
    {
      "title": "Mauvais fonctionnement de la pompe (montée en",
      "steps": [
        "• Vérifiez que les robinets d'arrêt départ et retour",
        "- 28 -"
      ]
    },
    {
      "title": "F23Problème de circulation d’eau",
      "steps": [
        "• Vérifiez la connexion des capteurs départ et retour",
        "• Vérifiez la vitesse de la pompe."
      ]
    },
    {
      "title": "Incohérence entre les températures départ et",
      "steps": [
        "• Vérifiez les connexions des capteurs de",
        "• Remplacez les capteurs défectueux."
      ]
    },
    {
      "title": "Fusible thermique défectueux",
      "steps": [
        "• Vérifiez les connexions du fusible.",
        "• Remplacez le corps de chauffe."
      ]
    },
    {
      "title": "Capteurs de température départ et retour",
      "steps": [
        "• Vérifiez les connexions des capteurs de"
      ]
    },
    {
      "title": "Capteur déconnecté ou défectueux",
      "steps": [
        "• Vérifiez les connexions du capteur.",
        "• Vérifiez que le capteur est connecté sur la carte"
      ]
    },
    {
      "title": "Pour un fonctionnement avec un gaz autre que celui prévu en",
      "steps": [
        "•\tEnlevez tout d’abord la façade étanche.",
        "•\tEnlevez le bouchon (3) puis raccordez un analyseur de CO2 par",
        "•\tAppuyez sur le bouton marche/arrêt pour mettre hors service",
        "•\tTournez la vis en respectant le sens et le nombre de tours"
      ]
    },
    {
      "title": "ModèleG20 ▸ G25G20 ▸ G31G31 ▸ G20",
      "steps": [
        "•\tRéglez l'appareil sur le mode de test \"P.03 : forçage brûleur à",
        "•\tAttendez environ 5 minutes pour lire une valeur de CO2",
        "•\tComparez la valeur mesurée avec les valeurs indiquée dans le"
      ]
    },
    {
      "title": "G20 ▸ G25G20 ▸ G31G31 ▸ G20",
      "steps": [
        "•\tVérifiez le taux de CO dans les produits de combustion et",
        "- 29 -"
      ]
    },
    {
      "title": "MAINTENANCE",
      "steps": [
        "•\tRemettez en place le bouchon du coude de ventouse.",
        "•\tRemontez la façade étanche de l’appareil."
      ]
    },
    {
      "title": "Nota : après remontage de la façade étanche, la valeur de CO2",
      "steps": [
        "•\tCollez l’étiquette de changement de gaz fournie avec l’appareil",
        "•\tEn fonction des étiquettes de changement de gaz, cochez sur",
        "•\tAvant de mettre l’appareil en fonctionnement, suivez les",
        "•\tOuvrez le robinet de vidange (1) situé en dessous de la",
        "•\tFaites une prise d’air en ouvrant, par exemple, un purgeur de",
        "•\tPour vidanger uniquement l’eau du circuit chauffage présente",
        "•\tFermez le robinet d'arrivée d’eau de l’installation.",
        "•\tFaites une prise d’air en ouvrant un robinet d’eau chaude.",
        "•\tReportez-vous au chapitre \"Consignes de sécurité\" pour",
        "•\tUne fois les opérations de maintenance terminées, reportez-",
        "•\tVérifiez que le capteur de débit fonctionne correctement.",
        "•\tVérifiez que le mécanisme gaz module correctement.",
        "•\tVérifiez que les capteurs de température fonctionnent",
        "•\tVérifiez la qualité de l'ionisation.",
        "•\tVérifiez que le fusible thermique assure la protection de",
        "•\tVérifiez que le détecteur de pression fonctionne correctement.",
        "•\tVérifiez la pression du vase d'expansion.",
        "•\tVérifiez le taux de CO2 dans les produits de combustion et",
        "•\tVérifiez qu'il n'y a pas de fuites au niveau des joints, des",
        "•\tVérifiez qu'il n'y a pas de fuites de gaz.",
        "•\tVérifiez l'état du joint du conduit d'évacuation des produits de",
        "•\tVérifiez le raccordement à la terre de l'appareil.",
        "- 30 -"
      ]
    },
    {
      "title": "MAINTENANCE",
      "steps": [
        "•\tNettoyez les composants suivants :"
      ]
    },
    {
      "title": "Les inhibiteurs doivent être compatibles avec les matériaux",
      "steps": [
        "•\tRetirez la façade avant de l'appareil en respectant l’ordre des",
        "•\tRetirez la vis de fixation du silencieux (1).",
        "•\tEnlevez le silencieux (2).",
        "•\tNettoyez l’intérieur du silencieux avec un chiffon sec si",
        "•\tProcédez dans l’ordre inverse des opérations pour remonter le",
        "•\tContrôlez la pression d’alimentation du vase d’expansion (voir",
        "•\tAprès le montage d’un vase d’expansion neuf, remplissez et",
        "- 31 -"
      ]
    },
    {
      "title": "MAINTENANCE",
      "steps": [
        "- 32 -"
      ]
    },
    {
      "title": "MAINTENANCE",
      "steps": [
        "•\tFermez l’alimentation générale en eau froide.",
        "•\tDégagez le clip de fixation du filtre au froide (8).",
        "•\tEnlevez le filtre eau froide (7) et nettoyez-le.",
        "•\tFermez les robinets d’arrêt départ et retour chauffage, puis",
        "•\tDégagez le clip de fixation du filtre (2) placé sous la pompe.",
        "•\tEnlevez le filtre chauffage (3).",
        "•\tNettoyez puis remettez-le en place en positionnant"
      ]
    },
    {
      "title": "Attention : les condensats sont très acides, utilisez",
      "steps": [
        "•\tPositionnez un récipient sous le récupérateur de condensats",
        "•\tEnlevez le bouchon du récupérateur (26).",
        "•\tNettoyez les flexibles et enlevez les débris éventuellement",
        "•\tRemontez l’ensemble en prenant soin de bien positionner le"
      ]
    },
    {
      "title": "Vérifiez que les condensats s'évacuent correctement",
      "steps": [
        "- 33 -"
      ]
    },
    {
      "title": "MAINTENANCE",
      "steps": [
        "- 34 -"
      ]
    },
    {
      "title": "MAINTENANCE",
      "steps": [
        "•\tDémontez le silencieux (reportez-vous au chapitre \"Démontage",
        "•\tDéconnectez le connecteur de l’électrode d’allumage et de",
        "•\tEnlevez la tubulure gaz (16).",
        "•\tRetirez les connecteurs du mécanisme gaz (1) et du ventilateur",
        "•\tDesserrez les 4 écrous (5).",
        "•\tRetirez l’ensemble brûleur du corps de chauffe (10)."
      ]
    },
    {
      "title": "L’isolation de la porte du brûleur sur l’ensemble brûleur ne doit",
      "steps": [
        "•\tNettoyez le serpentin (9) du corps de chauffe (10) avec de"
      ]
    },
    {
      "title": "Le brûleur (12) ne nécessite aucun entretien et n’a pas besoin",
      "steps": [
        "•\tVérifiez que sa surface n’est pas endommagée. Remplacez le",
        "•\tAprès le contrôle ou le remplacement du brûleur, montez"
      ]
    },
    {
      "title": "Attention : A chaque démontage du brûleur, il est",
      "steps": [
        "•\tPlacez l’ensemble brûleur sur le corps de chauffe (10).",
        "•\tSerrez progressivement les 4 écrous (5) dans un ordre croisé.",
        "•\tRemontez le silencieux.",
        "•\tRaccordez la tubulure gaz (16) avec un joint neuf sur",
        "•\tBranchez le connecteur de l’électrode d’allumage et de",
        "•\tBranchez le connecteur du mécanisme gaz (1) et du ventilateur",
        "•\tOuvrez l’arrivée de gaz de l’appareil.",
        "•\tVérifiez l’étanchéité sur le raccord de gaz."
      ]
    },
    {
      "title": "Le câble d'alimentation de l'appareil doit être",
      "steps": [
        "•\tSi le câble d'alimentation est endommagé, remplacez-le en"
      ]
    },
    {
      "title": "Utilisez uniquement des pièces détachées d’origine,",
      "steps": [
        "•\tAssurez-vous que les pièces détachées sont correctement",
        "- 35 -"
      ]
    },
    {
      "title": "Pression d’alimentation conseillée (*)bar222",
      "steps": [
        "- 36 -"
      ]
    }
  ],
  "processed_at": "2025-08-04T23:36:48.920Z"
}